Workbook
Name List_Distributed: _xlfn.ANCHORARRAY('Customer Pricing'!$Z$1)
Name List_Manufactured: _xlfn.ANCHORARRAY('Customer Pricing'!$AA$1)
Name Mfr_Items_Lookup: _xlfn.ANCHORARRAY('Customer Pricing'!$AB$1)
Name Mfr_Prices_Lookup: _xlfn.ANCHORARRAY('Customer Pricing'!$AC$1)

Sheet Cost Master List
A1: Vendor Material | B1: WWI Product Code | C1: Price per kg (unit) | D1: Price per lb | E1: Incoterms | F1: Origin | G1: Vendor | H1: HTS code | I1: Tariff | J1: Freight in per kg | K1: Cert. cost/kg | L1: Landed cost per kg | M1: Landed cost per lb | N1: Margin | O1: Price/kg | P1: Price/lb | Q1: Strength | R1: Minimum | S1: Lead time
A2: Beta Carotene 1% pwd | B2: Natural Yellow G1301 (Nutracean China) | C2: 12 | D2: =C2/2.20462 -> 5.4431149 | E2: CIF NY | F2: China | G2: Nutracean | H2: 3204.18.0000 | I2: 0.381 | J2: 3 | K2: 0 | L2: =(C2*(1+I2))+J2 -> 19.572 | M2: =L2/2.20462 -> 8.8777204 | O2: =L2/(1-N2) -> 19.572 | P2: =O2/2.2 -> 8.8963636
A3: Beta Carotene 1% pwd | B3: Natural Yellow G1301 (Nutracean Slovenia) | C3: 13.4 | D3: =C3/2.20462 -> 6.078145 | E3: FCA | F3: Slovenia | G3: Nutracean | H3: 3204.18.0000 | I3: 0.03 | J3: 3 | K3: 0 | L3: =(C3*(1+I3))+J3 -> 16.802 | M3: =L3/2.20462 -> 7.6212681 | N3: 0.32 | O3: =L3/(1-N3) -> 24.708824 | P3: =O3/2.2 -> 11.231283
A4: Plantcol Annatto B4-SF | B4: Annatto Extract P2404 (Cyber Colors) | C4: 12.95 | D4: =C4/2.20462 -> 5.8740282 | E4: EXW Cork? | F4: Ireland | G4: Cybercolors | H4: 3203.00.1000 | I4: 0.15 | J4: 1.25 | K4: 0 | L4: =(C4*(1+I4))+J4 -> 16.1425 | M4: =L4/2.20462 -> 7.3221235 | N4: 0.3 | O4: =L4/(1-N4) -> 23.060714 | P4: =O4/2.2 -> 10.482143 | T4: Freight is $.85/kg to Chicago
A5: Annatto Extract WS5 | B5: Annatto Extract WS5 (Cyber Colors) | C5: 10.4 | D5: =C5/2.20462 -> 4.7173663 | E5: EXW Cork | F5: Ireland | G5: Cybercolors | H5: 3203.00.1000 | I5: 0.15 | J5: 1.5 | K5: 0 | L5: =(C5*(1+I5))+J5 -> 13.46 | M5: =L5/2.20462 -> 6.1053606
A6: Annatto suspension B8-SF | B6: Annatto Extract P2408 (Cyber Colors) | C6: 20.75 | D6: =C6/2.20462 -> 9.4120529 | E6: EXW Brazil | F6: Brazil | G6: Cybercolors | H6: 3203.00.1000 | I6: 0.5 | J6: 3.14 | K6: 0 | L6: =(C6*(1+I6))+J6 -> 34.265 | M6: =L6/2.20462 -> 15.542361 | N6: 0.32 | O6: =L6/(1-N6) -> 50.389706 | P6: =O6/2.2 -> 22.904412 | R6: 26.50 landed washmo | S6: 8 weeks | T6: Freight estimate given by vendor for 1 x 980kg IBC or 4 x 200kg drum into chicago
A7: Annatto Ext SSH03 | B7: Not Assigned | C7: 7.85 | D7: =C7/2.20462 -> 3.5607043 | E7: EXW Cork | F7: Ireland | G7: Cybercolors | H7: 3203.00.1000 | I7: 0.15 | J7: 4 | K7: 0 | L7: =(C7*(1+I7))+J7 -> 13.0275 | M7: =L7/2.20462 -> 5.9091816 | N7: 0.3 | O7: =L7/(1-N7) -> 18.610714 | P7: =O7/2.2 -> 8.4594156
A8: Chlorophyll AS1 | B8: Natural Green J1410 (Cyber Colors) | C8: 37.75 | D8: =C8/2.20462 -> 17.123132 | E8: CIF Chicago | F8: Ireland | G8: Cybercolors | H8: 3203.00.8000 | I8: 0.031 | J8: 6 | K8: 0 | L8: =(C8*(1+I8))+J8 -> 44.92025 | M8: =L8/2.20462 -> 20.375507 | N8: 0.25 | O8: =L8/(1-N8) -> 59.893667 | P8: =O8/2.2 -> 27.224394
A9: Carmine WSP1 | B9: Natural Red Q2350 (Cyber Colors) | C9: 345 | D9: =C9/2.20462 -> 156.48955 | E9: CIF Chicago | F9: Peru | G9: Cybercolors | H9: 3203.00.8000 | I9: 0.1 | J9: 4 | K9: 0 | L9: =(C9*(1+I9))+J9 -> 383.5 | M9: =L9/2.20462 -> 173.95288 | N9: 0.25 | O9: =L9/(1-N9) -> 511.33333 | P9: =O9/2.2 -> 232.42424
A10: Carmine WS4 | B10: Natural Red Q1304 (Cyber Colors) | C10: 64.64 | D10: =C10/2.20462 -> 29.320246 | E10: EXW Cork | F10: Ireland | G10: Cybercolors | H10: 3205.00.0500 | I10: 0.15 | J10: 1.5 | K10: 0 | L10: =(C10*(1+I10))+J10 -> 75.836 | M10: =L10/2.20462 -> 34.398672 | N10: 0.35 | O10: =L10/(1-N10) -> 116.67077 | P10: =O10/2.2 -> 53.032168
A11: Annatto powder 15% | B11: Annatto Extract P1315 (Imbarex) | C11: 58.5 | D11: =C11/2.20462 -> 26.535185 | E11: CIP Chicago | F11: Peru | G11: Imbarex | H11: 3203.00.1000 | I11: 0.1 | J11: 0.5 | K11: 0 | L11: =(C11*(1+I11))+J11 -> 64.85 | M11: =L11/2.20462 -> 29.4155 | N11: 0.1 | O11: =L11/(1-N11) -> 72.055556 | P11: =O11/2.2 -> 32.752525
A12: Annatto powder 15% | B12: Annatto Extract P1315 (IFF) | C12: 52.3 | D12: =C12/2.20462 -> 23.722909 | E12: EXW Lima | F12: Peru | G12: IFF | H12: 3203.00.1000 | I12: 0.1 | K12: 0 | L12: =(C12*(1+I12))+J12 -> 57.53 | M12: =L12/2.20462 -> 26.0952 | N12: 0.175 | O12: =L12/(1-N12) -> 69.733333 | P12: =O12/2.2 -> 31.69697
A13: FD&C Yellow 5 powder | B13: FD&C Yellow 5 Powder (Vidhi) | C13: 5.3 | D13: =C13/2.20462 -> 2.4040424 | E13: CIF NY | F13: India | G13: Vidhi | H13: 3204.12.5020 | I13: 0.565 | J13: 1.25 | K13: 1 | L13: =(C13*(1+I13))+J13+K13 -> 10.5445 | M13: =L13/2.20462 -> 4.7829104 | N13: 0.3 | O13: =L13/(1-N13) -> 15.063571 | P13: =O13/2.2 -> 6.8470779 | S13: 8 weeks
A14: FD&C Yellow 6 powder | B14: FD&C Yellow 6 Powder (Vidhi) | C14: 4.8 | D14: =C14/2.20462 -> 2.177246 | E14: CIF NY | F14: India | G14: Vidhi | H14: 3204.12.5020 | I14: 0.565 | J14: 1.25 | K14: 1 | L14: =(C14*(1+I14))+J14+K14 -> 9.762 | M14: =L14/2.20462 -> 4.427974 | N14: 0.3 | O14: =L14/(1-N14) -> 13.945714 | P14: =O14/2.2 -> 6.338961 | S14: 8 weeks
A15: FD&C Blue 1 powder | B15: FD&C Blue 1 Powder (Vidhi) | C15: 15.8 | D15: =C15/2.20462 -> 7.166768 | E15: CIF NY | F15: India | G15: Vidhi | H15: 3204.12.5090 | I15: 0.565 | J15: 1.25 | K15: 1 | L15: =(C15*(1+I15))+J15+K15 -> 26.977 | M15: =L15/2.20462 -> 12.236576 | N15: 0.3 | O15: =L15/(1-N15) -> 38.538571 | P15: =O15/2.2 -> 17.517532 | S15: 8 weeks
A16: FD%C Red 40 granular | B16: FD&C Red 40 Granular (Vidhi) | C16: 9.3 | D16: =C16/2.20462 -> 4.2184141 | E16: CIF NY | F16: India | G16: Vidhi | H16: 3204.12.5010 | I16: 0.565 | J16: 1.25 | K16: 1 | L16: =(C16*(1+I16))+J16+K16 -> 16.8045 | M16: =L16/2.20462 -> 7.622402 | N16: 0.3 | O16: =L16/(1-N16) -> 24.006429 | P16: =O16/2.2 -> 10.912013 | S16: 8 weeks
A17: FD&C Red 3 powder | B17: FD&C Red 3 Powder (Vidhi) | C17: 71.2 | D17: =C17/2.20462 -> 32.295815 | E17: CIF NY | F17: India | G17: Vidhi | H17: 3204.16.10 | I17: 0.565 | J17: 1.25 | K17: 1 | L17: =(C17*(1+I17))+J17+K17 -> 113.678 | M17: =L17/2.20462 -> 51.563535 | N17: 0.25 | O17: =L17/(1-N17) -> 151.57067 | P17: =O17/2.2 -> 68.895758 | S17: 8 weeks
A18: FD&C Red 40 HD Lake | B18: FD&C Red 40 HD Lake (Vidhi) | C18: 14.7 | D18: =C18/2.20462 -> 6.6678158 | E18: CIF NY | F18: India | G18: Vidhi | H18: 3205.00.5020 | I18: 0.565 | J18: 1.25 | K18: 1 | L18: =(C18*(1+I18))+J18+K18 -> 25.2555 | M18: =L18/2.20462 -> 11.455716 | N18: 0.3 | O18: =L18/(1-N18) -> 36.079286 | P18: =O18/2.2 -> 16.399675 | S18: 8 weeks
A19: FD&C Blue 1 powder | B19: FD&C Blue 1 Powder (Vivify) | C19: 29 | D19: =C19/2.20462 -> 13.154194 | E19: FCA Glendale Heights, IL | F19: India | G19: Vivify | I19: 0 | J19: 0.75 | K19: 1 | L19: =(C19*(1+I19))+J19+K19 -> 30.75 | M19: =L19/2.20462 -> 13.947982 | N19: 0.25 | O19: =L19/(1-N19) -> 41 | P19: =O19/2.2 -> 18.636364
A20: FD&C Yellow 5 powder | B20: FD&C Yellow 5 Powder (Vivify) | C20: 10.02 | D20: =C20/2.20462 -> 4.545001 | E20: FCA Glendale Heights, IL | F20: India | G20: Vivify | I20: 0 | J20: 0.75 | K20: 1 | L20: =(C20*(1+I20))+J20+K20 -> 11.77 | M20: =L20/2.20462 -> 5.3387885 | N20: 0.3 | O20: =L20/(1-N20) -> 16.814286 | P20: =O20/2.2 -> 7.6428571
A21: Amaranth | B21: Amaranth (Vidhi) | C21: 7.6 | D21: =C21/2.20462 -> 3.4473061 | E21: CIF NY | F21: India | G21: Vidhi | H21: ?? | J21: 1.25 | K21: 0 | L21: =(C21*(1+I21))+J21+K21 -> 8.85 | M21: =L21/2.20462 -> 4.0142972 | N21: 0.3 | O21: =L21/(1-N21) -> 12.642857 | P21: =O21/2.2 -> 5.7467532
A22: Spirulina Extract E18 | B22: Natural Blue L1300 (Hiche) | C22: 80 | D22: =C22/2.20462 -> 36.287433 | E22: FOB Qingdao | F22: China | G22: Qingdao | H22: 3203.00.8000 | I22: 0.381 | J22: 3 | K22: 0 | L22: =(C22*(1+I22))+J22 -> 113.48 | M22: =L22/2.20462 -> 51.473723 | N22: 0.485 | O22: =L22/(1-N22) -> 220.34951 | P22: =O22/2.2 -> 100.15887 | Q22: 200-300
A23: Radish | B23: Radish (Hiche) | C23: 56 | D23: =C23/2.20462 -> 25.401203 | E23: FOB Qingdao | F23: China | G23: Qingdao | H23: 3203.00.8000 | I23: 0.381 | J23: 3 | K23: 0 | L23: =(C23*(1+I23))+J23 -> 80.336 | M23: =L23/2.20462 -> 36.43984 | N23: 0.55 | O23: =L23/(1-N23) -> 178.52444 | P23: =O23/2.2 -> 81.147475 | Q23: 800CV
A24: PSP | B24: Purple Sweet Potato (Hiche) | C24: 95 | D24: =C24/2.20462 -> 43.091326 | E24: FOB Qingdao | F24: China | G24: Qingdao | H24: 3203.00.8000 | I24: 0.381 | J24: 3 | K24: 0 | L24: =(C24*(1+I24))+J24 -> 134.195 | M24: =L24/2.20462 -> 60.8699 | O24: =L24/(1-N24) -> 134.195 | P24: =O24/2.2 -> 60.997727
A25: Butterfly pea | B25: Butterfly Pea (Hiche) | C25: 180 | D25: =C25/2.20462 -> 81.646724 | E25: FOB Qingdao | F25: China | G25: Qingdao | H25: 3203.00.8000 | I25: 0.381 | J25: 3 | K25: 0 | L25: =(C25*(1+I25))+J25 -> 251.58 | M25: =L25/2.20462 -> 114.1149 | O25: =L25/(1-N25) -> 251.58 | P25: =O25/2.2 -> 114.35455 | Q25: 300CV
A26: Beet powder 2.1% | B26: Beet Powder 2.1% (Nutracean) | C26: 35 | D26: =C26/2.20462 -> 15.875752 | E26: CIF NY | F26: China | G26: Nutracean | H26: 3203.00.8000 | I26: 0.381 | J26: 3 | K26: 0 | L26: =(C26*(1+I26))+J26 -> 51.335 | M26: =L26/2.20462 -> 23.285192 | O26: =L26/(1-N26) -> 51.335 | P26: =O26/2.2 -> 23.334091
A27: Beet powder .8% | B27: Beet Powder 0.8% (Nutracean) | C27: 11 | D27: =C27/2.20462 -> 4.989522 | E27: FCA Long Beach | F27: China | G27: Nutracean | H27: 3203.00.8000 | I27: 0.381 | J27: 1 | K27: 0 | L27: =(C27*(1+I27))+J27 -> 16.191 | M27: =L27/2.20462 -> 7.3441228 | N27: 0.145 | O27: =L27/(1-N27) -> 18.936842 | P27: =O27/2.2 -> 8.6076555
A28: Black Carrot EV100 | B28: Black Carrot EV100 (Nutracean) | C28: 120 | D28: =C28/2.20462 -> 54.431149 | E28: FOB China | F28: China | G28: Nutracean | H28: 3203.00.8000 | I28: 0.381 | J28: 2 | L28: =(C28*(1+I28))+J28 -> 167.72 | M28: =L28/2.20462 -> 76.076603
A29: Beet powder .7% | B29: Natural Red D1307 (Seneca) | C29: 17.23 | D29: =C29/2.20462 -> 7.8154058 | E29: FOB Clyman, WI | F29: US | G29: Seneca | H29: n/a | J29: 0.75 | K29: 0 | L29: =(C29*(1+I29))+J29 -> 17.98 | M29: =L29/2.20462 -> 8.1556005 | N29: 0.14 | O29: =L29/(1-N29) -> 20.906977 | P29: =O29/2.2 -> 9.5031712
A30: Beet powder .5% | B30: Natural Red D1305 (Seneca) | C30: 15.55 | D30: =C30/2.20462 -> 7.0533697 | E30: FOB Clyman, WI | F30: US | G30: Seneca | H30: n/a | J30: 0.75 | K30: 0 | L30: =(C30*(1+I30))+J30 -> 16.3 | M30: =L30/2.20462 -> 7.3935644 | N30: 0.2 | O30: =L30/(1-N30) -> 20.375 | P30: =O30/2.2 -> 9.2613636
A31: VeryOx 5% liquid | B31: VeryOx 5% liquid | C31: 21.38 | D31: =C31/2.20462 -> 9.6978164 | E31: EXW Casablanca | F31: Morocco | G31: PhytoProd | H31: 1302.19.9140 | I31: 0.1 | J31: 2 | K31: 0 | L31: =(C31*(1+I31))+J31 -> 25.518 | M31: =L31/2.20462 -> 11.574784 | O31: =L31/(1-N31) -> 25.518 | P31: =O31/2.2 -> 11.599091 | R31: Phytoprod raised prices 8% on 4/14 due to currency exchange rates
A32: VeryOx 5% powder | B32: VeryOx 5% powder | C32: 12.5 | D32: =C32/2.20462 -> 5.6699114 | E32: EXW Casablanca | F32: Morocco | G32: PhytoProd | H32: 1302.19.9140 | I32: 0.1 | J32: 2 | K32: 0 | L32: =(C32*(1+I32))+J32 -> 15.75 | M32: =L32/2.20462 -> 7.1440883 | O32: =L32/(1-N32) -> 15.75 | P32: =O32/2.2 -> 7.1590909
A33: Carnosox 10% liquid | B33: Carnosox 10% liquid | C33: 41.04 | D33: =C33/2.20462 -> 18.615453 | E33: EXW Casablanca | F33: Morocco | G33: PhytoProd | H33: 1302.19.9140 | I33: 0.1 | J33: 2 | K33: 0 | L33: =(C33*(1+I33))+J33 -> 47.144 | M33: =L33/2.20462 -> 21.384184 | N33: 0.3 | O33: =L33/(1-N33) -> 67.348571 | P33: =O33/2.2 -> 30.612987
A34: Carnosox 10% powder | B34: Carnosox 10% powder | C34: 18.36 | D34: =C34/2.20462 -> 8.3279658 | E34: EXW Casablanca | F34: Morocco | G34: PhytoProd | H34: 1302.19.9140 | I34: 0.1 | J34: 2 | K34: 0 | L34: =(C34*(1+I34))+J34 -> 22.196 | M34: =L34/2.20462 -> 10.067948 | O34: =L34/(1-N34) -> 22.196 | P34: =O34/2.2 -> 10.089091
A35: Carnosox PP (High vol price) | B35: Carnosox PP | C35: 13.64 | D35: =C35/2.20462 -> 6.1870073 | E35: CIF Chicago | F35: Morocco | G35: PhytoProd | H35: 1302.19.9140 | I35: 0.1 | J35: 2 | K35: 0 | L35: =(C35*(1+I35))+J35 -> 17.004 | M35: =L35/2.20462 -> 7.7128938 | N35: 0.4 | O35: =L35/(1-N35) -> 28.34 | P35: =O35/2.2 -> 12.881818 | T35: Can go to 14.87/kg for large volume
A36: Carnosic 5% liquid | B36: Carnosic 5% liquid | C36: 15 | D36: =C36/2.20462 -> 6.8038936 | E36: FOB Qingdao | F36: China | G36: Qingdao | H36: 1302.19.9140 | I36: 0.62 | J36: 2 | K36: 0 | L36: =(C36*(1+I36))+J36 -> 26.3 | M36: =L36/2.20462 -> 11.929494 | O36: =L36/(1-N36) -> 26.3 | P36: =O36/2.2 -> 11.954545
A37: Carnosic 15% pwd | B37: Carnosic 15% pwd | C37: 25 | D37: =C37/2.20462 -> 11.339823 | E37: FOB Qingdao | F37: China | G37: Qingdao | H37: 1302.19.9140 | I37: 0.62 | J37: 2 | K37: 0 | L37: =(C37*(1+I37))+J37 -> 42.5 | M37: =L37/2.20462 -> 19.277699 | N37: 0.3 | O37: =L37/(1-N37) -> 60.714286 | P37: =O37/2.2 -> 27.597403
A38: Carnosic 10% liquid | B38: Carnosic 10% liquid | C38: 29 | D38: =C38/2.20462 -> 13.154194 | E38: FOB Qingdao | F38: China | G38: Qingdao | H38: 1302.19.9140 | I38: 0.62 | J38: 2 | K38: 0 | L38: =(C38*(1+I38))+J38 -> 48.98 | M38: =L38/2.20462 -> 22.216981 | O38: =L38/(1-N38) -> 48.98 | P38: =O38/2.2 -> 22.263636
A39: Carnosic 20% pwd | B39: Carnosic 20% pwd | C39: 32 | D39: =C39/2.20462 -> 14.514973 | E39: FOB Qingdao | F39: China | G39: Qingdao | H39: 1302.19.9140 | I39: 0.62 | J39: 2 | K39: 0 | L39: =(C39*(1+I39))+J39 -> 53.84 | M39: =L39/2.20462 -> 24.421442 | O39: =L39/(1-N39) -> 53.84 | P39: =O39/2.2 -> 24.472727
A40: NaCu Chlorophyll 98% | B40: NaCu Chlorophyll 98% (Nutracean) | C40: 180 | D40: =C40/2.20462 -> 81.646724 | E40: FOB China | F40: China | G40: Nutracean | H40: 3203.00.8000 | I40: 0.48 | J40: 3 | K40: 0 | L40: =(C40*(1+I40))+J40 -> 269.4 | M40: =L40/2.20462 -> 122.19793 | O40: =L40/(1-N40) -> 269.4 | P40: =O40/2.2 -> 122.45455 | Q40: 0.98
A41: Titanium Dioxide | B41: Titanium Dioxide (Hiche) | C41: 2.7 | D41: =C41/2.20462 -> 1.2247009 | E41: CIF St. Louis | F41: China | G41: Qingdao | H41: 28230000 | I41: 0.3 | J41: 1 | K41: 0 | L41: =(C41*(1+I41))+J41 -> 4.51 | M41: =L41/2.20462 -> 2.045704 | N41: 0.2 | O41: =L41/(1-N41) -> 5.6375 | P41: =O41/2.2 -> 2.5625
A42: Fungal Beta Carotene 30% suspension | B42: Not Assigned | C42: 150 | D42: =C42/2.20462 -> 68.038936 | E42: FOB China | F42: China | G42: Nutracean | H42: 3204.18.0000 | I42: 0.381 | J42: 4 | K42: 0 | L42: =(C42*(1+I42))+J42 -> 211.15 | M42: =L42/2.20462 -> 95.776143 | N42: 0.25 | O42: =L42/(1-N42) -> 281.53333 | P42: =O42/2.2 -> 127.9697
A43: NI Beta Carotene 30% suspension | B43: Not Assigned | C43: 60 | D43: =C43/2.20462 -> 27.215575 | E43: FOB China | F43: China | G43: Nutracean | H43: 3204.18.0000 | I43: 0.381 | J43: 4 | K43: 0 | L43: =(C43*(1+I43))+J43 -> 86.86 | M43: =L43/2.20462 -> 39.39908 | N43: 0.25 | O43: =L43/(1-N43) -> 115.81333 | P43: =O43/2.2 -> 52.642424
A44: Beta Carotene 22% LF | B44: Natural Yellow G2422 (Nutracean) | C44: 55 | D44: =C44/2.20462 -> 24.94761 | E44: CIF Long Beach | F44: China | G44: Nutracean | H44: 3204.18.0000 | I44: 0.381 | J44: 1 | K44: 0 | L44: =(C44*(1+I44))+J44 -> 76.955 | M44: =L44/2.20462 -> 34.906242 | N44: 0.22 | O44: =L44/(1-N44) -> 98.660256 | P44: =O44/2.2 -> 44.845571
A45: Beta Carotene 22% LF | B45: Natural Yellow G2422 (Black Label) | C45: 85 | D45: =C45/2.20462 -> 38.555397 | E45: FOB NJ | F45: n/a | G45: Black Label | H45: n/a | I45: 0 | J45: 1 | K45: 0 | L45: =(C45*(1+I45))+J45 -> 86 | M45: =L45/2.20462 -> 39.00899 | N45: 0.3 | O45: =L45/(1-N45) -> 122.85714 | P45: =O45/2.2 -> 55.844156
A46: Turmeric liquid 8.5% | B46: Not Assigned | C46: 15.8 | D46: =C46/2.20462 -> 7.166768 | F46: n/a | H46: n/a | K46: 0 | L46: =(C46*(1+I46))+J46 -> 15.8 | M46: =L46/2.20462 -> 7.166768 | O46: =L46/(1-N46) -> 15.8 | P46: =O46/2.2 -> 7.1818182
A47: BS-180 (Class 1 caramel liquid) | B47: Not Assigned | C47: 1.8 | D47: =C47/2.20462 -> 0.81646724 | E47: CIF NY | F47: India | G47: Alvin | H47: 1702.90.9000 | I47: 0.551 | J47: 0.75 | K47: 0 | L47: =(C47*(1+I47))+J47 -> 3.5418 | M47: =L47/2.20462 -> 1.6065354 | N47: 0.2 | O47: =L47/(1-N47) -> 4.42725 | P47: =O47/2.2 -> 2.0123864
A48: BS-2 (Class 1 caramel) | B48: Not Assigned | C48: 1.09 | D48: =C48/2.20462 -> 0.49441627 | E48: CIF NY | F48: India | G48: Alvin | H48: 1702.90.9000 | I48: 0.551 | J48: 0.75 | K48: 0 | L48: =(C48*(1+I48))+J48 -> 2.44059 | M48: =L48/2.20462 -> 1.1070343 | N48: 0.3 | O48: =L48/(1-N48) -> 3.4865571 | P48: =O48/2.2 -> 1.5847987 | T48: Sethness list $1.57-$1.67/lb
A49: Caramel liquid E150d (Class 4 liquid) | B49: Caramel Color R1410 (Alvin) | C49: 1 | D49: =C49/2.20462 -> 0.45359291 | E49: CIF NY | F49: India | G49: Alvin | H49: 1702.90.9000 | I49: 0.55 | J49: 0.75 | K49: 0 | L49: =(C49*(1+I49))+J49 -> 2.3 | M49: =L49/2.20462 -> 1.0432637 | N49: 0.3 | O49: =L49/(1-N49) -> 3.2857143 | P49: =O49/2.2 -> 1.4935065 | T49: Sethness list $1.09/lb in drums
A50: Curcumin 8.5% WS Liquid | B50: Natural Yellow H1485 (Maak) | C50: 12.8 | D50: =C50/2.20462 -> 5.8059892 | E50: EXW Kerala | F50: India | G50: Maak Naturals | H50: 3203.00.8000 | I50: 0.031 | J50: 4 | K50: 0 | L50: =(C50*(1+I50))+J50 -> 17.1968 | M50: =L50/2.20462 -> 7.8003465 | N50: 0.3 | O50: =L50/(1-N50) -> 24.566857 | P50: =O50/2.2 -> 11.166753
A51: Turmeric 8.5% liquid | B51: Natural Yellow H1485 (Synthite) | C51: 9.3 | D51: =C51/2.20462 -> 4.2184141 | E51: EXW Tinley Park, IL | F51: India | G51: Synthite | H51: 3203.00.8000 | I51: 0 | J51: 1 | L51: =(C51*(1+I51))+J51 -> 10.3 | M51: =L51/2.20462 -> 4.672007
A52: Curcumin 95% | B52: Natural Yellow H2395 (Maak) | C52: 87.7 | D52: =C52/2.20462 -> 39.780098 | E52: EXW Kerala | F52: India | G52: Maak Naturals | H52: 3203.00.8000 | I52: 0.031 | J52: 4 | K52: 0 | L52: =(C52*(1+I52))+J52 -> 94.4187 | M52: =L52/2.20462 -> 42.827653 | N52: 0.4 | O52: =L52/(1-N52) -> 157.3645 | P52: =O52/2.2 -> 71.529318
A53: Turmeric Vextrano Encapsulated | B53: Natural Yellow H1385 (Synthite) | C53: 20.5 | D53: =C53/2.20462 -> 9.2986546 | E53: EXW Tinley Park, IL | F53: India | G53: Synthite | H53: 3203.00.8000 | I53: 0.031 | J53: 3 | L53: =(C53*(1+I53))+J53 -> 24.1355 | M53: =L53/2.20462 -> 10.947692
A54: Curcumin 8.5% WD Powder | B54: Natural Yellow H1385 (Maak) | C54: 12.7 | D54: =C54/2.20462 -> 5.7606299 | E54: EXW Kerala | F54: India | G54: Maak Naturals | H54: 3203.00.8000 | I54: 0.031 | J54: 4 | K54: 0 | L54: =(C54*(1+I54))+J54 -> 17.0937 | M54: =L54/2.20462 -> 7.7535811 | N54: 0.5 | O54: =L54/(1-N54) -> 34.1874 | P54: =O54/2.2 -> 15.539727
A55: Grape Skin ext 12, Art. No. DEP000130 | B55: Natural Red O1312 (AroMoss) | C55: 31.5 | D55: =C55/2.20462 -> 14.288177 | E55: EXW Mahlberg | F55: Germany | G55: AroMoss | I55: 0.15 | J55: 1.5 | K55: 0 | L55: =(C55*(1+I55))+J55 -> 37.725 | M55: =L55/2.20462 -> 17.111793 | N55: 0.3 | O55: =L55/(1-N55) -> 53.892857 | P55: =O55/2.2 -> 24.496753
A56: SPP000163 | B56: Natural Orange F1333 (AroMoss) | C56: 36.45 | D56: =C56/2.20462 -> 16.533462 | E56: EXW Mahlberg | F56: Germany | G56: AroMoss | I56: 0.15 | J56: 1.5 | K56: 0 | L56: =(C56*(1+I56))+J56 -> 43.4175 | M56: =L56/2.20462 -> 19.69387 | N56: 0.3 | O56: =L56/(1-N56) -> 62.025 | P56: =O56/2.2 -> 28.193182
A57: Milled beet***** | B57: Not Assigned | C57: 21 | D57: =C57/2.20462 -> 9.5254511 | I57: 0.48 | K57: 0 | L57: =(C57*(1+I57))+J57 -> 31.08 | M57: =L57/2.20462 -> 14.097668 | N57: 0 | O57: =L57/(1-N57) -> 31.08 | P57: =O57/2.2 -> 14.127273
A58: Red Radish EV50 | B58: Red Radish EV50 (Nutracean) | C58: 80 | D58: =C58/2.20462 -> 36.287433 | E58: FOB China | F58: China | G58: Nutracean | H58: 3203.00.8000 | I58: 0.381 | J58: 2 | K58: 0 | L58: =(C58*(1+I58))+J58 -> 112.48 | M58: =L58/2.20462 -> 51.02013 | N58: 0 | O58: =L58/(1-N58) -> 112.48 | P58: =O58/2.2 -> 51.127273
A59: Maltodextrin M-100 IP | B59: Maltodextrin M-100 IP (Brenntag) | C59: 1.85 | D59: =C59/2.20462 -> 0.83914688 | E59: DAP | F59: USA | G59: Brenntag | J59: 0 | K59: 0 | L59: =(C59*(1+I59))+J59 -> 1.85 | M59: =L59/2.20462 -> 0.83914688 | N59: 0 | O59: =L59/(1-N59) -> 1.85 | P59: =O59/2.2 -> 0.84090909
A60: Fine Flour Salt | B60: Fine Flour Salt (Brenntag) | C60: 0.99 | D60: =C60/2.20462 -> 0.44905698 | E60: DAP | F60: USA | G60: Brenntag | J60: 0 | K60: 0 | L60: =(C60*(1+I60))+J60 -> 0.99 | M60: =L60/2.20462 -> 0.44905698 | N60: 0 | O60: =L60/(1-N60) -> 0.99 | P60: =O60/2.2 -> 0.45
A61: Sun Flower Oil | B61: Sun Flower Oil (Columbus Oils) | C61: 2.6125 | D61: =C61/2.20462 -> 1.1850115 | J61: 0 | K61: 0 | L61: =(C61*(1+I61))+J61 -> 2.6125 | M61: =L61/2.20462 -> 1.1850115 | N61: 0 | O61: =L61/(1-N61) -> 2.6125 | P61: =O61/2.2 -> 1.1875
A62: DI Water | B62: DI Water | C62: 0.5 | D62: =C62/2.20462 -> 0.22679645 | J62: 0 | K62: 0 | L62: =(C62*(1+I62))+J62 -> 0.5 | M62: =L62/2.20462 -> 0.22679645 | O62: =L62/(1-N62) -> 0.5 | P62: =O62/2.2 -> 0.22727273
A63: Citric Acid | B63: Citric Acid* | C63: 10 | D63: =C63/2.20462 -> 4.5359291 | K63: 0 | L63: =(C63*(1+I63))+J63 -> 10 | M63: =L63/2.20462 -> 4.5359291 | O63: =L63/(1-N63) -> 10 | P63: =O63/2.2 -> 4.5454545
A64: Propelyene Glycol | B64: Propelyene Glycol* | C64: 10 | D64: =C64/2.20462 -> 4.5359291 | K64: 0 | L64: =(C64*(1+I64))+J64 -> 10 | M64: =L64/2.20462 -> 4.5359291 | O64: =L64/(1-N64) -> 10 | P64: =O64/2.2 -> 4.5454545
A65: Sorbitol | B65: Sorbitol* | C65: 4 | D65: =C65/2.20462 -> 1.8143716 | L65: =(C65*(1+I65))+J65 -> 4 | M65: =L65/2.20462 -> 1.8143716 | O65: =L65/(1-N65) -> 4 | P65: =O65/2.2 -> 1.8181818
A66: Glycerin | B66: Glycerin* | C66: 10 | D66: =C66/2.20462 -> 4.5359291 | K66: 0 | L66: =(C66*(1+I66))+J66 -> 10 | M66: =L66/2.20462 -> 4.5359291 | O66: =L66/(1-N66) -> 10 | P66: =O66/2.2 -> 4.5454545
A67: Tocobiol SF | B67: Tocobiol SF (BTSA) | C67: 38.8 | D67: =C67/2.20462 -> 17.599405 | E67: EXW Madrid | F67: Spain | I67: 0 | J67: 4 | K67: 0 | L67: =(C67*(1+I67))+J67 -> 42.8 | M67: =L67/2.20462 -> 19.413777 | N67: 0.22 | O67: =L67/(1-N67) -> 54.871795 | P67: =O67/2.2 -> 24.941725
A68: VJfC Bcarrot/BIB | B68: VJfC Bcarrot/BIB (Dohler) | C68: 42.57 | D68: =C68/2.20462 -> 19.30945 | E68: DAP Washington | G68: Doehler | H68: 3203.00.8000 | I68: 0.031 | J68: 2 | K68: 0 | L68: =(C68*(1+I68))+J68 -> 45.88967 | M68: =L68/2.20462 -> 20.815229 | O68: =L68/(1-N68) -> 45.88967 | P68: =O68/2.2 -> 20.858941
A69: Natural Carotene FP100 | B69: Natural Yellow G1301-N (Cybercolors) | C69: 28.27 | D69: =C69/2.20462 -> 12.823072 | E69: EXW Ireland | F69: Ireland | G69: Cybercolors | H69: 3204.18.0000 | I69: 0.031 | J69: 4 | K69: 0 | L69: =(C69*(1+I69))+J69 -> 33.14637 | M69: =L69/2.20462 -> 15.034958 | N69: 0.3 | O69: =L69/(1-N69) -> 47.351957 | P69: =O69/2.2 -> 21.523617
A70: Red Cabbage E60 | B70: Red Cabbage E60 (Nutracean) | C70: 128 | D70: =C70/2.20462 -> 58.059892 | E70: FOB China | F70: China | G70: Nutracean | H70: 3203.00.8000 | I70: 0.381 | J70: 3 | K70: 0 | L70: =(C70*(1+I70))+J70 -> 179.768 | M70: =L70/2.20462 -> 81.54149 | O70: =L70/(1-N70) -> 179.768 | P70: =O70/2.2 -> 81.712727
A71: Carmine Extract WS3 | B71: Natural Red Q1404 (Cybercolors) | C71: 43.25 | D71: =C71/2.20462 -> 19.617893 | E71: CIF Chicago | F71: Ireland | G71: Cybercolors | H71: 3205.00.0500 | I71: 0.15 | J71: 1 | K71: 0 | L71: =(C71*(1+I71))+J71 -> 50.7375 | M71: =L71/2.20462 -> 23.01417 | N71: 0.3 | O71: =L71/(1-N71) -> 72.482143 | P71: =O71/2.2 -> 32.946429
A72: Beta Carotene WS5 | B72: Natural Yellow G3403 (Cybercolors) | C72: 31.97 | D72: =C72/2.20462 -> 14.501365 | E72: EXW Cork | F72: Ireland | G72: Cybercolors | H72: 3204.18.0000 | I72: 0.031 | J72: 1 | K72: 0 | L72: =(C72*(1+I72))+J72 -> 33.96107 | M72: =L72/2.20462 -> 15.404501 | N72: 0 | O72: =L72/(1-N72) -> 33.96107 | P72: =O72/2.2 -> 15.43685
A73: Ascorbic Acid 162028 | B73: Ascorbic Acid (Brenntag) | C73: 3.98 | D73: =C73/2.20462 -> 1.8052998 | K73: 1 | L73: =(C73*(1+I73))+J73 -> 3.98 | M73: =L73/2.20462 -> 1.8052998 | O73: =L73/(1-N73) -> 3.98 | P73: =O73/2.2 -> 1.8090909
A74: Potassium Sorbate | B74: Potassium Sorbate (Brenntag) | C74: 4.45 | D74: =C74/2.20462 -> 2.0184884 | K74: 0 | L74: =(C74*(1+I74))+J74 -> 4.45 | M74: =L74/2.20462 -> 2.0184884 | N74: 0 | O74: =L74/(1-N74) -> 4.45 | P74: =O74/2.2 -> 2.0227273
D75: =C75/2.20462 -> 0 | K75: 0 | L75: =(C75*(1+I75))+J75 -> 0 | M75: =L75/2.20462 -> 0 | O75: =L75/(1-N75) -> 0 | P75: =O75/2.2 -> 0
D76: =C76/2.20462 -> 0 | K76: 0 | L76: =(C76*(1+I76))+J76 -> 0 | M76: =L76/2.20462 -> 0 | O76: =L76/(1-N76) -> 0 | P76: =O76/2.2 -> 0
O77: =L77/(1-N77) -> 0 | P77: =O77/2.2 -> 0
A83: Packaging
A84: 12x12x16 box | B84: 12x12x16 box | C84: 1.92 | E84: FOB Wisconsin | F84: USA | G84: Uline | J84: 0.5 | L84: =(C84*(1+I84))+J84 -> 2.42
A85: 15x15x15 box | B85: 15x15x15 box | C85: 1.97 | E85: FOB Wisconsin | F85: USA | G85: Uline | J85: 0.5 | L85: =(C85*(1+I85))+J85 -> 2.47
A86: 16x12x10 box | B86: 16x12x10 box | C86: 1.42 | E86: FOB Wisconsin | F86: USA | G86: Uline | J86: 0.5 | L86: =(C86*(1+I86))+J86 -> 1.92
A87: 30 Gal Fiber Drums | B87: 30 Gal Fiber Drums | C87: 58 | E87: FOB Wisconsin | F87: USA | G87: Uline | J87: 0.5 | L87: =(C87*(1+I87))+J87 -> 58.5
A88: Blue USFDA Poly Bag 32x32x.004 | B88: Blue USFDA Poly Bag 32x32x.004 | C88: 0.553 | E88: DAP | F88: USA | G88: TriCor | J88: 0 | L88: =(C88*(1+I88))+J88 -> 0.553
A89: Blue USFDA Poly Bag 34x40x.004 | B89: Blue USFDA Poly Bag 34x40x.004 | C89: 0.678 | E89: DAP | F89: USA | G89: TriCor | J89: 0 | L89: =(C89*(1+I89))+J89 -> 0.678
A90: 1 Gallon Jug & Box Combo | B90: 1 Gallon Jug & Box Combo | C90: =1.49+0.11 -> 1.6 | G90: CL Smith | J90: 0 | L90: =(C90*(1+I90))+J90 -> 1.6
A91: 5 Gallon Pails | B91: 5 Gallon Pails | C91: =7.75+1.93 -> 9.68 | G91: CL Smith | J91: 0 | L91: =(C91*(1+I91))+J91 -> 9.68
A92: Mystery Box for Beet | B92: Mystery Box for Beet* | L92: =(C92*(1+I92))+J92 -> 0
A93: 55 gal steel open head drums | C93: 175 | E93: FOB Wisconsin | F93: USA | G93: Uline | L93: =(C93*(1+I93))+J93 -> 175
L94: =(C94*(1+I94))+J94 -> 0
L95: =(C95*(1+I95))+J95 -> 0
L96: =(C96*(1+I96))+J96 -> 0
L97: =(C97*(1+I97))+J97 -> 0
L98: =(C98*(1+I98))+J98 -> 0

Sheet Manufactured Items Models
A1: Annatto | G1: Beet | M1: Butterfly Pea | S1: Purple Sweet Potato | Y1: Radish | AE1: Spirulina | AK1: Black Carrot | AQ1: Red Cabbage | AW1: Beta Carotene
A2: 8 | B2: Annatto Extract P2401 | C2: Composition | D2: Price/lb | E2: Formula Cost | G2: 40 | H2: Natural Red D1303 | I2: Composition | J2: Price/lb | K2: Formula Cost | M2: 11 | N2: Natural BP N1399 | O2: Composition | P2: Price/lb | Q2: Formula Cost | S2: 44 | T2: Natural Red A1320 | U2: Composition | V2: Price/lb | W2: Formula Cost | Y2: 44 | Z2: Natural Red E1430 | AA2: Composition | AB2: Price/lb | AC2: Formula Cost | AE2: 11 | AF2: Natural Blue L1355 | AG2: Composition | AH2: Price/lb | AI2: Formula Cost | AK2: 8 | AL2: Natural Red C1409 | AM2: Composition | AN2: Price/lb | AO2: Formula Cost | AQ2: 8 | AR2: Natural Red B1416 | AS2: Composition | AT2: Price/lb | AU2: Formula Cost | AW2: 44 | AX2: Natural Yellow G3401-N | AY2: Composition | AZ2: Price/lb | BA2: Formula Cost
A3: R1 | B3: Annatto Extract P2404 (Cyber Colors) | C3: 0.05 | D3: =IFERROR(VLOOKUP(B3,'Cost Master List'!$B$2:$P$74,12,),0) -> 7.3221235 | E3: =+D3*C3 -> 0.36610618 | G3: R1 | H3: Beet Powder 0.8% (Nutracean) | I3: 0.375 | J3: =IFERROR(VLOOKUP(H3,'Cost Master List'!$B$2:$P$74,12,),0) -> 7.3441228 | K3: =+J3*I3 -> 2.754046 | M3: R1 | N3: Butterfly Pea (Hiche) | O3: 0.33 | P3: =IFERROR(VLOOKUP(N3,'Cost Master List'!$B$2:$P$74,12,),0) -> 114.1149 | Q3: =+P3*O3 -> 37.657918 | S3: R1 | T3: Purple Sweet Potato (Hiche) | U3: 0.25 | V3: =IFERROR(VLOOKUP(T3,'Cost Master List'!$B$2:$P$74,12,),0) -> 60.8699 | W3: =+V3*U3 -> 15.217475 | Y3: R1 | Z3: Red Radish EV50 (Nutracean) | AA3: 0.06 | AB3: =IFERROR(VLOOKUP(Z3,'Cost Master List'!$B$2:$P$74,12,),0) -> 51.02013 | AC3: =+AB3*AA3 -> 3.0612078 | AE3: R1 | AF3: Natural Blue L1300 (Hiche) | AG3: 0.317 | AH3: =IFERROR(VLOOKUP(AF3,'Cost Master List'!$B$2:$P$74,12,),0) -> 51.473723 | AI3: =+AH3*AG3 -> 16.31717 | AK3: R1 | AL3: VJfC Bcarrot/BIB (Dohler) | AM3: 0.275 | AN3: =IFERROR(VLOOKUP(AL3,'Cost Master List'!$B$2:$P$74,12,),0) -> 20.815229 | AO3: =+AN3*AM3 -> 5.724188 | AQ3: R1 | AR3: Red Cabbage E60 (Nutracean) | AS3: 0.243 | AT3: =IFERROR(VLOOKUP(AR3,'Cost Master List'!$B$2:$P$74,12,),0) -> 81.54149 | AU3: =+AT3*AS3 -> 19.814582 | AW3: R1 | AX3: Natural Yellow G3403 (Cybercolors) | AY3: 0.215 | AZ3: =IFERROR(VLOOKUP(AX3,'Cost Master List'!$B$2:$P$74,12,),0) -> 15.404501 | BA3: =+AZ3*AY3 -> 3.3119676
A4: R2 | B4: Sun Flower Oil* | C4: 0.95 | D4: =IFERROR(VLOOKUP(B4,'Cost Master List'!$B$2:$P$74,12,),0) -> 1.1850115 | E4: =+D4*C4 -> 1.1257609 | G4: R2 | H4: Maltodextrin M-100 IP (Brenntag) | I4: 0.63 | J4: =IFERROR(VLOOKUP(H4,'Cost Master List'!$B$2:$P$74,12,),0) -> 0.83914688 | K4: =+J4*I4 -> 0.52866254 | M4: R2 | N4: Maltodextrin M-100 IP (Brenntag) | O4: 0.67 | P4: =IFERROR(VLOOKUP(N4,'Cost Master List'!$B$2:$P$74,12,),0) -> 0.83914688 | Q4: =+P4*O4 -> 0.56222841 | S4: R2 | T4: Maltodextrin M-100 IP (Brenntag) | U4: 0.75 | V4: =IFERROR(VLOOKUP(T4,'Cost Master List'!$B$2:$P$74,12,),0) -> 0.83914688 | W4: =+V4*U4 -> 0.62936016 | Y4: R2 | Z4: Citric Acid* | AA4: 0.005 | AB4: =IFERROR(VLOOKUP(Z4,'Cost Master List'!$B$2:$P$74,12,),0) -> 4.5359291 | AC4: =+AB4*AA4 -> 0.022679645 | AE4: R2 | AF4: Maltodextrin M-100 IP (Brenntag) | AG4: 0.683 | AH4: =IFERROR(VLOOKUP(AF4,'Cost Master List'!$B$2:$P$74,12,),0) -> 0.83914688 | AI4: =+AH4*AG4 -> 0.57313732 | AK4: R2 | AL4: DI Water | AM4: 0.1008 | AN4: =IFERROR(VLOOKUP(AL4,'Cost Master List'!$B$2:$P$74,12,),0) -> 0.22679645 | AO4: =+AN4*AM4 -> 0.022861083 | AQ4: R2 | AR4: Propelyene Glycol* | AS4: 0.2 | AT4: =IFERROR(VLOOKUP(AR4,'Cost Master List'!$B$2:$P$74,12,),0) -> 4.5359291 | AU4: =+AT4*AS4 -> 0.90718582 | AW4: R2 | AX4: DI Water | AY4: 0.771 | AZ4: =IFERROR(VLOOKUP(AX4,'Cost Master List'!$B$2:$P$74,12,),0) -> 0.22679645 | BA4: =+AZ4*AY4 -> 0.17486007
A5: R3 | D5: =IFERROR(VLOOKUP(B5,'Cost Master List'!$B$2:$P$74,12,),0) -> 0 | E5: =+D5*C5 -> 0 | G5: R3 | J5: =IFERROR(VLOOKUP(H5,'Cost Master List'!$B$2:$P$74,12,),0) -> 0 | K5: =+J5*I5 -> 0 | M5: R3 | P5: =IFERROR(VLOOKUP(N5,'Cost Master List'!$B$2:$P$74,12,),0) -> 0 | Q5: =+P5*O5 -> 0 | S5: R3 | V5: =IFERROR(VLOOKUP(T5,'Cost Master List'!$B$2:$P$74,12,),0) -> 0 | W5: =+V5*U5 -> 0 | Y5: R3 | Z5: Propelyene Glycol* | AA5: 0.2047 | AB5: =IFERROR(VLOOKUP(Z5,'Cost Master List'!$B$2:$P$74,12,),0) -> 4.5359291 | AC5: =+AB5*AA5 -> 0.92850469 | AE5: R3 | AH5: =IFERROR(VLOOKUP(AF5,'Cost Master List'!$B$2:$P$74,12,),0) -> 0 | AI5: =+AH5*AG5 -> 0 | AK5: R3 | AL5: Citric Acid* | AM5: 0.003 | AN5: =IFERROR(VLOOKUP(AL5,'Cost Master List'!$B$2:$P$74,12,),0) -> 4.5359291 | AO5: =+AN5*AM5 -> 0.013607787 | AQ5: R3 | AR5: DI Water | AS5: 0.553 | AT5: =IFERROR(VLOOKUP(AR5,'Cost Master List'!$B$2:$P$74,12,),0) -> 0.22679645 | AU5: =+AT5*AS5 -> 0.12541844 | AW5: R3 | AX5: Potassium Sorbate (Brenntag) | AY5: 0.0013 | AZ5: =IFERROR(VLOOKUP(AX5,'Cost Master List'!$B$2:$P$74,12,),0) -> 2.0184884 | BA5: =+AZ5*AY5 -> 0.002624035
A6: R4 | D6: =IFERROR(VLOOKUP(B6,'Cost Master List'!$B$2:$P$74,12,),0) -> 0 | E6: =+D6*C6 -> 0 | G6: R4 | J6: =IFERROR(VLOOKUP(H6,'Cost Master List'!$B$2:$P$74,12,),0) -> 0 | K6: =+J6*I6 -> 0 | M6: R4 | P6: =IFERROR(VLOOKUP(N6,'Cost Master List'!$B$2:$P$74,12,),0) -> 0 | Q6: =+P6*O6 -> 0 | S6: R4 | V6: =IFERROR(VLOOKUP(T6,'Cost Master List'!$B$2:$P$74,12,),0) -> 0 | W6: =+V6*U6 -> 0 | Y6: R4 | Z6: DI Water | AA6: 0.7303 | AB6: =IFERROR(VLOOKUP(Z6,'Cost Master List'!$B$2:$P$74,12,),0) -> 0.22679645 | AC6: =+AB6*AA6 -> 0.16562945 | AE6: R4 | AH6: =IFERROR(VLOOKUP(AF6,'Cost Master List'!$B$2:$P$74,12,),0) -> 0 | AI6: =+AH6*AG6 -> 0 | AK6: R4 | AL6: Potassium Sorbate (Brenntag) | AM6: 0.002 | AN6: =IFERROR(VLOOKUP(AL6,'Cost Master List'!$B$2:$P$74,12,),0) -> 2.0184884 | AO6: =+AN6*AM6 -> 0.0040369769 | AQ6: R4 | AR6: Citric Acid* | AS6: 0.004 | AT6: =IFERROR(VLOOKUP(AR6,'Cost Master List'!$B$2:$P$74,12,),0) -> 4.5359291 | AU6: =+AT6*AS6 -> 0.018143716 | AW6: R4 | AX6: Ascorbic Acid (Brenntag) | AY6: 0.01 | AZ6: =IFERROR(VLOOKUP(AX6,'Cost Master List'!$B$2:$P$74,12,),0) -> 1.8052998 | BA6: =+AZ6*AY6 -> 0.018052998
A7: R5 | D7: =IFERROR(VLOOKUP(B7,'Cost Master List'!$B$2:$P$74,12,),0) -> 0 | E7: =+D7*C7 -> 0 | G7: R5 | J7: =IFERROR(VLOOKUP(H7,'Cost Master List'!$B$2:$P$74,12,),0) -> 0 | K7: =+J7*I7 -> 0 | M7: R5 | P7: =IFERROR(VLOOKUP(N7,'Cost Master List'!$B$2:$P$74,12,),0) -> 0 | Q7: =+P7*O7 -> 0 | S7: R5 | V7: =IFERROR(VLOOKUP(T7,'Cost Master List'!$B$2:$P$74,12,),0) -> 0 | W7: =+V7*U7 -> 0 | Y7: R5 | AB7: =IFERROR(VLOOKUP(Z7,'Cost Master List'!$B$2:$P$74,12,),0) -> 0 | AC7: =+AB7*AA7 -> 0 | AE7: R5 | AH7: =IFERROR(VLOOKUP(AF7,'Cost Master List'!$B$2:$P$74,12,),0) -> 0 | AI7: =+AH7*AG7 -> 0 | AK7: R5 | AL7: Sorbitol* | AM7: 0.6192 | AN7: =IFERROR(VLOOKUP(AL7,'Cost Master List'!$B$2:$P$74,12,),0) -> 1.8143716 | AO7: =+AN7*AM7 -> 1.1234589 | AQ7: R5 | AT7: =IFERROR(VLOOKUP(AR7,'Cost Master List'!$B$2:$P$74,12,),0) -> 0 | AU7: =+AT7*AS7 -> 0 | AW7: R5 | AZ7: =IFERROR(VLOOKUP(AX7,'Cost Master List'!$B$2:$P$74,12,),0) -> 0 | BA7: =+AZ7*AY7 -> 0
A8: P1 | B8: 1 Gallon Jug & Box Combo | D8: =IFERROR(VLOOKUP('Manufactured Items Models'!B8,'Cost Master List'!$B$84:$L$98,11,FALSE),0) -> 1.6 | E8: =+D8/$A$2 -> 0.2 | G8: P1 | H8: 15x15x15 box | J8: =IFERROR(VLOOKUP('Manufactured Items Models'!H8,'Cost Master List'!$B$84:$L$98,11,FALSE),0) -> 2.47 | K8: =+J8/$G$2 -> 0.06175 | M8: P1 | N8: 16x12x10 box | P8: =IFERROR(VLOOKUP('Manufactured Items Models'!N8,'Cost Master List'!$B$84:$L$98,11,FALSE),0) -> 1.92 | Q8: =+P8/$M$2 -> 0.17454545 | S8: P1 | T8: 15x15x15 box | V8: =IFERROR(VLOOKUP('Manufactured Items Models'!T8,'Cost Master List'!$B$84:$L$98,11,FALSE),0) -> 2.47 | W8: =+V8/$S$2 -> 0.056136364 | Y8: P1 | Z8: 5 Gallon Pails | AB8: =IFERROR(VLOOKUP('Manufactured Items Models'!Z8,'Cost Master List'!$B$84:$L$98,11,FALSE),0) -> 9.68 | AC8: =+AB8/$Y$2 -> 0.22 | AE8: P1 | AF8: 16x12x10 box | AH8: =IFERROR(VLOOKUP('Manufactured Items Models'!AF8,'Cost Master List'!$B$84:$L$98,11,FALSE),0) -> 1.92 | AI8: =+AH8/$AE$2 -> 0.17454545 | AK8: P1 | AL8: 5 Gallon Pails | AN8: =IFERROR(VLOOKUP('Manufactured Items Models'!AL8,'Cost Master List'!$B$84:$L$98,11,FALSE),0) -> 9.68 | AO8: =+AN8/$G$14 -> 0.242 | AQ8: P1 | AR8: 1 Gallon Jug & Box Combo | AT8: =IFERROR(VLOOKUP('Manufactured Items Models'!AR8,'Cost Master List'!$B$84:$L$98,11,FALSE),0) -> 1.6 | AU8: =+AT8/$G$14 -> 0.04 | AW8: P1 | AX8: 5 Gallon Pails | AZ8: =IFERROR(VLOOKUP('Manufactured Items Models'!AX8,'Cost Master List'!$B$84:$L$98,11,FALSE),0) -> 9.68 | BA8: =+AZ8/$G$14 -> 0.242
A9: P2 | D9: =IFERROR(VLOOKUP('Manufactured Items Models'!B9,'Cost Master List'!$B$84:$L$98,11,FALSE),0) -> 0 | E9: =+D9/$A$2 -> 0 | G9: P2 | H9: Blue USFDA Poly Bag 34x40x.004 | J9: =IFERROR(VLOOKUP('Manufactured Items Models'!H9,'Cost Master List'!$B$84:$L$98,11,FALSE),0) -> 0.678 | K9: =+J9/$G$2 -> 0.01695 | M9: P2 | N9: Blue USFDA Poly Bag 32x32x.004 | P9: =IFERROR(VLOOKUP('Manufactured Items Models'!N9,'Cost Master List'!$B$84:$L$98,11,FALSE),0) -> 0.553 | Q9: =+P9/$M$2 -> 0.050272727 | S9: P2 | T9: Blue USFDA Poly Bag 34x40x.004 | V9: =IFERROR(VLOOKUP('Manufactured Items Models'!T9,'Cost Master List'!$B$84:$L$98,11,FALSE),0) -> 0.678 | W9: =+V9/$S$2 -> 0.015409091 | Y9: P2 | AB9: =IFERROR(VLOOKUP('Manufactured Items Models'!Z9,'Cost Master List'!$B$84:$L$98,11,FALSE),0) -> 0 | AC9: =+AB9/$Y$2 -> 0 | AE9: P2 | AF9: Blue USFDA Poly Bag 32x32x.004 | AH9: =IFERROR(VLOOKUP('Manufactured Items Models'!AF9,'Cost Master List'!$B$84:$L$98,11,FALSE),0) -> 0.553 | AI9: =+AH9/$AE$2 -> 0.050272727 | AK9: P2 | AN9: =IFERROR(VLOOKUP('Manufactured Items Models'!AL9,'Cost Master List'!$B$84:$L$98,11,FALSE),0) -> 0 | AO9: =+AN9/$G$14 -> 0 | AQ9: P2 | AT9: =IFERROR(VLOOKUP('Manufactured Items Models'!AR9,'Cost Master List'!$B$84:$L$98,11,FALSE),0) -> 0 | AU9: =+AT9/$G$14 -> 0 | AW9: P2 | AZ9: =IFERROR(VLOOKUP('Manufactured Items Models'!AX9,'Cost Master List'!$B$84:$L$98,11,FALSE),0) -> 0 | BA9: =+AZ9/$G$14 -> 0
A10: P3 | D10: =IFERROR(VLOOKUP('Manufactured Items Models'!B10,'Cost Master List'!$B$84:$L$98,11,FALSE),0) -> 0 | E10: =+D10/$A$2 -> 0 | G10: P3 | J10: =IFERROR(VLOOKUP('Manufactured Items Models'!H10,'Cost Master List'!$B$84:$L$98,11,FALSE),0) -> 0 | K10: =+J10/$G$2 -> 0 | M10: P3 | P10: =IFERROR(VLOOKUP('Manufactured Items Models'!N10,'Cost Master List'!$B$84:$L$98,11,FALSE),0) -> 0 | Q10: =+P10/$M$2 -> 0 | S10: P3 | V10: =IFERROR(VLOOKUP('Manufactured Items Models'!T10,'Cost Master List'!$B$84:$L$98,11,FALSE),0) -> 0 | W10: =+V10/$S$2 -> 0 | Y10: P3 | AB10: =IFERROR(VLOOKUP('Manufactured Items Models'!Z10,'Cost Master List'!$B$84:$L$98,11,FALSE),0) -> 0 | AC10: =+AB10/$Y$2 -> 0 | AE10: P3 | AH10: =IFERROR(VLOOKUP('Manufactured Items Models'!AF10,'Cost Master List'!$B$84:$L$98,11,FALSE),0) -> 0 | AI10: =+AH10/$AE$2 -> 0 | AK10: P3 | AN10: =IFERROR(VLOOKUP('Manufactured Items Models'!AL10,'Cost Master List'!$B$84:$L$98,11,FALSE),0) -> 0 | AO10: =+AN10/$G$14 -> 0 | AQ10: P3 | AT10: =IFERROR(VLOOKUP('Manufactured Items Models'!AR10,'Cost Master List'!$B$84:$L$98,11,FALSE),0) -> 0 | AU10: =+AT10/$G$14 -> 0 | AW10: P3 | AZ10: =IFERROR(VLOOKUP('Manufactured Items Models'!AX10,'Cost Master List'!$B$84:$L$98,11,FALSE),0) -> 0 | BA10: =+AZ10/$G$14 -> 0
A11: Labor | E11: 0.25 | G11: Labor | K11: 1 | M11: Labor | Q11: 1 | S11: Labor | W11: 1 | Y11: Labor | AC11: 1 | AE11: Labor | AI11: 1 | AK11: Labor | AO11: 1 | AQ11: Labor | AU11: 1 | AW11: Labor | BA11: 1
B12: Annatto Extract P2401 (8) | D12: Cost/lb | E12: =+SUM(E3:E11) -> 1.9418671 | H12: Natural Red D1303 (40) | J12: Cost/lb | K12: =+SUM(K3:K11) -> 4.3614086 | N12: Natural BP N1399 (11) | P12: Cost/lb | Q12: =+SUM(Q3:Q11) -> 39.444965 | T12: Natural Red A1320 (44) | V12: Cost/lb | W12: =+SUM(W3:W11) -> 16.918381 | Z12: Natural Red E1430 (44) | AB12: Cost/lb | AC12: =+SUM(AC3:AC11) -> 5.3980216 | AF12: Natural Blue L1355 (11) | AH12: Cost/lb | AI12: =+SUM(AI3:AI11) -> 18.115126 | AL12: Natural Red C1409 (8) | AN12: Cost/lb | AO12: =+SUM(AO3:AO11) -> 8.1301527 | AR12: Natural Red B1416 (8) | AT12: Cost/lb | AU12: =+SUM(AU3:AU11) -> 21.90533 | AX12: Natural Yellow G3401-N (44) | AZ12: Cost/lb | BA12: =+SUM(BA3:BA11) -> 4.7495047
A14: 40 | B14: Annatto Extract P2401 | C14: Composition | D14: Price/lb | E14: Formula Cost | G14: 40 | H14: Natural Red D1305 | I14: Composition | J14: Price/lb | K14: Formula Cost | O14: Composition | P14: Price/lb | Q14: Formula Cost | U14: Composition | V14: Price/lb | W14: Formula Cost | AA14: Composition | AB14: Price/lb | AC14: Formula Cost | AE14: 44 | AF14: Natural Blue L1405 | AG14: Composition | AH14: Price/lb | AI14: Formula Cost | AK14: 44 | AL14: Natural Red C1309 | AM14: Composition | AN14: Price/lb | AO14: Formula Cost | AS14: Composition | AT14: Price/lb | AU14: Formula Cost | AY14: Composition | AZ14: Price/lb | BA14: Formula Cost
A15: R1 | B15: Annatto Extract P2404 (Cyber Colors) | C15: 0.05 | D15: =IFERROR(VLOOKUP(B15,'Cost Master List'!$B$2:$P$74,12,),0) -> 7.3221235 | E15: =+D15*C15 -> 0.36610618 | G15: R1 | H15: Beet Powder 0.8% (Nutracean) | I15: 0.625 | J15: =IFERROR(VLOOKUP(H15,'Cost Master List'!$B$2:$P$74,12,),0) -> 7.3441228 | K15: =+J15*I15 -> 4.5900767 | M15: R1 | P15: =IFERROR(VLOOKUP(N15,'Cost Master List'!$B$2:$P$74,12,),0) -> 0 | Q15: =+P15*O15 -> 0 | S15: R1 | V15: =IFERROR(VLOOKUP(T15,'Cost Master List'!$B$2:$P$74,12,),0) -> 0 | W15: =+V15*U15 -> 0 | Y15: R1 | AB15: =IFERROR(VLOOKUP(Z15,'Cost Master List'!$B$2:$P$74,12,),0) -> 0 | AC15: =+AB15*AA15 -> 0 | AE15: R1 | AF15: Natural Blue L1300 (Hiche) | AG15: 0.25 | AH15: =IFERROR(VLOOKUP(AF15,'Cost Master List'!$B$2:$P$74,12,),0) -> 51.473723 | AI15: =+AH15*AG15 -> 12.868431 | AK15: R1 | AL15: Not Assigned | AM15: 0.3 | AN15: =IFERROR(VLOOKUP(AL15,'Cost Master List'!$B$2:$P$74,12,),0) -> 5.9091816 | AO15: =+AN15*AM15 -> 1.7727545 | AQ15: R1 | AT15: =IFERROR(VLOOKUP(AR15,'Cost Master List'!$B$2:$P$74,12,),0) -> 0 | AU15: =+AT15*AS15 -> 0 | AW15: R1 | AZ15: =IFERROR(VLOOKUP(AX15,'Cost Master List'!$B$2:$P$74,12,),0) -> 0 | BA15: =+AZ15*AY15 -> 0
A16: R2 | B16: Sun Flower Oil* | C16: 0.95 | D16: =IFERROR(VLOOKUP(B16,'Cost Master List'!$B$2:$P$74,12,),0) -> 1.1850115 | E16: =+D16*C16 -> 1.1257609 | G16: R2 | H16: Maltodextrin M-100 IP (Brenntag) | I16: 0.375 | J16: =IFERROR(VLOOKUP(H16,'Cost Master List'!$B$2:$P$74,12,),0) -> 0.83914688 | K16: =+J16*I16 -> 0.31468008 | M16: R2 | P16: =IFERROR(VLOOKUP(N16,'Cost Master List'!$B$2:$P$74,12,),0) -> 0 | Q16: =+P16*O16 -> 0 | S16: R2 | V16: =IFERROR(VLOOKUP(T16,'Cost Master List'!$B$2:$P$74,12,),0) -> 0 | W16: =+V16*U16 -> 0 | Y16: R2 | AB16: =IFERROR(VLOOKUP(Z16,'Cost Master List'!$B$2:$P$74,12,),0) -> 0 | AC16: =+AB16*AA16 -> 0 | AE16: R2 | AF16: Glycerin* | AG16: 0.55 | AH16: =IFERROR(VLOOKUP(AF16,'Cost Master List'!$B$2:$P$74,12,),0) -> 4.5359291 | AI16: =+AH16*AG16 -> 2.494761 | AK16: R2 | AL16: Maltodextrin M-100 IP (Brenntag) | AM16: 0.7 | AN16: =IFERROR(VLOOKUP(AL16,'Cost Master List'!$B$2:$P$74,12,),0) -> 0.83914688 | AO16: =+AN16*AM16 -> 0.58740282 | AQ16: R2 | AT16: =IFERROR(VLOOKUP(AR16,'Cost Master List'!$B$2:$P$74,12,),0) -> 0 | AU16: =+AT16*AS16 -> 0 | AW16: R2 | AZ16: =IFERROR(VLOOKUP(AX16,'Cost Master List'!$B$2:$P$74,12,),0) -> 0 | BA16: =+AZ16*AY16 -> 0
A17: R3 | D17: =IFERROR(VLOOKUP(B17,'Cost Master List'!$B$2:$P$74,12,),0) -> 0 | E17: =+D17*C17 -> 0 | G17: R3 | J17: =IFERROR(VLOOKUP(H17,'Cost Master List'!$B$2:$P$74,12,),0) -> 0 | K17: =+J17*I17 -> 0 | M17: R3 | P17: =IFERROR(VLOOKUP(N17,'Cost Master List'!$B$2:$P$74,12,),0) -> 0 | Q17: =+P17*O17 -> 0 | S17: R3 | V17: =IFERROR(VLOOKUP(T17,'Cost Master List'!$B$2:$P$74,12,),0) -> 0 | W17: =+V17*U17 -> 0 | Y17: R3 | AB17: =IFERROR(VLOOKUP(Z17,'Cost Master List'!$B$2:$P$74,12,),0) -> 0 | AC17: =+AB17*AA17 -> 0 | AE17: R3 | AF17: DI Water | AG17: 0.2 | AH17: =IFERROR(VLOOKUP(AF17,'Cost Master List'!$B$2:$P$74,12,),0) -> 0.22679645 | AI17: =+AH17*AG17 -> 0.045359291 | AK17: R3 | AN17: =IFERROR(VLOOKUP(AL17,'Cost Master List'!$B$2:$P$74,12,),0) -> 0 | AO17: =+AN17*AM17 -> 0 | AQ17: R3 | AT17: =IFERROR(VLOOKUP(AR17,'Cost Master List'!$B$2:$P$74,12,),0) -> 0 | AU17: =+AT17*AS17 -> 0 | AW17: R3 | AZ17: =IFERROR(VLOOKUP(AX17,'Cost Master List'!$B$2:$P$74,12,),0) -> 0 | BA17: =+AZ17*AY17 -> 0
A18: R4 | D18: =IFERROR(VLOOKUP(B18,'Cost Master List'!$B$2:$P$74,12,),0) -> 0 | E18: =+D18*C18 -> 0 | G18: R4 | J18: =IFERROR(VLOOKUP(H18,'Cost Master List'!$B$2:$P$74,12,),0) -> 0 | K18: =+J18*I18 -> 0 | M18: R4 | P18: =IFERROR(VLOOKUP(N18,'Cost Master List'!$B$2:$P$74,12,),0) -> 0 | Q18: =+P18*O18 -> 0 | S18: R4 | V18: =IFERROR(VLOOKUP(T18,'Cost Master List'!$B$2:$P$74,12,),0) -> 0 | W18: =+V18*U18 -> 0 | Y18: R4 | AB18: =IFERROR(VLOOKUP(Z18,'Cost Master List'!$B$2:$P$74,12,),0) -> 0 | AC18: =+AB18*AA18 -> 0 | AE18: R4 | AH18: =IFERROR(VLOOKUP(AF18,'Cost Master List'!$B$2:$P$74,12,),0) -> 0 | AI18: =+AH18*AG18 -> 0 | AK18: R4 | AN18: =IFERROR(VLOOKUP(AL18,'Cost Master List'!$B$2:$P$74,12,),0) -> 0 | AO18: =+AN18*AM18 -> 0 | AQ18: R4 | AT18: =IFERROR(VLOOKUP(AR18,'Cost Master List'!$B$2:$P$74,12,),0) -> 0 | AU18: =+AT18*AS18 -> 0 | AW18: R4 | AZ18: =IFERROR(VLOOKUP(AX18,'Cost Master List'!$B$2:$P$74,12,),0) -> 0 | BA18: =+AZ18*AY18 -> 0
A19: R5 | D19: =IFERROR(VLOOKUP(B19,'Cost Master List'!$B$2:$P$74,12,),0) -> 0 | E19: =+D19*C19 -> 0 | G19: R5 | J19: =IFERROR(VLOOKUP(H19,'Cost Master List'!$B$2:$P$74,12,),0) -> 0 | K19: =+J19*I19 -> 0 | M19: R5 | P19: =IFERROR(VLOOKUP(N19,'Cost Master List'!$B$2:$P$74,12,),0) -> 0 | Q19: =+P19*O19 -> 0 | S19: R5 | V19: =IFERROR(VLOOKUP(T19,'Cost Master List'!$B$2:$P$74,12,),0) -> 0 | W19: =+V19*U19 -> 0 | Y19: R5 | AB19: =IFERROR(VLOOKUP(Z19,'Cost Master List'!$B$2:$P$74,12,),0) -> 0 | AC19: =+AB19*AA19 -> 0 | AE19: R5 | AH19: =IFERROR(VLOOKUP(AF19,'Cost Master List'!$B$2:$P$74,12,),0) -> 0 | AI19: =+AH19*AG19 -> 0 | AK19: R5 | AN19: =IFERROR(VLOOKUP(AL19,'Cost Master List'!$B$2:$P$74,12,),0) -> 0 | AO19: =+AN19*AM19 -> 0 | AQ19: R5 | AT19: =IFERROR(VLOOKUP(AR19,'Cost Master List'!$B$2:$P$74,12,),0) -> 0 | AU19: =+AT19*AS19 -> 0 | AW19: R5 | AZ19: =IFERROR(VLOOKUP(AX19,'Cost Master List'!$B$2:$P$74,12,),0) -> 0 | BA19: =+AZ19*AY19 -> 0
A20: P1 | B20: 5 Gallon Pails | D20: =IFERROR(VLOOKUP('Manufactured Items Models'!B20,'Cost Master List'!$B$84:$L$98,11,FALSE),0) -> 9.68 | E20: =+D20/$A$14 -> 0.242 | G20: P1 | H20: 15x15x15 box | J20: =IFERROR(VLOOKUP('Manufactured Items Models'!H20,'Cost Master List'!$B$84:$L$98,11,FALSE),0) -> 2.47 | K20: =+J20/$G$14 -> 0.06175 | M20: P1 | P20: =IFERROR(VLOOKUP('Manufactured Items Models'!N20,'Cost Master List'!$B$84:$L$98,11,FALSE),0) -> 0 | Q20: =+P20/$G$14 -> 0 | S20: P1 | V20: =IFERROR(VLOOKUP('Manufactured Items Models'!T20,'Cost Master List'!$B$84:$L$98,11,FALSE),0) -> 0 | W20: =+V20/$G$14 -> 0 | Y20: P1 | AB20: =IFERROR(VLOOKUP('Manufactured Items Models'!Z20,'Cost Master List'!$B$84:$L$98,11,FALSE),0) -> 0 | AC20: =+AB20/$G$14 -> 0 | AE20: P1 | AF20: 5 Gallon Pails | AH20: =IFERROR(VLOOKUP('Manufactured Items Models'!AF20,'Cost Master List'!$B$84:$L$98,11,FALSE),0) -> 9.68 | AI20: =+AH20/$AE$14 -> 0.22 | AK20: P1 | AL20: 16x12x10 box | AN20: =IFERROR(VLOOKUP('Manufactured Items Models'!AL20,'Cost Master List'!$B$84:$L$98,11,FALSE),0) -> 1.92 | AO20: =+AN20/$G$14 -> 0.048 | AQ20: P1 | AT20: =IFERROR(VLOOKUP('Manufactured Items Models'!AR20,'Cost Master List'!$B$84:$L$98,11,FALSE),0) -> 0 | AU20: =+AT20/$G$14 -> 0 | AW20: P1 | AZ20: =IFERROR(VLOOKUP('Manufactured Items Models'!AX20,'Cost Master List'!$B$84:$L$98,11,FALSE),0) -> 0 | BA20: =+AZ20/$G$14 -> 0
A21: P2 | D21: =IFERROR(VLOOKUP('Manufactured Items Models'!B21,'Cost Master List'!$B$84:$L$98,11,FALSE),0) -> 0 | E21: =+D21/$A$14 -> 0 | G21: P2 | H21: Blue USFDA Poly Bag 34x40x.004 | J21: =IFERROR(VLOOKUP('Manufactured Items Models'!H21,'Cost Master List'!$B$84:$L$98,11,FALSE),0) -> 0.678 | K21: =+J21/$G$14 -> 0.01695 | M21: P2 | P21: =IFERROR(VLOOKUP('Manufactured Items Models'!N21,'Cost Master List'!$B$84:$L$98,11,FALSE),0) -> 0 | Q21: =+P21/$G$14 -> 0 | S21: P2 | V21: =IFERROR(VLOOKUP('Manufactured Items Models'!T21,'Cost Master List'!$B$84:$L$98,11,FALSE),0) -> 0 | W21: =+V21/$G$14 -> 0 | Y21: P2 | AB21: =IFERROR(VLOOKUP('Manufactured Items Models'!Z21,'Cost Master List'!$B$84:$L$98,11,FALSE),0) -> 0 | AC21: =+AB21/$G$14 -> 0 | AE21: P2 | AH21: =IFERROR(VLOOKUP('Manufactured Items Models'!AF21,'Cost Master List'!$B$84:$L$98,11,FALSE),0) -> 0 | AI21: =+AH21/$AE$14 -> 0 | AK21: P2 | AL21: Blue USFDA Poly Bag 32x32x.004 | AN21: =IFERROR(VLOOKUP('Manufactured Items Models'!AL21,'Cost Master List'!$B$84:$L$98,11,FALSE),0) -> 0.553 | AO21: =+AN21/$G$14 -> 0.013825 | AQ21: P2 | AT21: =IFERROR(VLOOKUP('Manufactured Items Models'!AR21,'Cost Master List'!$B$84:$L$98,11,FALSE),0) -> 0 | AU21: =+AT21/$G$14 -> 0 | AW21: P2 | AZ21: =IFERROR(VLOOKUP('Manufactured Items Models'!AX21,'Cost Master List'!$B$84:$L$98,11,FALSE),0) -> 0 | BA21: =+AZ21/$G$14 -> 0
A22: P3 | D22: =IFERROR(VLOOKUP('Manufactured Items Models'!B22,'Cost Master List'!$B$84:$L$98,11,FALSE),0) -> 0 | E22: =+D22/$A$14 -> 0 | G22: P3 | J22: =IFERROR(VLOOKUP('Manufactured Items Models'!H22,'Cost Master List'!$B$84:$L$98,11,FALSE),0) -> 0 | K22: =+J22/$G$14 -> 0 | M22: P3 | P22: =IFERROR(VLOOKUP('Manufactured Items Models'!N22,'Cost Master List'!$B$84:$L$98,11,FALSE),0) -> 0 | Q22: =+P22/$G$14 -> 0 | S22: P3 | V22: =IFERROR(VLOOKUP('Manufactured Items Models'!T22,'Cost Master List'!$B$84:$L$98,11,FALSE),0) -> 0 | W22: =+V22/$G$14 -> 0 | Y22: P3 | AB22: =IFERROR(VLOOKUP('Manufactured Items Models'!Z22,'Cost Master List'!$B$84:$L$98,11,FALSE),0) -> 0 | AC22: =+AB22/$G$14 -> 0 | AE22: P3 | AH22: =IFERROR(VLOOKUP('Manufactured Items Models'!AF22,'Cost Master List'!$B$84:$L$98,11,FALSE),0) -> 0 | AI22: =+AH22/$AE$14 -> 0 | AK22: P3 | AN22: =IFERROR(VLOOKUP('Manufactured Items Models'!AL22,'Cost Master List'!$B$84:$L$98,11,FALSE),0) -> 0 | AO22: =+AN22/$G$14 -> 0 | AQ22: P3 | AT22: =IFERROR(VLOOKUP('Manufactured Items Models'!AR22,'Cost Master List'!$B$84:$L$98,11,FALSE),0) -> 0 | AU22: =+AT22/$G$14 -> 0 | AW22: P3 | AZ22: =IFERROR(VLOOKUP('Manufactured Items Models'!AX22,'Cost Master List'!$B$84:$L$98,11,FALSE),0) -> 0 | BA22: =+AZ22/$G$14 -> 0
A23: Labor | E23: 0.25 | G23: Labor | K23: 1 | M23: Labor | Q23: 1 | S23: Labor | W23: 1 | Y23: Labor | AC23: 1 | AE23: Labor | AI23: 1 | AK23: Labor | AO23: 1 | AQ23: Labor | AU23: 1 | AW23: Labor | BA23: 1
B24: Annatto Extract P2401 (40) | D24: Cost/lb | E24: =+SUM(E15:E23) -> 1.9838671 | H24: Natural Red D1305 (40) | J24: Cost/lb | K24: =+SUM(K15:K23) -> 5.9834568 | P24: Cost/lb | Q24: =+SUM(Q15:Q23) -> 1 | V24: Cost/lb | W24: =+SUM(W15:W23) -> 1 | AB24: Cost/lb | AC24: =+SUM(AC15:AC23) -> 1 | AF24: Natural Blue L1405 (44) | AH24: Cost/lb | AI24: =+SUM(AI15:AI23) -> 16.628551 | AL24: Natural Red C1309 (44) | AN24: Cost/lb | AO24: =+SUM(AO15:AO23) -> 3.4219823 | AT24: Cost/lb | AU24: =+SUM(AU15:AU23) -> 1 | AZ24: Cost/lb | BA24: =+SUM(BA15:BA23) -> 1
A26: 40 | B26: Annatto Extract P2404 | C26: Composition | D26: Price/lb | E26: Formula Cost | G26: 40 | H26: Natural Red D1307 | I26: Composition | J26: Price/lb | K26: Formula Cost | O26: Composition | P26: Price/lb | Q26: Formula Cost | U26: Composition | V26: Price/lb | W26: Formula Cost | AA26: Composition | AB26: Price/lb | AC26: Formula Cost | AG26: Composition | AH26: Price/lb | AI26: Formula Cost | AL26: Natural Red C1409 Chen | AM26: Composition | AN26: Price/lb | AO26: Formula Cost | AS26: Composition | AT26: Price/lb | AU26: Formula Cost | AY26: Composition | AZ26: Price/lb | BA26: Formula Cost
A27: R1 | B27: Annatto Extract P2408 (Cyber Colors) | C27: 0.5 | D27: =IFERROR(VLOOKUP(B27,'Cost Master List'!$B$2:$P$74,12,),0) -> 15.542361 | E27: =+D27*C27 -> 7.7711805 | G27: R1 | H27: Beet Powder 0.8% (Nutracean) | I27: 0.875 | J27: =IFERROR(VLOOKUP(H27,'Cost Master List'!$B$2:$P$74,12,),0) -> 7.3441228 | K27: =+J27*I27 -> 6.4261074 | M27: R1 | P27: =IFERROR(VLOOKUP(N27,'Cost Master List'!$B$2:$P$74,12,),0) -> 0 | Q27: =+P27*O27 -> 0 | S27: R1 | V27: =IFERROR(VLOOKUP(T27,'Cost Master List'!$B$2:$P$74,12,),0) -> 0 | W27: =+V27*U27 -> 0 | Y27: R1 | AB27: =IFERROR(VLOOKUP(Z27,'Cost Master List'!$B$2:$P$74,12,),0) -> 0 | AC27: =+AB27*AA27 -> 0 | AE27: R1 | AH27: =IFERROR(VLOOKUP(AF27,'Cost Master List'!$B$2:$P$74,12,),0) -> 0 | AI27: =+AH27*AG27 -> 0 | AK27: R1 | AL27: Sorbitol* | AM27: 0.7956 | AN27: =IFERROR(VLOOKUP(AL27,'Cost Master List'!$B$2:$P$74,12,),0) -> 1.8143716 | AO27: =+AN27*AM27 -> 1.4435141 | AQ27: R1 | AT27: =IFERROR(VLOOKUP(AR27,'Cost Master List'!$B$2:$P$74,12,),0) -> 0 | AU27: =+AT27*AS27 -> 0 | AW27: R1 | AZ27: =IFERROR(VLOOKUP(AX27,'Cost Master List'!$B$2:$P$74,12,),0) -> 0 | BA27: =+AZ27*AY27 -> 0
A28: R2 | B28: Sun Flower Oil* | C28: 0.95 | D28: =IFERROR(VLOOKUP(B28,'Cost Master List'!$B$2:$P$74,12,),0) -> 1.1850115 | E28: =+D28*C28 -> 1.1257609 | G28: R2 | H28: Maltodextrin M-100 IP (Brenntag) | I28: 0.125 | J28: =IFERROR(VLOOKUP(H28,'Cost Master List'!$B$2:$P$74,12,),0) -> 0.83914688 | K28: =+J28*I28 -> 0.10489336 | M28: R2 | P28: =IFERROR(VLOOKUP(N28,'Cost Master List'!$B$2:$P$74,12,),0) -> 0 | Q28: =+P28*O28 -> 0 | S28: R2 | V28: =IFERROR(VLOOKUP(T28,'Cost Master List'!$B$2:$P$74,12,),0) -> 0 | W28: =+V28*U28 -> 0 | Y28: R2 | AB28: =IFERROR(VLOOKUP(Z28,'Cost Master List'!$B$2:$P$74,12,),0) -> 0 | AC28: =+AB28*AA28 -> 0 | AE28: R2 | AH28: =IFERROR(VLOOKUP(AF28,'Cost Master List'!$B$2:$P$74,12,),0) -> 0 | AI28: =+AH28*AG28 -> 0 | AK28: R2 | AL28: DI Water | AM28: 0.1094 | AN28: =IFERROR(VLOOKUP(AL28,'Cost Master List'!$B$2:$P$74,12,),0) -> 0.22679645 | AO28: =+AN28*AM28 -> 0.024811532 | AQ28: R2 | AT28: =IFERROR(VLOOKUP(AR28,'Cost Master List'!$B$2:$P$74,12,),0) -> 0 | AU28: =+AT28*AS28 -> 0 | AW28: R2 | AZ28: =IFERROR(VLOOKUP(AX28,'Cost Master List'!$B$2:$P$74,12,),0) -> 0 | BA28: =+AZ28*AY28 -> 0
A29: R3 | D29: =IFERROR(VLOOKUP(B29,'Cost Master List'!$B$2:$P$74,12,),0) -> 0 | E29: =+D29*C29 -> 0 | G29: R3 | J29: =IFERROR(VLOOKUP(H29,'Cost Master List'!$B$2:$P$74,12,),0) -> 0 | K29: =+J29*I29 -> 0 | M29: R3 | P29: =IFERROR(VLOOKUP(N29,'Cost Master List'!$B$2:$P$74,12,),0) -> 0 | Q29: =+P29*O29 -> 0 | S29: R3 | V29: =IFERROR(VLOOKUP(T29,'Cost Master List'!$B$2:$P$74,12,),0) -> 0 | W29: =+V29*U29 -> 0 | Y29: R3 | AB29: =IFERROR(VLOOKUP(Z29,'Cost Master List'!$B$2:$P$74,12,),0) -> 0 | AC29: =+AB29*AA29 -> 0 | AE29: R3 | AH29: =IFERROR(VLOOKUP(AF29,'Cost Master List'!$B$2:$P$74,12,),0) -> 0 | AI29: =+AH29*AG29 -> 0 | AK29: R3 | AL29: Potassium Sorbate (Brenntag) | AM29: 0.002 | AN29: =IFERROR(VLOOKUP(AL29,'Cost Master List'!$B$2:$P$74,12,),0) -> 2.0184884 | AO29: =+AN29*AM29 -> 0.0040369769 | AQ29: R3 | AT29: =IFERROR(VLOOKUP(AR29,'Cost Master List'!$B$2:$P$74,12,),0) -> 0 | AU29: =+AT29*AS29 -> 0 | AW29: R3 | AZ29: =IFERROR(VLOOKUP(AX29,'Cost Master List'!$B$2:$P$74,12,),0) -> 0 | BA29: =+AZ29*AY29 -> 0
A30: R4 | D30: =IFERROR(VLOOKUP(B30,'Cost Master List'!$B$2:$P$74,12,),0) -> 0 | E30: =+D30*C30 -> 0 | G30: R4 | J30: =IFERROR(VLOOKUP(H30,'Cost Master List'!$B$2:$P$74,12,),0) -> 0 | K30: =+J30*I30 -> 0 | M30: R4 | P30: =IFERROR(VLOOKUP(N30,'Cost Master List'!$B$2:$P$74,12,),0) -> 0 | Q30: =+P30*O30 -> 0 | S30: R4 | V30: =IFERROR(VLOOKUP(T30,'Cost Master List'!$B$2:$P$74,12,),0) -> 0 | W30: =+V30*U30 -> 0 | Y30: R4 | AB30: =IFERROR(VLOOKUP(Z30,'Cost Master List'!$B$2:$P$74,12,),0) -> 0 | AC30: =+AB30*AA30 -> 0 | AE30: R4 | AH30: =IFERROR(VLOOKUP(AF30,'Cost Master List'!$B$2:$P$74,12,),0) -> 0 | AI30: =+AH30*AG30 -> 0 | AK30: R4 | AL30: Citric Acid* | AM30: 0.003 | AN30: =IFERROR(VLOOKUP(AL30,'Cost Master List'!$B$2:$P$74,12,),0) -> 4.5359291 | AO30: =+AN30*AM30 -> 0.013607787 | AQ30: R4 | AT30: =IFERROR(VLOOKUP(AR30,'Cost Master List'!$B$2:$P$74,12,),0) -> 0 | AU30: =+AT30*AS30 -> 0 | AW30: R4 | AZ30: =IFERROR(VLOOKUP(AX30,'Cost Master List'!$B$2:$P$74,12,),0) -> 0 | BA30: =+AZ30*AY30 -> 0
A31: R5 | D31: =IFERROR(VLOOKUP(B31,'Cost Master List'!$B$2:$P$74,12,),0) -> 0 | E31: =+D31*C31 -> 0 | G31: R5 | J31: =IFERROR(VLOOKUP(H31,'Cost Master List'!$B$2:$P$74,12,),0) -> 0 | K31: =+J31*I31 -> 0 | M31: R5 | P31: =IFERROR(VLOOKUP(N31,'Cost Master List'!$B$2:$P$74,12,),0) -> 0 | Q31: =+P31*O31 -> 0 | S31: R5 | V31: =IFERROR(VLOOKUP(T31,'Cost Master List'!$B$2:$P$74,12,),0) -> 0 | W31: =+V31*U31 -> 0 | Y31: R5 | AB31: =IFERROR(VLOOKUP(Z31,'Cost Master List'!$B$2:$P$74,12,),0) -> 0 | AC31: =+AB31*AA31 -> 0 | AE31: R5 | AH31: =IFERROR(VLOOKUP(AF31,'Cost Master List'!$B$2:$P$74,12,),0) -> 0 | AI31: =+AH31*AG31 -> 0 | AK31: R5 | AL31: Black Carrot EV100 (Nutracean) | AM31: 0.09 | AN31: =IFERROR(VLOOKUP(AL31,'Cost Master List'!$B$2:$P$74,12,),0) -> 76.076603 | AO31: =+AN31*AM31 -> 6.8468942 | AQ31: R5 | AT31: =IFERROR(VLOOKUP(AR31,'Cost Master List'!$B$2:$P$74,12,),0) -> 0 | AU31: =+AT31*AS31 -> 0 | AW31: R5 | AZ31: =IFERROR(VLOOKUP(AX31,'Cost Master List'!$B$2:$P$74,12,),0) -> 0 | BA31: =+AZ31*AY31 -> 0
A32: P1 | B32: 5 Gallon Pails | D32: =IFERROR(VLOOKUP('Manufactured Items Models'!B32,'Cost Master List'!$B$84:$L$98,11,FALSE),0) -> 9.68 | E32: =+D32/$A$26 -> 0.242 | G32: P1 | H32: 15x15x15 box | J32: =IFERROR(VLOOKUP('Manufactured Items Models'!H32,'Cost Master List'!$B$84:$L$98,11,FALSE),0) -> 2.47 | K32: =+J32/$G$26 -> 0.06175 | M32: P1 | P32: =IFERROR(VLOOKUP('Manufactured Items Models'!N32,'Cost Master List'!$B$84:$L$98,11,FALSE),0) -> 0 | Q32: =+P32/$G$14 -> 0 | S32: P1 | V32: =IFERROR(VLOOKUP('Manufactured Items Models'!T32,'Cost Master List'!$B$84:$L$98,11,FALSE),0) -> 0 | W32: =+V32/$G$14 -> 0 | Y32: P1 | AB32: =IFERROR(VLOOKUP('Manufactured Items Models'!Z32,'Cost Master List'!$B$84:$L$98,11,FALSE),0) -> 0 | AC32: =+AB32/$G$14 -> 0 | AE32: P1 | AH32: =IFERROR(VLOOKUP('Manufactured Items Models'!AF32,'Cost Master List'!$B$84:$L$98,11,FALSE),0) -> 0 | AI32: =+AH32/$G$14 -> 0 | AK32: P1 | AL32: 5 Gallon Pails | AN32: =IFERROR(VLOOKUP('Manufactured Items Models'!AL32,'Cost Master List'!$B$84:$L$98,11,FALSE),0) -> 9.68 | AO32: =+AN32/$G$14 -> 0.242 | AQ32: P1 | AT32: =IFERROR(VLOOKUP('Manufactured Items Models'!AR32,'Cost Master List'!$B$84:$L$98,11,FALSE),0) -> 0 | AU32: =+AT32/$G$14 -> 0 | AW32: P1 | AZ32: =IFERROR(VLOOKUP('Manufactured Items Models'!AX32,'Cost Master List'!$B$84:$L$98,11,FALSE),0) -> 0 | BA32: =+AZ32/$G$14 -> 0
A33: P2 | D33: =IFERROR(VLOOKUP('Manufactured Items Models'!B33,'Cost Master List'!$B$84:$L$98,11,FALSE),0) -> 0 | E33: =+D33/$A$26 -> 0 | G33: P2 | H33: Blue USFDA Poly Bag 34x40x.004 | J33: =IFERROR(VLOOKUP('Manufactured Items Models'!H33,'Cost Master List'!$B$84:$L$98,11,FALSE),0) -> 0.678 | K33: =+J33/$G$26 -> 0.01695 | M33: P2 | P33: =IFERROR(VLOOKUP('Manufactured Items Models'!N33,'Cost Master List'!$B$84:$L$98,11,FALSE),0) -> 0 | Q33: =+P33/$G$14 -> 0 | S33: P2 | V33: =IFERROR(VLOOKUP('Manufactured Items Models'!T33,'Cost Master List'!$B$84:$L$98,11,FALSE),0) -> 0 | W33: =+V33/$G$14 -> 0 | Y33: P2 | AB33: =IFERROR(VLOOKUP('Manufactured Items Models'!Z33,'Cost Master List'!$B$84:$L$98,11,FALSE),0) -> 0 | AC33: =+AB33/$G$14 -> 0 | AE33: P2 | AH33: =IFERROR(VLOOKUP('Manufactured Items Models'!AF33,'Cost Master List'!$B$84:$L$98,11,FALSE),0) -> 0 | AI33: =+AH33/$G$14 -> 0 | AK33: P2 | AN33: =IFERROR(VLOOKUP('Manufactured Items Models'!AL33,'Cost Master List'!$B$84:$L$98,11,FALSE),0) -> 0 | AO33: =+AN33/$G$14 -> 0 | AQ33: P2 | AT33: =IFERROR(VLOOKUP('Manufactured Items Models'!AR33,'Cost Master List'!$B$84:$L$98,11,FALSE),0) -> 0 | AU33: =+AT33/$G$14 -> 0 | AW33: P2 | AZ33: =IFERROR(VLOOKUP('Manufactured Items Models'!AX33,'Cost Master List'!$B$84:$L$98,11,FALSE),0) -> 0 | BA33: =+AZ33/$G$14 -> 0
A34: P3 | D34: =IFERROR(VLOOKUP('Manufactured Items Models'!B34,'Cost Master List'!$B$84:$L$98,11,FALSE),0) -> 0 | E34: =+D34/$A$26 -> 0 | G34: P3 | J34: =IFERROR(VLOOKUP('Manufactured Items Models'!H34,'Cost Master List'!$B$84:$L$98,11,FALSE),0) -> 0 | K34: =+J34/$G$26 -> 0 | M34: P3 | P34: =IFERROR(VLOOKUP('Manufactured Items Models'!N34,'Cost Master List'!$B$84:$L$98,11,FALSE),0) -> 0 | Q34: =+P34/$G$14 -> 0 | S34: P3 | V34: =IFERROR(VLOOKUP('Manufactured Items Models'!T34,'Cost Master List'!$B$84:$L$98,11,FALSE),0) -> 0 | W34: =+V34/$G$14 -> 0 | Y34: P3 | AB34: =IFERROR(VLOOKUP('Manufactured Items Models'!Z34,'Cost Master List'!$B$84:$L$98,11,FALSE),0) -> 0 | AC34: =+AB34/$G$14 -> 0 | AE34: P3 | AH34: =IFERROR(VLOOKUP('Manufactured Items Models'!AF34,'Cost Master List'!$B$84:$L$98,11,FALSE),0) -> 0 | AI34: =+AH34/$G$14 -> 0 | AK34: P3 | AN34: =IFERROR(VLOOKUP('Manufactured Items Models'!AL34,'Cost Master List'!$B$84:$L$98,11,FALSE),0) -> 0 | AO34: =+AN34/$G$14 -> 0 | AQ34: P3 | AT34: =IFERROR(VLOOKUP('Manufactured Items Models'!AR34,'Cost Master List'!$B$84:$L$98,11,FALSE),0) -> 0 | AU34: =+AT34/$G$14 -> 0 | AW34: P3 | AZ34: =IFERROR(VLOOKUP('Manufactured Items Models'!AX34,'Cost Master List'!$B$84:$L$98,11,FALSE),0) -> 0 | BA34: =+AZ34/$G$14 -> 0
A35: Labor | E35: 1 | G35: Labor | K35: 1 | M35: Labor | Q35: 1 | S35: Labor | W35: 1 | Y35: Labor | AC35: 1 | AE35: Labor | AI35: 1 | AK35: Labor | AO35: 1 | AQ35: Labor | AU35: 1 | AW35: Labor | BA35: 1
B36: =+B26 -> Annatto Extract P2404 | D36: Cost/lb | E36: =+SUM(E27:E35) -> 10.138941 | H36: Natural Red D1307 (40) | J36: Cost/lb | K36: =+SUM(K27:K35) -> 7.6097008 | P36: Cost/lb | Q36: =+SUM(Q27:Q35) -> 1 | V36: Cost/lb | W36: =+SUM(W27:W35) -> 1 | AB36: Cost/lb | AC36: =+SUM(AC27:AC35) -> 1 | AH36: Cost/lb | AI36: =+SUM(AI27:AI35) -> 1 | AN36: Cost/lb | AO36: =+SUM(AO27:AO35) -> 9.5748646 | AT36: Cost/lb | AU36: =+SUM(AU27:AU35) -> 1 | AZ36: Cost/lb | BA36: =+SUM(BA27:BA35) -> 1
A38: 8 | B38: Annatto Extract P1411 | C38: Composition | D38: Price/lb | E38: Formula Cost | I38: Composition | J38: Price/lb | K38: Formula Cost | O38: Composition | P38: Price/lb | Q38: Formula Cost | U38: Composition | V38: Price/lb | W38: Formula Cost | AA38: Composition | AB38: Price/lb | AC38: Formula Cost | AG38: Composition | AH38: Price/lb | AI38: Formula Cost | AM38: Composition | AN38: Price/lb | AO38: Formula Cost | AS38: Composition | AT38: Price/lb | AU38: Formula Cost | AY38: Composition | AZ38: Price/lb | BA38: Formula Cost
A39: R1 | B39: Annatto Extract WS5 (Cyber Colors) | C39: 0.21 | D39: =IFERROR(VLOOKUP(B39,'Cost Master List'!$B$2:$P$74,12,),0) -> 6.1053606 | E39: =+D39*C39 -> 1.2821257 | G39: R1 | J39: =IFERROR(VLOOKUP(H39,'Cost Master List'!$B$2:$P$74,12,),0) -> 0 | K39: =+J39*I39 -> 0 | M39: R1 | P39: =IFERROR(VLOOKUP(N39,'Cost Master List'!$B$2:$P$74,12,),0) -> 0 | Q39: =+P39*O39 -> 0 | S39: R1 | V39: =IFERROR(VLOOKUP(T39,'Cost Master List'!$B$2:$P$74,12,),0) -> 0 | W39: =+V39*U39 -> 0 | Y39: R1 | AB39: =IFERROR(VLOOKUP(Z39,'Cost Master List'!$B$2:$P$74,12,),0) -> 0 | AC39: =+AB39*AA39 -> 0 | AE39: R1 | AH39: =IFERROR(VLOOKUP(AF39,'Cost Master List'!$B$2:$P$74,12,),0) -> 0 | AI39: =+AH39*AG39 -> 0 | AK39: R1 | AN39: =IFERROR(VLOOKUP(AL39,'Cost Master List'!$B$2:$P$74,12,),0) -> 0 | AO39: =+AN39*AM39 -> 0 | AQ39: R1 | AT39: =IFERROR(VLOOKUP(AR39,'Cost Master List'!$B$2:$P$74,12,),0) -> 0 | AU39: =+AT39*AS39 -> 0 | AW39: R1 | AZ39: =IFERROR(VLOOKUP(AX39,'Cost Master List'!$B$2:$P$74,12,),0) -> 0 | BA39: =+AZ39*AY39 -> 0
A40: R2 | B40: DI Water | C40: 0.79 | D40: =IFERROR(VLOOKUP(B40,'Cost Master List'!$B$2:$P$74,12,),0) -> 0.22679645 | E40: =+D40*C40 -> 0.1791692 | G40: R2 | J40: =IFERROR(VLOOKUP(H40,'Cost Master List'!$B$2:$P$74,12,),0) -> 0 | K40: =+J40*I40 -> 0 | M40: R2 | P40: =IFERROR(VLOOKUP(N40,'Cost Master List'!$B$2:$P$74,12,),0) -> 0 | Q40: =+P40*O40 -> 0 | S40: R2 | V40: =IFERROR(VLOOKUP(T40,'Cost Master List'!$B$2:$P$74,12,),0) -> 0 | W40: =+V40*U40 -> 0 | Y40: R2 | AB40: =IFERROR(VLOOKUP(Z40,'Cost Master List'!$B$2:$P$74,12,),0) -> 0 | AC40: =+AB40*AA40 -> 0 | AE40: R2 | AH40: =IFERROR(VLOOKUP(AF40,'Cost Master List'!$B$2:$P$74,12,),0) -> 0 | AI40: =+AH40*AG40 -> 0 | AK40: R2 | AN40: =IFERROR(VLOOKUP(AL40,'Cost Master List'!$B$2:$P$74,12,),0) -> 0 | AO40: =+AN40*AM40 -> 0 | AQ40: R2 | AT40: =IFERROR(VLOOKUP(AR40,'Cost Master List'!$B$2:$P$74,12,),0) -> 0 | AU40: =+AT40*AS40 -> 0 | AW40: R2 | AZ40: =IFERROR(VLOOKUP(AX40,'Cost Master List'!$B$2:$P$74,12,),0) -> 0 | BA40: =+AZ40*AY40 -> 0
A41: R3 | D41: =IFERROR(VLOOKUP(B41,'Cost Master List'!$B$2:$P$74,12,),0) -> 0 | E41: =+D41*C41 -> 0 | G41: R3 | J41: =IFERROR(VLOOKUP(H41,'Cost Master List'!$B$2:$P$74,12,),0) -> 0 | K41: =+J41*I41 -> 0 | M41: R3 | P41: =IFERROR(VLOOKUP(N41,'Cost Master List'!$B$2:$P$74,12,),0) -> 0 | Q41: =+P41*O41 -> 0 | S41: R3 | V41: =IFERROR(VLOOKUP(T41,'Cost Master List'!$B$2:$P$74,12,),0) -> 0 | W41: =+V41*U41 -> 0 | Y41: R3 | AB41: =IFERROR(VLOOKUP(Z41,'Cost Master List'!$B$2:$P$74,12,),0) -> 0 | AC41: =+AB41*AA41 -> 0 | AE41: R3 | AH41: =IFERROR(VLOOKUP(AF41,'Cost Master List'!$B$2:$P$74,12,),0) -> 0 | AI41: =+AH41*AG41 -> 0 | AK41: R3 | AN41: =IFERROR(VLOOKUP(AL41,'Cost Master List'!$B$2:$P$74,12,),0) -> 0 | AO41: =+AN41*AM41 -> 0 | AQ41: R3 | AT41: =IFERROR(VLOOKUP(AR41,'Cost Master List'!$B$2:$P$74,12,),0) -> 0 | AU41: =+AT41*AS41 -> 0 | AW41: R3 | AZ41: =IFERROR(VLOOKUP(AX41,'Cost Master List'!$B$2:$P$74,12,),0) -> 0 | BA41: =+AZ41*AY41 -> 0
A42: R4 | D42: =IFERROR(VLOOKUP(B42,'Cost Master List'!$B$2:$P$74,12,),0) -> 0 | E42: =+D42*C42 -> 0 | G42: R4 | J42: =IFERROR(VLOOKUP(H42,'Cost Master List'!$B$2:$P$74,12,),0) -> 0 | K42: =+J42*I42 -> 0 | M42: R4 | P42: =IFERROR(VLOOKUP(N42,'Cost Master List'!$B$2:$P$74,12,),0) -> 0 | Q42: =+P42*O42 -> 0 | S42: R4 | V42: =IFERROR(VLOOKUP(T42,'Cost Master List'!$B$2:$P$74,12,),0) -> 0 | W42: =+V42*U42 -> 0 | Y42: R4 | AB42: =IFERROR(VLOOKUP(Z42,'Cost Master List'!$B$2:$P$74,12,),0) -> 0 | AC42: =+AB42*AA42 -> 0 | AE42: R4 | AH42: =IFERROR(VLOOKUP(AF42,'Cost Master List'!$B$2:$P$74,12,),0) -> 0 | AI42: =+AH42*AG42 -> 0 | AK42: R4 | AN42: =IFERROR(VLOOKUP(AL42,'Cost Master List'!$B$2:$P$74,12,),0) -> 0 | AO42: =+AN42*AM42 -> 0 | AQ42: R4 | AT42: =IFERROR(VLOOKUP(AR42,'Cost Master List'!$B$2:$P$74,12,),0) -> 0 | AU42: =+AT42*AS42 -> 0 | AW42: R4 | AZ42: =IFERROR(VLOOKUP(AX42,'Cost Master List'!$B$2:$P$74,12,),0) -> 0 | BA42: =+AZ42*AY42 -> 0
A43: R5 | D43: =IFERROR(VLOOKUP(B43,'Cost Master List'!$B$2:$P$74,12,),0) -> 0 | E43: =+D43*C43 -> 0 | G43: R5 | J43: =IFERROR(VLOOKUP(H43,'Cost Master List'!$B$2:$P$74,12,),0) -> 0 | K43: =+J43*I43 -> 0 | M43: R5 | P43: =IFERROR(VLOOKUP(N43,'Cost Master List'!$B$2:$P$74,12,),0) -> 0 | Q43: =+P43*O43 -> 0 | S43: R5 | V43: =IFERROR(VLOOKUP(T43,'Cost Master List'!$B$2:$P$74,12,),0) -> 0 | W43: =+V43*U43 -> 0 | Y43: R5 | AB43: =IFERROR(VLOOKUP(Z43,'Cost Master List'!$B$2:$P$74,12,),0) -> 0 | AC43: =+AB43*AA43 -> 0 | AE43: R5 | AH43: =IFERROR(VLOOKUP(AF43,'Cost Master List'!$B$2:$P$74,12,),0) -> 0 | AI43: =+AH43*AG43 -> 0 | AK43: R5 | AN43: =IFERROR(VLOOKUP(AL43,'Cost Master List'!$B$2:$P$74,12,),0) -> 0 | AO43: =+AN43*AM43 -> 0 | AQ43: R5 | AT43: =IFERROR(VLOOKUP(AR43,'Cost Master List'!$B$2:$P$74,12,),0) -> 0 | AU43: =+AT43*AS43 -> 0 | AW43: R5 | AZ43: =IFERROR(VLOOKUP(AX43,'Cost Master List'!$B$2:$P$74,12,),0) -> 0 | BA43: =+AZ43*AY43 -> 0
A44: P1 | B44: 1 Gallon Jug & Box Combo | D44: =IFERROR(VLOOKUP('Manufactured Items Models'!B44,'Cost Master List'!$B$84:$L$98,11,FALSE),0) -> 1.6 | E44: =+D44/$A$38 -> 0.2 | G44: P1 | J44: =IFERROR(VLOOKUP('Manufactured Items Models'!H44,'Cost Master List'!$B$84:$L$98,11,FALSE),0) -> 0 | K44: =+J44/$G$14 -> 0 | M44: P1 | P44: =IFERROR(VLOOKUP('Manufactured Items Models'!N44,'Cost Master List'!$B$84:$L$98,11,FALSE),0) -> 0 | Q44: =+P44/$G$14 -> 0 | S44: P1 | V44: =IFERROR(VLOOKUP('Manufactured Items Models'!T44,'Cost Master List'!$B$84:$L$98,11,FALSE),0) -> 0 | W44: =+V44/$G$14 -> 0 | Y44: P1 | AB44: =IFERROR(VLOOKUP('Manufactured Items Models'!Z44,'Cost Master List'!$B$84:$L$98,11,FALSE),0) -> 0 | AC44: =+AB44/$G$14 -> 0 | AE44: P1 | AH44: =IFERROR(VLOOKUP('Manufactured Items Models'!AF44,'Cost Master List'!$B$84:$L$98,11,FALSE),0) -> 0 | AI44: =+AH44/$G$14 -> 0 | AK44: P1 | AN44: =IFERROR(VLOOKUP('Manufactured Items Models'!AL44,'Cost Master List'!$B$84:$L$98,11,FALSE),0) -> 0 | AO44: =+AN44/$G$14 -> 0 | AQ44: P1 | AT44: =IFERROR(VLOOKUP('Manufactured Items Models'!AR44,'Cost Master List'!$B$84:$L$98,11,FALSE),0) -> 0 | AU44: =+AT44/$G$14 -> 0 | AW44: P1 | AZ44: =IFERROR(VLOOKUP('Manufactured Items Models'!AX44,'Cost Master List'!$B$84:$L$98,11,FALSE),0) -> 0 | BA44: =+AZ44/$G$14 -> 0
A45: P2 | D45: =IFERROR(VLOOKUP('Manufactured Items Models'!B45,'Cost Master List'!$B$84:$L$98,11,FALSE),0) -> 0 | E45: =+D45/$A$38 -> 0 | G45: P2 | J45: =IFERROR(VLOOKUP('Manufactured Items Models'!H45,'Cost Master List'!$B$84:$L$98,11,FALSE),0) -> 0 | K45: =+J45/$G$14 -> 0 | M45: P2 | P45: =IFERROR(VLOOKUP('Manufactured Items Models'!N45,'Cost Master List'!$B$84:$L$98,11,FALSE),0) -> 0 | Q45: =+P45/$G$14 -> 0 | S45: P2 | V45: =IFERROR(VLOOKUP('Manufactured Items Models'!T45,'Cost Master List'!$B$84:$L$98,11,FALSE),0) -> 0 | W45: =+V45/$G$14 -> 0 | Y45: P2 | AB45: =IFERROR(VLOOKUP('Manufactured Items Models'!Z45,'Cost Master List'!$B$84:$L$98,11,FALSE),0) -> 0 | AC45: =+AB45/$G$14 -> 0 | AE45: P2 | AH45: =IFERROR(VLOOKUP('Manufactured Items Models'!AF45,'Cost Master List'!$B$84:$L$98,11,FALSE),0) -> 0 | AI45: =+AH45/$G$14 -> 0 | AK45: P2 | AN45: =IFERROR(VLOOKUP('Manufactured Items Models'!AL45,'Cost Master List'!$B$84:$L$98,11,FALSE),0) -> 0 | AO45: =+AN45/$G$14 -> 0 | AQ45: P2 | AT45: =IFERROR(VLOOKUP('Manufactured Items Models'!AR45,'Cost Master List'!$B$84:$L$98,11,FALSE),0) -> 0 | AU45: =+AT45/$G$14 -> 0 | AW45: P2 | AZ45: =IFERROR(VLOOKUP('Manufactured Items Models'!AX45,'Cost Master List'!$B$84:$L$98,11,FALSE),0) -> 0 | BA45: =+AZ45/$G$14 -> 0
A46: P3 | D46: =IFERROR(VLOOKUP('Manufactured Items Models'!B46,'Cost Master List'!$B$84:$L$98,11,FALSE),0) -> 0 | E46: =+D46/$A$38 -> 0 | G46: P3 | J46: =IFERROR(VLOOKUP('Manufactured Items Models'!H46,'Cost Master List'!$B$84:$L$98,11,FALSE),0) -> 0 | K46: =+J46/$G$14 -> 0 | M46: P3 | P46: =IFERROR(VLOOKUP('Manufactured Items Models'!N46,'Cost Master List'!$B$84:$L$98,11,FALSE),0) -> 0 | Q46: =+P46/$G$14 -> 0 | S46: P3 | V46: =IFERROR(VLOOKUP('Manufactured Items Models'!T46,'Cost Master List'!$B$84:$L$98,11,FALSE),0) -> 0 | W46: =+V46/$G$14 -> 0 | Y46: P3 | AB46: =IFERROR(VLOOKUP('Manufactured Items Models'!Z46,'Cost Master List'!$B$84:$L$98,11,FALSE),0) -> 0 | AC46: =+AB46/$G$14 -> 0 | AE46: P3 | AH46: =IFERROR(VLOOKUP('Manufactured Items Models'!AF46,'Cost Master List'!$B$84:$L$98,11,FALSE),0) -> 0 | AI46: =+AH46/$G$14 -> 0 | AK46: P3 | AN46: =IFERROR(VLOOKUP('Manufactured Items Models'!AL46,'Cost Master List'!$B$84:$L$98,11,FALSE),0) -> 0 | AO46: =+AN46/$G$14 -> 0 | AQ46: P3 | AT46: =IFERROR(VLOOKUP('Manufactured Items Models'!AR46,'Cost Master List'!$B$84:$L$98,11,FALSE),0) -> 0 | AU46: =+AT46/$G$14 -> 0 | AW46: P3 | AZ46: =IFERROR(VLOOKUP('Manufactured Items Models'!AX46,'Cost Master List'!$B$84:$L$98,11,FALSE),0) -> 0 | BA46: =+AZ46/$G$14 -> 0
A47: Labor | E47: 1 | G47: Labor | K47: 1 | M47: Labor | Q47: 1 | S47: Labor | W47: 1 | Y47: Labor | AC47: 1 | AE47: Labor | AI47: 1 | AK47: Labor | AO47: 1 | AQ47: Labor | AU47: 1 | AW47: Labor | BA47: 1
B48: Annatto Extract P1411 (8) | D48: Cost/lb | E48: =+SUM(E39:E47) -> 2.6612949 | J48: Cost/lb | K48: =+SUM(K39:K47) -> 1 | P48: Cost/lb | Q48: =+SUM(Q39:Q47) -> 1 | V48: Cost/lb | W48: =+SUM(W39:W47) -> 1 | AB48: Cost/lb | AC48: =+SUM(AC39:AC47) -> 1 | AH48: Cost/lb | AI48: =+SUM(AI39:AI47) -> 1 | AN48: Cost/lb | AO48: =+SUM(AO39:AO47) -> 1 | AT48: Cost/lb | AU48: =+SUM(AU39:AU47) -> 1 | AZ48: Cost/lb | BA48: =+SUM(BA39:BA47) -> 1
A50: 44 | B50: Annatto Extract P1411 | C50: Composition | D50: Price/lb | E50: Formula Cost | I50: Composition | J50: Price/lb | K50: Formula Cost | O50: Composition | P50: Price/lb | Q50: Formula Cost | U50: Composition | V50: Price/lb | W50: Formula Cost | AA50: Composition | AB50: Price/lb | AC50: Formula Cost | AG50: Composition | AH50: Price/lb | AI50: Formula Cost | AM50: Composition | AN50: Price/lb | AO50: Formula Cost | AS50: Composition | AT50: Price/lb | AU50: Formula Cost | AY50: Composition | AZ50: Price/lb | BA50: Formula Cost
A51: R1 | B51: Annatto Extract WS5 (Cyber Colors) | C51: 0.21 | D51: =IFERROR(VLOOKUP(B51,'Cost Master List'!$B$2:$P$74,12,),0) -> 6.1053606 | E51: =+D51*C51 -> 1.2821257 | G51: R1 | J51: =IFERROR(VLOOKUP(H51,'Cost Master List'!$B$2:$P$74,12,),0) -> 0 | K51: =+J51*I51 -> 0 | M51: R1 | P51: =IFERROR(VLOOKUP(N51,'Cost Master List'!$B$2:$P$74,12,),0) -> 0 | Q51: =+P51*O51 -> 0 | S51: R1 | V51: =IFERROR(VLOOKUP(T51,'Cost Master List'!$B$2:$P$74,12,),0) -> 0 | W51: =+V51*U51 -> 0 | Y51: R1 | AB51: =IFERROR(VLOOKUP(Z51,'Cost Master List'!$B$2:$P$74,12,),0) -> 0 | AC51: =+AB51*AA51 -> 0 | AE51: R1 | AH51: =IFERROR(VLOOKUP(AF51,'Cost Master List'!$B$2:$P$74,12,),0) -> 0 | AI51: =+AH51*AG51 -> 0 | AK51: R1 | AN51: =IFERROR(VLOOKUP(AL51,'Cost Master List'!$B$2:$P$74,12,),0) -> 0 | AO51: =+AN51*AM51 -> 0 | AQ51: R1 | AT51: =IFERROR(VLOOKUP(AR51,'Cost Master List'!$B$2:$P$74,12,),0) -> 0 | AU51: =+AT51*AS51 -> 0 | AW51: R1 | AZ51: =IFERROR(VLOOKUP(AX51,'Cost Master List'!$B$2:$P$74,12,),0) -> 0 | BA51: =+AZ51*AY51 -> 0
A52: R2 | B52: DI Water | C52: 0.79 | D52: =IFERROR(VLOOKUP(B52,'Cost Master List'!$B$2:$P$74,12,),0) -> 0.22679645 | E52: =+D52*C52 -> 0.1791692 | G52: R2 | J52: =IFERROR(VLOOKUP(H52,'Cost Master List'!$B$2:$P$74,12,),0) -> 0 | K52: =+J52*I52 -> 0 | M52: R2 | P52: =IFERROR(VLOOKUP(N52,'Cost Master List'!$B$2:$P$74,12,),0) -> 0 | Q52: =+P52*O52 -> 0 | S52: R2 | V52: =IFERROR(VLOOKUP(T52,'Cost Master List'!$B$2:$P$74,12,),0) -> 0 | W52: =+V52*U52 -> 0 | Y52: R2 | AB52: =IFERROR(VLOOKUP(Z52,'Cost Master List'!$B$2:$P$74,12,),0) -> 0 | AC52: =+AB52*AA52 -> 0 | AE52: R2 | AH52: =IFERROR(VLOOKUP(AF52,'Cost Master List'!$B$2:$P$74,12,),0) -> 0 | AI52: =+AH52*AG52 -> 0 | AK52: R2 | AN52: =IFERROR(VLOOKUP(AL52,'Cost Master List'!$B$2:$P$74,12,),0) -> 0 | AO52: =+AN52*AM52 -> 0 | AQ52: R2 | AT52: =IFERROR(VLOOKUP(AR52,'Cost Master List'!$B$2:$P$74,12,),0) -> 0 | AU52: =+AT52*AS52 -> 0 | AW52: R2 | AZ52: =IFERROR(VLOOKUP(AX52,'Cost Master List'!$B$2:$P$74,12,),0) -> 0 | BA52: =+AZ52*AY52 -> 0
A53: R3 | D53: =IFERROR(VLOOKUP(B53,'Cost Master List'!$B$2:$P$74,12,),0) -> 0 | E53: =+D53*C53 -> 0 | G53: R3 | J53: =IFERROR(VLOOKUP(H53,'Cost Master List'!$B$2:$P$74,12,),0) -> 0 | K53: =+J53*I53 -> 0 | M53: R3 | P53: =IFERROR(VLOOKUP(N53,'Cost Master List'!$B$2:$P$74,12,),0) -> 0 | Q53: =+P53*O53 -> 0 | S53: R3 | V53: =IFERROR(VLOOKUP(T53,'Cost Master List'!$B$2:$P$74,12,),0) -> 0 | W53: =+V53*U53 -> 0 | Y53: R3 | AB53: =IFERROR(VLOOKUP(Z53,'Cost Master List'!$B$2:$P$74,12,),0) -> 0 | AC53: =+AB53*AA53 -> 0 | AE53: R3 | AH53: =IFERROR(VLOOKUP(AF53,'Cost Master List'!$B$2:$P$74,12,),0) -> 0 | AI53: =+AH53*AG53 -> 0 | AK53: R3 | AN53: =IFERROR(VLOOKUP(AL53,'Cost Master List'!$B$2:$P$74,12,),0) -> 0 | AO53: =+AN53*AM53 -> 0 | AQ53: R3 | AT53: =IFERROR(VLOOKUP(AR53,'Cost Master List'!$B$2:$P$74,12,),0) -> 0 | AU53: =+AT53*AS53 -> 0 | AW53: R3 | AZ53: =IFERROR(VLOOKUP(AX53,'Cost Master List'!$B$2:$P$74,12,),0) -> 0 | BA53: =+AZ53*AY53 -> 0
A54: R4 | D54: =IFERROR(VLOOKUP(B54,'Cost Master List'!$B$2:$P$74,12,),0) -> 0 | E54: =+D54*C54 -> 0 | G54: R4 | J54: =IFERROR(VLOOKUP(H54,'Cost Master List'!$B$2:$P$74,12,),0) -> 0 | K54: =+J54*I54 -> 0 | M54: R4 | P54: =IFERROR(VLOOKUP(N54,'Cost Master List'!$B$2:$P$74,12,),0) -> 0 | Q54: =+P54*O54 -> 0 | S54: R4 | V54: =IFERROR(VLOOKUP(T54,'Cost Master List'!$B$2:$P$74,12,),0) -> 0 | W54: =+V54*U54 -> 0 | Y54: R4 | AB54: =IFERROR(VLOOKUP(Z54,'Cost Master List'!$B$2:$P$74,12,),0) -> 0 | AC54: =+AB54*AA54 -> 0 | AE54: R4 | AH54: =IFERROR(VLOOKUP(AF54,'Cost Master List'!$B$2:$P$74,12,),0) -> 0 | AI54: =+AH54*AG54 -> 0 | AK54: R4 | AN54: =IFERROR(VLOOKUP(AL54,'Cost Master List'!$B$2:$P$74,12,),0) -> 0 | AO54: =+AN54*AM54 -> 0 | AQ54: R4 | AT54: =IFERROR(VLOOKUP(AR54,'Cost Master List'!$B$2:$P$74,12,),0) -> 0 | AU54: =+AT54*AS54 -> 0 | AW54: R4 | AZ54: =IFERROR(VLOOKUP(AX54,'Cost Master List'!$B$2:$P$74,12,),0) -> 0 | BA54: =+AZ54*AY54 -> 0
A55: R5 | D55: =IFERROR(VLOOKUP(B55,'Cost Master List'!$B$2:$P$74,12,),0) -> 0 | E55: =+D55*C55 -> 0 | G55: R5 | J55: =IFERROR(VLOOKUP(H55,'Cost Master List'!$B$2:$P$74,12,),0) -> 0 | K55: =+J55*I55 -> 0 | M55: R5 | P55: =IFERROR(VLOOKUP(N55,'Cost Master List'!$B$2:$P$74,12,),0) -> 0 | Q55: =+P55*O55 -> 0 | S55: R5 | V55: =IFERROR(VLOOKUP(T55,'Cost Master List'!$B$2:$P$74,12,),0) -> 0 | W55: =+V55*U55 -> 0 | Y55: R5 | AB55: =IFERROR(VLOOKUP(Z55,'Cost Master List'!$B$2:$P$74,12,),0) -> 0 | AC55: =+AB55*AA55 -> 0 | AE55: R5 | AH55: =IFERROR(VLOOKUP(AF55,'Cost Master List'!$B$2:$P$74,12,),0) -> 0 | AI55: =+AH55*AG55 -> 0 | AK55: R5 | AN55: =IFERROR(VLOOKUP(AL55,'Cost Master List'!$B$2:$P$74,12,),0) -> 0 | AO55: =+AN55*AM55 -> 0 | AQ55: R5 | AT55: =IFERROR(VLOOKUP(AR55,'Cost Master List'!$B$2:$P$74,12,),0) -> 0 | AU55: =+AT55*AS55 -> 0 | AW55: R5 | AZ55: =IFERROR(VLOOKUP(AX55,'Cost Master List'!$B$2:$P$74,12,),0) -> 0 | BA55: =+AZ55*AY55 -> 0
A56: P1 | B56: 5 Gallon Pails | D56: =IFERROR(VLOOKUP('Manufactured Items Models'!B56,'Cost Master List'!$B$84:$L$98,11,FALSE),0) -> 9.68 | E56: =+D56/$A$50 -> 0.22 | G56: P1 | J56: =IFERROR(VLOOKUP('Manufactured Items Models'!H56,'Cost Master List'!$B$84:$L$98,11,FALSE),0) -> 0 | K56: =+J56/$G$14 -> 0 | M56: P1 | P56: =IFERROR(VLOOKUP('Manufactured Items Models'!N56,'Cost Master List'!$B$84:$L$98,11,FALSE),0) -> 0 | Q56: =+P56/$G$14 -> 0 | S56: P1 | V56: =IFERROR(VLOOKUP('Manufactured Items Models'!T56,'Cost Master List'!$B$84:$L$98,11,FALSE),0) -> 0 | W56: =+V56/$G$14 -> 0 | Y56: P1 | AB56: =IFERROR(VLOOKUP('Manufactured Items Models'!Z56,'Cost Master List'!$B$84:$L$98,11,FALSE),0) -> 0 | AC56: =+AB56/$G$14 -> 0 | AE56: P1 | AH56: =IFERROR(VLOOKUP('Manufactured Items Models'!AF56,'Cost Master List'!$B$84:$L$98,11,FALSE),0) -> 0 | AI56: =+AH56/$G$14 -> 0 | AK56: P1 | AN56: =IFERROR(VLOOKUP('Manufactured Items Models'!AL56,'Cost Master List'!$B$84:$L$98,11,FALSE),0) -> 0 | AO56: =+AN56/$G$14 -> 0 | AQ56: P1 | AT56: =IFERROR(VLOOKUP('Manufactured Items Models'!AR56,'Cost Master List'!$B$84:$L$98,11,FALSE),0) -> 0 | AU56: =+AT56/$G$14 -> 0 | AW56: P1 | AZ56: =IFERROR(VLOOKUP('Manufactured Items Models'!AX56,'Cost Master List'!$B$84:$L$98,11,FALSE),0) -> 0 | BA56: =+AZ56/$G$14 -> 0
A57: P2 | D57: =IFERROR(VLOOKUP('Manufactured Items Models'!B57,'Cost Master List'!$B$84:$L$98,11,FALSE),0) -> 0 | E57: =+D57/$A$50 -> 0 | G57: P2 | J57: =IFERROR(VLOOKUP('Manufactured Items Models'!H57,'Cost Master List'!$B$84:$L$98,11,FALSE),0) -> 0 | K57: =+J57/$G$14 -> 0 | M57: P2 | P57: =IFERROR(VLOOKUP('Manufactured Items Models'!N57,'Cost Master List'!$B$84:$L$98,11,FALSE),0) -> 0 | Q57: =+P57/$G$14 -> 0 | S57: P2 | V57: =IFERROR(VLOOKUP('Manufactured Items Models'!T57,'Cost Master List'!$B$84:$L$98,11,FALSE),0) -> 0 | W57: =+V57/$G$14 -> 0 | Y57: P2 | AB57: =IFERROR(VLOOKUP('Manufactured Items Models'!Z57,'Cost Master List'!$B$84:$L$98,11,FALSE),0) -> 0 | AC57: =+AB57/$G$14 -> 0 | AE57: P2 | AH57: =IFERROR(VLOOKUP('Manufactured Items Models'!AF57,'Cost Master List'!$B$84:$L$98,11,FALSE),0) -> 0 | AI57: =+AH57/$G$14 -> 0 | AK57: P2 | AN57: =IFERROR(VLOOKUP('Manufactured Items Models'!AL57,'Cost Master List'!$B$84:$L$98,11,FALSE),0) -> 0 | AO57: =+AN57/$G$14 -> 0 | AQ57: P2 | AT57: =IFERROR(VLOOKUP('Manufactured Items Models'!AR57,'Cost Master List'!$B$84:$L$98,11,FALSE),0) -> 0 | AU57: =+AT57/$G$14 -> 0 | AW57: P2 | AZ57: =IFERROR(VLOOKUP('Manufactured Items Models'!AX57,'Cost Master List'!$B$84:$L$98,11,FALSE),0) -> 0 | BA57: =+AZ57/$G$14 -> 0
A58: P3 | D58: =IFERROR(VLOOKUP('Manufactured Items Models'!B58,'Cost Master List'!$B$84:$L$98,11,FALSE),0) -> 0 | E58: =+D58/$A$50 -> 0 | G58: P3 | J58: =IFERROR(VLOOKUP('Manufactured Items Models'!H58,'Cost Master List'!$B$84:$L$98,11,FALSE),0) -> 0 | K58: =+J58/$G$14 -> 0 | M58: P3 | P58: =IFERROR(VLOOKUP('Manufactured Items Models'!N58,'Cost Master List'!$B$84:$L$98,11,FALSE),0) -> 0 | Q58: =+P58/$G$14 -> 0 | S58: P3 | V58: =IFERROR(VLOOKUP('Manufactured Items Models'!T58,'Cost Master List'!$B$84:$L$98,11,FALSE),0) -> 0 | W58: =+V58/$G$14 -> 0 | Y58: P3 | AB58: =IFERROR(VLOOKUP('Manufactured Items Models'!Z58,'Cost Master List'!$B$84:$L$98,11,FALSE),0) -> 0 | AC58: =+AB58/$G$14 -> 0 | AE58: P3 | AH58: =IFERROR(VLOOKUP('Manufactured Items Models'!AF58,'Cost Master List'!$B$84:$L$98,11,FALSE),0) -> 0 | AI58: =+AH58/$G$14 -> 0 | AK58: P3 | AN58: =IFERROR(VLOOKUP('Manufactured Items Models'!AL58,'Cost Master List'!$B$84:$L$98,11,FALSE),0) -> 0 | AO58: =+AN58/$G$14 -> 0 | AQ58: P3 | AT58: =IFERROR(VLOOKUP('Manufactured Items Models'!AR58,'Cost Master List'!$B$84:$L$98,11,FALSE),0) -> 0 | AU58: =+AT58/$G$14 -> 0 | AW58: P3 | AZ58: =IFERROR(VLOOKUP('Manufactured Items Models'!AX58,'Cost Master List'!$B$84:$L$98,11,FALSE),0) -> 0 | BA58: =+AZ58/$G$14 -> 0
A59: Labor | E59: 1 | G59: Labor | K59: 1 | M59: Labor | Q59: 1 | S59: Labor | W59: 1 | Y59: Labor | AC59: 1 | AE59: Labor | AI59: 1 | AK59: Labor | AO59: 1 | AQ59: Labor | AU59: 1 | AW59: Labor | BA59: 1
B60: Annatto Extract P1411 (44) | D60: Cost/lb | E60: =+SUM(E51:E59) -> 2.6812949 | J60: Cost/lb | K60: =+SUM(K51:K59) -> 1 | P60: Cost/lb | Q60: =+SUM(Q51:Q59) -> 1 | V60: Cost/lb | W60: =+SUM(W51:W59) -> 1 | AB60: Cost/lb | AC60: =+SUM(AC51:AC59) -> 1 | AH60: Cost/lb | AI60: =+SUM(AI51:AI59) -> 1 | AN60: Cost/lb | AO60: =+SUM(AO51:AO59) -> 1 | AT60: Cost/lb | AU60: =+SUM(AU51:AU59) -> 1 | AZ60: Cost/lb | BA60: =+SUM(BA51:BA59) -> 1
A62: 8 | B62: Annatto Extract P1414 | C62: Composition | D62: Price/lb | E62: Formula Cost | I62: Composition | J62: Price/lb | K62: Formula Cost | O62: Composition | P62: Price/lb | Q62: Formula Cost | U62: Composition | V62: Price/lb | W62: Formula Cost | AA62: Composition | AB62: Price/lb | AC62: Formula Cost | AG62: Composition | AH62: Price/lb | AI62: Formula Cost | AM62: Composition | AN62: Price/lb | AO62: Formula Cost | AS62: Composition | AT62: Price/lb | AU62: Formula Cost | AY62: Composition | AZ62: Price/lb | BA62: Formula Cost
A63: R1 | B63: Annatto Extract WS5 (Cyber Colors) | C63: 0.27 | D63: =IFERROR(VLOOKUP(B63,'Cost Master List'!$B$2:$P$74,12,),0) -> 6.1053606 | E63: =+D63*C63 -> 1.6484474 | G63: R1 | J63: =IFERROR(VLOOKUP(H63,'Cost Master List'!$B$2:$P$74,12,),0) -> 0 | K63: =+J63*I63 -> 0 | M63: R1 | P63: =IFERROR(VLOOKUP(N63,'Cost Master List'!$B$2:$P$74,12,),0) -> 0 | Q63: =+P63*O63 -> 0 | S63: R1 | V63: =IFERROR(VLOOKUP(T63,'Cost Master List'!$B$2:$P$74,12,),0) -> 0 | W63: =+V63*U63 -> 0 | Y63: R1 | AB63: =IFERROR(VLOOKUP(Z63,'Cost Master List'!$B$2:$P$74,12,),0) -> 0 | AC63: =+AB63*AA63 -> 0 | AE63: R1 | AH63: =IFERROR(VLOOKUP(AF63,'Cost Master List'!$B$2:$P$74,12,),0) -> 0 | AI63: =+AH63*AG63 -> 0 | AK63: R1 | AN63: =IFERROR(VLOOKUP(AL63,'Cost Master List'!$B$2:$P$74,12,),0) -> 0 | AO63: =+AN63*AM63 -> 0 | AQ63: R1 | AT63: =IFERROR(VLOOKUP(AR63,'Cost Master List'!$B$2:$P$74,12,),0) -> 0 | AU63: =+AT63*AS63 -> 0 | AW63: R1 | AZ63: =IFERROR(VLOOKUP(AX63,'Cost Master List'!$B$2:$P$74,12,),0) -> 0 | BA63: =+AZ63*AY63 -> 0
A64: R2 | B64: DI Water | C64: 0.73 | D64: =IFERROR(VLOOKUP(B64,'Cost Master List'!$B$2:$P$74,12,),0) -> 0.22679645 | E64: =+D64*C64 -> 0.16556141 | G64: R2 | J64: =IFERROR(VLOOKUP(H64,'Cost Master List'!$B$2:$P$74,12,),0) -> 0 | K64: =+J64*I64 -> 0 | M64: R2 | P64: =IFERROR(VLOOKUP(N64,'Cost Master List'!$B$2:$P$74,12,),0) -> 0 | Q64: =+P64*O64 -> 0 | S64: R2 | V64: =IFERROR(VLOOKUP(T64,'Cost Master List'!$B$2:$P$74,12,),0) -> 0 | W64: =+V64*U64 -> 0 | Y64: R2 | AB64: =IFERROR(VLOOKUP(Z64,'Cost Master List'!$B$2:$P$74,12,),0) -> 0 | AC64: =+AB64*AA64 -> 0 | AE64: R2 | AH64: =IFERROR(VLOOKUP(AF64,'Cost Master List'!$B$2:$P$74,12,),0) -> 0 | AI64: =+AH64*AG64 -> 0 | AK64: R2 | AN64: =IFERROR(VLOOKUP(AL64,'Cost Master List'!$B$2:$P$74,12,),0) -> 0 | AO64: =+AN64*AM64 -> 0 | AQ64: R2 | AT64: =IFERROR(VLOOKUP(AR64,'Cost Master List'!$B$2:$P$74,12,),0) -> 0 | AU64: =+AT64*AS64 -> 0 | AW64: R2 | AZ64: =IFERROR(VLOOKUP(AX64,'Cost Master List'!$B$2:$P$74,12,),0) -> 0 | BA64: =+AZ64*AY64 -> 0
A65: R3 | D65: =IFERROR(VLOOKUP(B65,'Cost Master List'!$B$2:$P$74,12,),0) -> 0 | E65: =+D65*C65 -> 0 | G65: R3 | J65: =IFERROR(VLOOKUP(H65,'Cost Master List'!$B$2:$P$74,12,),0) -> 0 | K65: =+J65*I65 -> 0 | M65: R3 | P65: =IFERROR(VLOOKUP(N65,'Cost Master List'!$B$2:$P$74,12,),0) -> 0 | Q65: =+P65*O65 -> 0 | S65: R3 | V65: =IFERROR(VLOOKUP(T65,'Cost Master List'!$B$2:$P$74,12,),0) -> 0 | W65: =+V65*U65 -> 0 | Y65: R3 | AB65: =IFERROR(VLOOKUP(Z65,'Cost Master List'!$B$2:$P$74,12,),0) -> 0 | AC65: =+AB65*AA65 -> 0 | AE65: R3 | AH65: =IFERROR(VLOOKUP(AF65,'Cost Master List'!$B$2:$P$74,12,),0) -> 0 | AI65: =+AH65*AG65 -> 0 | AK65: R3 | AN65: =IFERROR(VLOOKUP(AL65,'Cost Master List'!$B$2:$P$74,12,),0) -> 0 | AO65: =+AN65*AM65 -> 0 | AQ65: R3 | AT65: =IFERROR(VLOOKUP(AR65,'Cost Master List'!$B$2:$P$74,12,),0) -> 0 | AU65: =+AT65*AS65 -> 0 | AW65: R3 | AZ65: =IFERROR(VLOOKUP(AX65,'Cost Master List'!$B$2:$P$74,12,),0) -> 0 | BA65: =+AZ65*AY65 -> 0
A66: R4 | D66: =IFERROR(VLOOKUP(B66,'Cost Master List'!$B$2:$P$74,12,),0) -> 0 | E66: =+D66*C66 -> 0 | G66: R4 | J66: =IFERROR(VLOOKUP(H66,'Cost Master List'!$B$2:$P$74,12,),0) -> 0 | K66: =+J66*I66 -> 0 | M66: R4 | P66: =IFERROR(VLOOKUP(N66,'Cost Master List'!$B$2:$P$74,12,),0) -> 0 | Q66: =+P66*O66 -> 0 | S66: R4 | V66: =IFERROR(VLOOKUP(T66,'Cost Master List'!$B$2:$P$74,12,),0) -> 0 | W66: =+V66*U66 -> 0 | Y66: R4 | AB66: =IFERROR(VLOOKUP(Z66,'Cost Master List'!$B$2:$P$74,12,),0) -> 0 | AC66: =+AB66*AA66 -> 0 | AE66: R4 | AH66: =IFERROR(VLOOKUP(AF66,'Cost Master List'!$B$2:$P$74,12,),0) -> 0 | AI66: =+AH66*AG66 -> 0 | AK66: R4 | AN66: =IFERROR(VLOOKUP(AL66,'Cost Master List'!$B$2:$P$74,12,),0) -> 0 | AO66: =+AN66*AM66 -> 0 | AQ66: R4 | AT66: =IFERROR(VLOOKUP(AR66,'Cost Master List'!$B$2:$P$74,12,),0) -> 0 | AU66: =+AT66*AS66 -> 0 | AW66: R4 | AZ66: =IFERROR(VLOOKUP(AX66,'Cost Master List'!$B$2:$P$74,12,),0) -> 0 | BA66: =+AZ66*AY66 -> 0
A67: R5 | D67: =IFERROR(VLOOKUP(B67,'Cost Master List'!$B$2:$P$74,12,),0) -> 0 | E67: =+D67*C67 -> 0 | G67: R5 | J67: =IFERROR(VLOOKUP(H67,'Cost Master List'!$B$2:$P$74,12,),0) -> 0 | K67: =+J67*I67 -> 0 | M67: R5 | P67: =IFERROR(VLOOKUP(N67,'Cost Master List'!$B$2:$P$74,12,),0) -> 0 | Q67: =+P67*O67 -> 0 | S67: R5 | V67: =IFERROR(VLOOKUP(T67,'Cost Master List'!$B$2:$P$74,12,),0) -> 0 | W67: =+V67*U67 -> 0 | Y67: R5 | AB67: =IFERROR(VLOOKUP(Z67,'Cost Master List'!$B$2:$P$74,12,),0) -> 0 | AC67: =+AB67*AA67 -> 0 | AE67: R5 | AH67: =IFERROR(VLOOKUP(AF67,'Cost Master List'!$B$2:$P$74,12,),0) -> 0 | AI67: =+AH67*AG67 -> 0 | AK67: R5 | AN67: =IFERROR(VLOOKUP(AL67,'Cost Master List'!$B$2:$P$74,12,),0) -> 0 | AO67: =+AN67*AM67 -> 0 | AQ67: R5 | AT67: =IFERROR(VLOOKUP(AR67,'Cost Master List'!$B$2:$P$74,12,),0) -> 0 | AU67: =+AT67*AS67 -> 0 | AW67: R5 | AZ67: =IFERROR(VLOOKUP(AX67,'Cost Master List'!$B$2:$P$74,12,),0) -> 0 | BA67: =+AZ67*AY67 -> 0
A68: P1 | B68: 1 Gallon Jug & Box Combo | D68: =IFERROR(VLOOKUP('Manufactured Items Models'!B68,'Cost Master List'!$B$84:$L$98,11,FALSE),0) -> 1.6 | E68: =+D68/$A$62 -> 0.2 | G68: P1 | J68: =IFERROR(VLOOKUP('Manufactured Items Models'!H68,'Cost Master List'!$B$84:$L$98,11,FALSE),0) -> 0 | K68: =+J68/$G$14 -> 0 | M68: P1 | P68: =IFERROR(VLOOKUP('Manufactured Items Models'!N68,'Cost Master List'!$B$84:$L$98,11,FALSE),0) -> 0 | Q68: =+P68/$G$14 -> 0 | S68: P1 | V68: =IFERROR(VLOOKUP('Manufactured Items Models'!T68,'Cost Master List'!$B$84:$L$98,11,FALSE),0) -> 0 | W68: =+V68/$G$14 -> 0 | Y68: P1 | AB68: =IFERROR(VLOOKUP('Manufactured Items Models'!Z68,'Cost Master List'!$B$84:$L$98,11,FALSE),0) -> 0 | AC68: =+AB68/$G$14 -> 0 | AE68: P1 | AH68: =IFERROR(VLOOKUP('Manufactured Items Models'!AF68,'Cost Master List'!$B$84:$L$98,11,FALSE),0) -> 0 | AI68: =+AH68/$G$14 -> 0 | AK68: P1 | AN68: =IFERROR(VLOOKUP('Manufactured Items Models'!AL68,'Cost Master List'!$B$84:$L$98,11,FALSE),0) -> 0 | AO68: =+AN68/$G$14 -> 0 | AQ68: P1 | AT68: =IFERROR(VLOOKUP('Manufactured Items Models'!AR68,'Cost Master List'!$B$84:$L$98,11,FALSE),0) -> 0 | AU68: =+AT68/$G$14 -> 0 | AW68: P1 | AZ68: =IFERROR(VLOOKUP('Manufactured Items Models'!AX68,'Cost Master List'!$B$84:$L$98,11,FALSE),0) -> 0 | BA68: =+AZ68/$G$14 -> 0
A69: P2 | D69: =IFERROR(VLOOKUP('Manufactured Items Models'!B69,'Cost Master List'!$B$84:$L$98,11,FALSE),0) -> 0 | E69: =+D69/$A$62 -> 0 | G69: P2 | J69: =IFERROR(VLOOKUP('Manufactured Items Models'!H69,'Cost Master List'!$B$84:$L$98,11,FALSE),0) -> 0 | K69: =+J69/$G$14 -> 0 | M69: P2 | P69: =IFERROR(VLOOKUP('Manufactured Items Models'!N69,'Cost Master List'!$B$84:$L$98,11,FALSE),0) -> 0 | Q69: =+P69/$G$14 -> 0 | S69: P2 | V69: =IFERROR(VLOOKUP('Manufactured Items Models'!T69,'Cost Master List'!$B$84:$L$98,11,FALSE),0) -> 0 | W69: =+V69/$G$14 -> 0 | Y69: P2 | AB69: =IFERROR(VLOOKUP('Manufactured Items Models'!Z69,'Cost Master List'!$B$84:$L$98,11,FALSE),0) -> 0 | AC69: =+AB69/$G$14 -> 0 | AE69: P2 | AH69: =IFERROR(VLOOKUP('Manufactured Items Models'!AF69,'Cost Master List'!$B$84:$L$98,11,FALSE),0) -> 0 | AI69: =+AH69/$G$14 -> 0 | AK69: P2 | AN69: =IFERROR(VLOOKUP('Manufactured Items Models'!AL69,'Cost Master List'!$B$84:$L$98,11,FALSE),0) -> 0 | AO69: =+AN69/$G$14 -> 0 | AQ69: P2 | AT69: =IFERROR(VLOOKUP('Manufactured Items Models'!AR69,'Cost Master List'!$B$84:$L$98,11,FALSE),0) -> 0 | AU69: =+AT69/$G$14 -> 0 | AW69: P2 | AZ69: =IFERROR(VLOOKUP('Manufactured Items Models'!AX69,'Cost Master List'!$B$84:$L$98,11,FALSE),0) -> 0 | BA69: =+AZ69/$G$14 -> 0
A70: P3 | D70: =IFERROR(VLOOKUP('Manufactured Items Models'!B70,'Cost Master List'!$B$84:$L$98,11,FALSE),0) -> 0 | E70: =+D70/$A$62 -> 0 | G70: P3 | J70: =IFERROR(VLOOKUP('Manufactured Items Models'!H70,'Cost Master List'!$B$84:$L$98,11,FALSE),0) -> 0 | K70: =+J70/$G$14 -> 0 | M70: P3 | P70: =IFERROR(VLOOKUP('Manufactured Items Models'!N70,'Cost Master List'!$B$84:$L$98,11,FALSE),0) -> 0 | Q70: =+P70/$G$14 -> 0 | S70: P3 | V70: =IFERROR(VLOOKUP('Manufactured Items Models'!T70,'Cost Master List'!$B$84:$L$98,11,FALSE),0) -> 0 | W70: =+V70/$G$14 -> 0 | Y70: P3 | AB70: =IFERROR(VLOOKUP('Manufactured Items Models'!Z70,'Cost Master List'!$B$84:$L$98,11,FALSE),0) -> 0 | AC70: =+AB70/$G$14 -> 0 | AE70: P3 | AH70: =IFERROR(VLOOKUP('Manufactured Items Models'!AF70,'Cost Master List'!$B$84:$L$98,11,FALSE),0) -> 0 | AI70: =+AH70/$G$14 -> 0 | AK70: P3 | AN70: =IFERROR(VLOOKUP('Manufactured Items Models'!AL70,'Cost Master List'!$B$84:$L$98,11,FALSE),0) -> 0 | AO70: =+AN70/$G$14 -> 0 | AQ70: P3 | AT70: =IFERROR(VLOOKUP('Manufactured Items Models'!AR70,'Cost Master List'!$B$84:$L$98,11,FALSE),0) -> 0 | AU70: =+AT70/$G$14 -> 0 | AW70: P3 | AZ70: =IFERROR(VLOOKUP('Manufactured Items Models'!AX70,'Cost Master List'!$B$84:$L$98,11,FALSE),0) -> 0 | BA70: =+AZ70/$G$14 -> 0
A71: Labor | E71: 1 | G71: Labor | K71: 1 | M71: Labor | Q71: 1 | S71: Labor | W71: 1 | Y71: Labor | AC71: 1 | AE71: Labor | AI71: 1 | AK71: Labor | AO71: 1 | AQ71: Labor | AU71: 1 | AW71: Labor | BA71: 1
B72: Annatto Extract P1414 (8) | D72: Cost/lb | E72: =+SUM(E63:E71) -> 3.0140088 | J72: Cost/lb | K72: =+SUM(K63:K71) -> 1 | P72: Cost/lb | Q72: =+SUM(Q63:Q71) -> 1 | V72: Cost/lb | W72: =+SUM(W63:W71) -> 1 | AB72: Cost/lb | AC72: =+SUM(AC63:AC71) -> 1 | AH72: Cost/lb | AI72: =+SUM(AI63:AI71) -> 1 | AN72: Cost/lb | AO72: =+SUM(AO63:AO71) -> 1 | AT72: Cost/lb | AU72: =+SUM(AU63:AU71) -> 1 | AZ72: Cost/lb | BA72: =+SUM(BA63:BA71) -> 1
A74: 44 | B74: Annatto Extract P1414 | C74: Composition | D74: Price/lb | E74: Formula Cost | I74: Composition | J74: Price/lb | K74: Formula Cost | O74: Composition | P74: Price/lb | Q74: Formula Cost | U74: Composition | V74: Price/lb | W74: Formula Cost | AA74: Composition | AB74: Price/lb | AC74: Formula Cost | AG74: Composition | AH74: Price/lb | AI74: Formula Cost | AM74: Composition | AN74: Price/lb | AO74: Formula Cost | AS74: Composition | AT74: Price/lb | AU74: Formula Cost | AY74: Composition | AZ74: Price/lb | BA74: Formula Cost
A75: R1 | B75: Annatto Extract WS5 (Cyber Colors) | C75: 0.27 | D75: =IFERROR(VLOOKUP(B75,'Cost Master List'!$B$2:$P$74,12,),0) -> 6.1053606 | E75: =+D75*C75 -> 1.6484474 | G75: R1 | J75: =IFERROR(VLOOKUP(H75,'Cost Master List'!$B$2:$P$74,12,),0) -> 0 | K75: =+J75*I75 -> 0 | M75: R1 | P75: =IFERROR(VLOOKUP(N75,'Cost Master List'!$B$2:$P$74,12,),0) -> 0 | Q75: =+P75*O75 -> 0 | S75: R1 | V75: =IFERROR(VLOOKUP(T75,'Cost Master List'!$B$2:$P$74,12,),0) -> 0 | W75: =+V75*U75 -> 0 | Y75: R1 | AB75: =IFERROR(VLOOKUP(Z75,'Cost Master List'!$B$2:$P$74,12,),0) -> 0 | AC75: =+AB75*AA75 -> 0 | AE75: R1 | AH75: =IFERROR(VLOOKUP(AF75,'Cost Master List'!$B$2:$P$74,12,),0) -> 0 | AI75: =+AH75*AG75 -> 0 | AK75: R1 | AN75: =IFERROR(VLOOKUP(AL75,'Cost Master List'!$B$2:$P$74,12,),0) -> 0 | AO75: =+AN75*AM75 -> 0 | AQ75: R1 | AT75: =IFERROR(VLOOKUP(AR75,'Cost Master List'!$B$2:$P$74,12,),0) -> 0 | AU75: =+AT75*AS75 -> 0 | AW75: R1 | AZ75: =IFERROR(VLOOKUP(AX75,'Cost Master List'!$B$2:$P$74,12,),0) -> 0 | BA75: =+AZ75*AY75 -> 0
A76: R2 | B76: DI Water | C76: 0.73 | D76: =IFERROR(VLOOKUP(B76,'Cost Master List'!$B$2:$P$74,12,),0) -> 0.22679645 | E76: =+D76*C76 -> 0.16556141 | G76: R2 | J76: =IFERROR(VLOOKUP(H76,'Cost Master List'!$B$2:$P$74,12,),0) -> 0 | K76: =+J76*I76 -> 0 | M76: R2 | P76: =IFERROR(VLOOKUP(N76,'Cost Master List'!$B$2:$P$74,12,),0) -> 0 | Q76: =+P76*O76 -> 0 | S76: R2 | V76: =IFERROR(VLOOKUP(T76,'Cost Master List'!$B$2:$P$74,12,),0) -> 0 | W76: =+V76*U76 -> 0 | Y76: R2 | AB76: =IFERROR(VLOOKUP(Z76,'Cost Master List'!$B$2:$P$74,12,),0) -> 0 | AC76: =+AB76*AA76 -> 0 | AE76: R2 | AH76: =IFERROR(VLOOKUP(AF76,'Cost Master List'!$B$2:$P$74,12,),0) -> 0 | AI76: =+AH76*AG76 -> 0 | AK76: R2 | AN76: =IFERROR(VLOOKUP(AL76,'Cost Master List'!$B$2:$P$74,12,),0) -> 0 | AO76: =+AN76*AM76 -> 0 | AQ76: R2 | AT76: =IFERROR(VLOOKUP(AR76,'Cost Master List'!$B$2:$P$74,12,),0) -> 0 | AU76: =+AT76*AS76 -> 0 | AW76: R2 | AZ76: =IFERROR(VLOOKUP(AX76,'Cost Master List'!$B$2:$P$74,12,),0) -> 0 | BA76: =+AZ76*AY76 -> 0
A77: R3 | D77: =IFERROR(VLOOKUP(B77,'Cost Master List'!$B$2:$P$74,12,),0) -> 0 | E77: =+D77*C77 -> 0 | G77: R3 | J77: =IFERROR(VLOOKUP(H77,'Cost Master List'!$B$2:$P$74,12,),0) -> 0 | K77: =+J77*I77 -> 0 | M77: R3 | P77: =IFERROR(VLOOKUP(N77,'Cost Master List'!$B$2:$P$74,12,),0) -> 0 | Q77: =+P77*O77 -> 0 | S77: R3 | V77: =IFERROR(VLOOKUP(T77,'Cost Master List'!$B$2:$P$74,12,),0) -> 0 | W77: =+V77*U77 -> 0 | Y77: R3 | AB77: =IFERROR(VLOOKUP(Z77,'Cost Master List'!$B$2:$P$74,12,),0) -> 0 | AC77: =+AB77*AA77 -> 0 | AE77: R3 | AH77: =IFERROR(VLOOKUP(AF77,'Cost Master List'!$B$2:$P$74,12,),0) -> 0 | AI77: =+AH77*AG77 -> 0 | AK77: R3 | AN77: =IFERROR(VLOOKUP(AL77,'Cost Master List'!$B$2:$P$74,12,),0) -> 0 | AO77: =+AN77*AM77 -> 0 | AQ77: R3 | AT77: =IFERROR(VLOOKUP(AR77,'Cost Master List'!$B$2:$P$74,12,),0) -> 0 | AU77: =+AT77*AS77 -> 0 | AW77: R3 | AZ77: =IFERROR(VLOOKUP(AX77,'Cost Master List'!$B$2:$P$74,12,),0) -> 0 | BA77: =+AZ77*AY77 -> 0
A78: R4 | D78: =IFERROR(VLOOKUP(B78,'Cost Master List'!$B$2:$P$74,12,),0) -> 0 | E78: =+D78*C78 -> 0 | G78: R4 | J78: =IFERROR(VLOOKUP(H78,'Cost Master List'!$B$2:$P$74,12,),0) -> 0 | K78: =+J78*I78 -> 0 | M78: R4 | P78: =IFERROR(VLOOKUP(N78,'Cost Master List'!$B$2:$P$74,12,),0) -> 0 | Q78: =+P78*O78 -> 0 | S78: R4 | V78: =IFERROR(VLOOKUP(T78,'Cost Master List'!$B$2:$P$74,12,),0) -> 0 | W78: =+V78*U78 -> 0 | Y78: R4 | AB78: =IFERROR(VLOOKUP(Z78,'Cost Master List'!$B$2:$P$74,12,),0) -> 0 | AC78: =+AB78*AA78 -> 0 | AE78: R4 | AH78: =IFERROR(VLOOKUP(AF78,'Cost Master List'!$B$2:$P$74,12,),0) -> 0 | AI78: =+AH78*AG78 -> 0 | AK78: R4 | AN78: =IFERROR(VLOOKUP(AL78,'Cost Master List'!$B$2:$P$74,12,),0) -> 0 | AO78: =+AN78*AM78 -> 0 | AQ78: R4 | AT78: =IFERROR(VLOOKUP(AR78,'Cost Master List'!$B$2:$P$74,12,),0) -> 0 | AU78: =+AT78*AS78 -> 0 | AW78: R4 | AZ78: =IFERROR(VLOOKUP(AX78,'Cost Master List'!$B$2:$P$74,12,),0) -> 0 | BA78: =+AZ78*AY78 -> 0
A79: R5 | D79: =IFERROR(VLOOKUP(B79,'Cost Master List'!$B$2:$P$74,12,),0) -> 0 | E79: =+D79*C79 -> 0 | G79: R5 | J79: =IFERROR(VLOOKUP(H79,'Cost Master List'!$B$2:$P$74,12,),0) -> 0 | K79: =+J79*I79 -> 0 | M79: R5 | P79: =IFERROR(VLOOKUP(N79,'Cost Master List'!$B$2:$P$74,12,),0) -> 0 | Q79: =+P79*O79 -> 0 | S79: R5 | V79: =IFERROR(VLOOKUP(T79,'Cost Master List'!$B$2:$P$74,12,),0) -> 0 | W79: =+V79*U79 -> 0 | Y79: R5 | AB79: =IFERROR(VLOOKUP(Z79,'Cost Master List'!$B$2:$P$74,12,),0) -> 0 | AC79: =+AB79*AA79 -> 0 | AE79: R5 | AH79: =IFERROR(VLOOKUP(AF79,'Cost Master List'!$B$2:$P$74,12,),0) -> 0 | AI79: =+AH79*AG79 -> 0 | AK79: R5 | AN79: =IFERROR(VLOOKUP(AL79,'Cost Master List'!$B$2:$P$74,12,),0) -> 0 | AO79: =+AN79*AM79 -> 0 | AQ79: R5 | AT79: =IFERROR(VLOOKUP(AR79,'Cost Master List'!$B$2:$P$74,12,),0) -> 0 | AU79: =+AT79*AS79 -> 0 | AW79: R5 | AZ79: =IFERROR(VLOOKUP(AX79,'Cost Master List'!$B$2:$P$74,12,),0) -> 0 | BA79: =+AZ79*AY79 -> 0
A80: P1 | B80: 1 Gallon Jug & Box Combo | D80: =IFERROR(VLOOKUP('Manufactured Items Models'!B80,'Cost Master List'!$B$84:$L$98,11,FALSE),0) -> 1.6 | E80: =+D80/$A$74 -> 0.036363636 | G80: P1 | J80: =IFERROR(VLOOKUP('Manufactured Items Models'!H80,'Cost Master List'!$B$84:$L$98,11,FALSE),0) -> 0 | K80: =+J80/$G$14 -> 0 | M80: P1 | P80: =IFERROR(VLOOKUP('Manufactured Items Models'!N80,'Cost Master List'!$B$84:$L$98,11,FALSE),0) -> 0 | Q80: =+P80/$G$14 -> 0 | S80: P1 | V80: =IFERROR(VLOOKUP('Manufactured Items Models'!T80,'Cost Master List'!$B$84:$L$98,11,FALSE),0) -> 0 | W80: =+V80/$G$14 -> 0 | Y80: P1 | AB80: =IFERROR(VLOOKUP('Manufactured Items Models'!Z80,'Cost Master List'!$B$84:$L$98,11,FALSE),0) -> 0 | AC80: =+AB80/$G$14 -> 0 | AE80: P1 | AH80: =IFERROR(VLOOKUP('Manufactured Items Models'!AF80,'Cost Master List'!$B$84:$L$98,11,FALSE),0) -> 0 | AI80: =+AH80/$G$14 -> 0 | AK80: P1 | AN80: =IFERROR(VLOOKUP('Manufactured Items Models'!AL80,'Cost Master List'!$B$84:$L$98,11,FALSE),0) -> 0 | AO80: =+AN80/$G$14 -> 0 | AQ80: P1 | AT80: =IFERROR(VLOOKUP('Manufactured Items Models'!AR80,'Cost Master List'!$B$84:$L$98,11,FALSE),0) -> 0 | AU80: =+AT80/$G$14 -> 0 | AW80: P1 | AZ80: =IFERROR(VLOOKUP('Manufactured Items Models'!AX80,'Cost Master List'!$B$84:$L$98,11,FALSE),0) -> 0 | BA80: =+AZ80/$G$14 -> 0
A81: P2 | D81: =IFERROR(VLOOKUP('Manufactured Items Models'!B81,'Cost Master List'!$B$84:$L$98,11,FALSE),0) -> 0 | E81: =+D81/$A$74 -> 0 | G81: P2 | J81: =IFERROR(VLOOKUP('Manufactured Items Models'!H81,'Cost Master List'!$B$84:$L$98,11,FALSE),0) -> 0 | K81: =+J81/$G$14 -> 0 | M81: P2 | P81: =IFERROR(VLOOKUP('Manufactured Items Models'!N81,'Cost Master List'!$B$84:$L$98,11,FALSE),0) -> 0 | Q81: =+P81/$G$14 -> 0 | S81: P2 | V81: =IFERROR(VLOOKUP('Manufactured Items Models'!T81,'Cost Master List'!$B$84:$L$98,11,FALSE),0) -> 0 | W81: =+V81/$G$14 -> 0 | Y81: P2 | AB81: =IFERROR(VLOOKUP('Manufactured Items Models'!Z81,'Cost Master List'!$B$84:$L$98,11,FALSE),0) -> 0 | AC81: =+AB81/$G$14 -> 0 | AE81: P2 | AH81: =IFERROR(VLOOKUP('Manufactured Items Models'!AF81,'Cost Master List'!$B$84:$L$98,11,FALSE),0) -> 0 | AI81: =+AH81/$G$14 -> 0 | AK81: P2 | AN81: =IFERROR(VLOOKUP('Manufactured Items Models'!AL81,'Cost Master List'!$B$84:$L$98,11,FALSE),0) -> 0 | AO81: =+AN81/$G$14 -> 0 | AQ81: P2 | AT81: =IFERROR(VLOOKUP('Manufactured Items Models'!AR81,'Cost Master List'!$B$84:$L$98,11,FALSE),0) -> 0 | AU81: =+AT81/$G$14 -> 0 | AW81: P2 | AZ81: =IFERROR(VLOOKUP('Manufactured Items Models'!AX81,'Cost Master List'!$B$84:$L$98,11,FALSE),0) -> 0 | BA81: =+AZ81/$G$14 -> 0
A82: P3 | D82: =IFERROR(VLOOKUP('Manufactured Items Models'!B82,'Cost Master List'!$B$84:$L$98,11,FALSE),0) -> 0 | E82: =+D82/$A$74 -> 0 | G82: P3 | J82: =IFERROR(VLOOKUP('Manufactured Items Models'!H82,'Cost Master List'!$B$84:$L$98,11,FALSE),0) -> 0 | K82: =+J82/$G$14 -> 0 | M82: P3 | P82: =IFERROR(VLOOKUP('Manufactured Items Models'!N82,'Cost Master List'!$B$84:$L$98,11,FALSE),0) -> 0 | Q82: =+P82/$G$14 -> 0 | S82: P3 | V82: =IFERROR(VLOOKUP('Manufactured Items Models'!T82,'Cost Master List'!$B$84:$L$98,11,FALSE),0) -> 0 | W82: =+V82/$G$14 -> 0 | Y82: P3 | AB82: =IFERROR(VLOOKUP('Manufactured Items Models'!Z82,'Cost Master List'!$B$84:$L$98,11,FALSE),0) -> 0 | AC82: =+AB82/$G$14 -> 0 | AE82: P3 | AH82: =IFERROR(VLOOKUP('Manufactured Items Models'!AF82,'Cost Master List'!$B$84:$L$98,11,FALSE),0) -> 0 | AI82: =+AH82/$G$14 -> 0 | AK82: P3 | AN82: =IFERROR(VLOOKUP('Manufactured Items Models'!AL82,'Cost Master List'!$B$84:$L$98,11,FALSE),0) -> 0 | AO82: =+AN82/$G$14 -> 0 | AQ82: P3 | AT82: =IFERROR(VLOOKUP('Manufactured Items Models'!AR82,'Cost Master List'!$B$84:$L$98,11,FALSE),0) -> 0 | AU82: =+AT82/$G$14 -> 0 | AW82: P3 | AZ82: =IFERROR(VLOOKUP('Manufactured Items Models'!AX82,'Cost Master List'!$B$84:$L$98,11,FALSE),0) -> 0 | BA82: =+AZ82/$G$14 -> 0
A83: Labor | E83: 1 | G83: Labor | K83: 1 | M83: Labor | Q83: 1 | S83: Labor | W83: 1 | Y83: Labor | AC83: 1 | AE83: Labor | AI83: 1 | AK83: Labor | AO83: 1 | AQ83: Labor | AU83: 1 | AW83: Labor | BA83: 1
B84: Annatto Extract P1414 (44) | D84: Cost/lb | E84: =+SUM(E75:E83) -> 2.8503724 | J84: Cost/lb | K84: =+SUM(K75:K83) -> 1 | P84: Cost/lb | Q84: =+SUM(Q75:Q83) -> 1 | V84: Cost/lb | W84: =+SUM(W75:W83) -> 1 | AB84: Cost/lb | AC84: =+SUM(AC75:AC83) -> 1 | AH84: Cost/lb | AI84: =+SUM(AI75:AI83) -> 1 | AN84: Cost/lb | AO84: =+SUM(AO75:AO83) -> 1 | AT84: Cost/lb | AU84: =+SUM(AU75:AU83) -> 1 | AZ84: Cost/lb | BA84: =+SUM(BA75:BA83) -> 1
A86: 8 | B86: Annatto Extract P1428 | C86: Composition | D86: Price/lb | E86: Formula Cost | I86: Composition | J86: Price/lb | K86: Formula Cost | O86: Composition | P86: Price/lb | Q86: Formula Cost | U86: Composition | V86: Price/lb | W86: Formula Cost | AA86: Composition | AB86: Price/lb | AC86: Formula Cost | AG86: Composition | AH86: Price/lb | AI86: Formula Cost | AM86: Composition | AN86: Price/lb | AO86: Formula Cost | AS86: Composition | AT86: Price/lb | AU86: Formula Cost | AY86: Composition | AZ86: Price/lb | BA86: Formula Cost
A87: R1 | B87: Annatto Extract WS5 (Cyber Colors) | C87: 0.4 | D87: =IFERROR(VLOOKUP(B87,'Cost Master List'!$B$2:$P$74,12,),0) -> 6.1053606 | E87: =+D87*C87 -> 2.4421442 | G87: R1 | J87: =IFERROR(VLOOKUP(H87,'Cost Master List'!$B$2:$P$74,12,),0) -> 0 | K87: =+J87*I87 -> 0 | M87: R1 | P87: =IFERROR(VLOOKUP(N87,'Cost Master List'!$B$2:$P$74,12,),0) -> 0 | Q87: =+P87*O87 -> 0 | S87: R1 | V87: =IFERROR(VLOOKUP(T87,'Cost Master List'!$B$2:$P$74,12,),0) -> 0 | W87: =+V87*U87 -> 0 | Y87: R1 | AB87: =IFERROR(VLOOKUP(Z87,'Cost Master List'!$B$2:$P$74,12,),0) -> 0 | AC87: =+AB87*AA87 -> 0 | AE87: R1 | AH87: =IFERROR(VLOOKUP(AF87,'Cost Master List'!$B$2:$P$74,12,),0) -> 0 | AI87: =+AH87*AG87 -> 0 | AK87: R1 | AN87: =IFERROR(VLOOKUP(AL87,'Cost Master List'!$B$2:$P$74,12,),0) -> 0 | AO87: =+AN87*AM87 -> 0 | AQ87: R1 | AT87: =IFERROR(VLOOKUP(AR87,'Cost Master List'!$B$2:$P$74,12,),0) -> 0 | AU87: =+AT87*AS87 -> 0 | AW87: R1 | AZ87: =IFERROR(VLOOKUP(AX87,'Cost Master List'!$B$2:$P$74,12,),0) -> 0 | BA87: =+AZ87*AY87 -> 0
A88: R2 | B88: DI Water | C88: 0.6 | D88: =IFERROR(VLOOKUP(B88,'Cost Master List'!$B$2:$P$74,12,),0) -> 0.22679645 | E88: =+D88*C88 -> 0.13607787 | G88: R2 | J88: =IFERROR(VLOOKUP(H88,'Cost Master List'!$B$2:$P$74,12,),0) -> 0 | K88: =+J88*I88 -> 0 | M88: R2 | P88: =IFERROR(VLOOKUP(N88,'Cost Master List'!$B$2:$P$74,12,),0) -> 0 | Q88: =+P88*O88 -> 0 | S88: R2 | V88: =IFERROR(VLOOKUP(T88,'Cost Master List'!$B$2:$P$74,12,),0) -> 0 | W88: =+V88*U88 -> 0 | Y88: R2 | AB88: =IFERROR(VLOOKUP(Z88,'Cost Master List'!$B$2:$P$74,12,),0) -> 0 | AC88: =+AB88*AA88 -> 0 | AE88: R2 | AH88: =IFERROR(VLOOKUP(AF88,'Cost Master List'!$B$2:$P$74,12,),0) -> 0 | AI88: =+AH88*AG88 -> 0 | AK88: R2 | AN88: =IFERROR(VLOOKUP(AL88,'Cost Master List'!$B$2:$P$74,12,),0) -> 0 | AO88: =+AN88*AM88 -> 0 | AQ88: R2 | AT88: =IFERROR(VLOOKUP(AR88,'Cost Master List'!$B$2:$P$74,12,),0) -> 0 | AU88: =+AT88*AS88 -> 0 | AW88: R2 | AZ88: =IFERROR(VLOOKUP(AX88,'Cost Master List'!$B$2:$P$74,12,),0) -> 0 | BA88: =+AZ88*AY88 -> 0
A89: R3 | D89: =IFERROR(VLOOKUP(B89,'Cost Master List'!$B$2:$P$74,12,),0) -> 0 | E89: =+D89*C89 -> 0 | G89: R3 | J89: =IFERROR(VLOOKUP(H89,'Cost Master List'!$B$2:$P$74,12,),0) -> 0 | K89: =+J89*I89 -> 0 | M89: R3 | P89: =IFERROR(VLOOKUP(N89,'Cost Master List'!$B$2:$P$74,12,),0) -> 0 | Q89: =+P89*O89 -> 0 | S89: R3 | V89: =IFERROR(VLOOKUP(T89,'Cost Master List'!$B$2:$P$74,12,),0) -> 0 | W89: =+V89*U89 -> 0 | Y89: R3 | AB89: =IFERROR(VLOOKUP(Z89,'Cost Master List'!$B$2:$P$74,12,),0) -> 0 | AC89: =+AB89*AA89 -> 0 | AE89: R3 | AH89: =IFERROR(VLOOKUP(AF89,'Cost Master List'!$B$2:$P$74,12,),0) -> 0 | AI89: =+AH89*AG89 -> 0 | AK89: R3 | AN89: =IFERROR(VLOOKUP(AL89,'Cost Master List'!$B$2:$P$74,12,),0) -> 0 | AO89: =+AN89*AM89 -> 0 | AQ89: R3 | AT89: =IFERROR(VLOOKUP(AR89,'Cost Master List'!$B$2:$P$74,12,),0) -> 0 | AU89: =+AT89*AS89 -> 0 | AW89: R3 | AZ89: =IFERROR(VLOOKUP(AX89,'Cost Master List'!$B$2:$P$74,12,),0) -> 0 | BA89: =+AZ89*AY89 -> 0
A90: R4 | D90: =IFERROR(VLOOKUP(B90,'Cost Master List'!$B$2:$P$74,12,),0) -> 0 | E90: =+D90*C90 -> 0 | G90: R4 | J90: =IFERROR(VLOOKUP(H90,'Cost Master List'!$B$2:$P$74,12,),0) -> 0 | K90: =+J90*I90 -> 0 | M90: R4 | P90: =IFERROR(VLOOKUP(N90,'Cost Master List'!$B$2:$P$74,12,),0) -> 0 | Q90: =+P90*O90 -> 0 | S90: R4 | V90: =IFERROR(VLOOKUP(T90,'Cost Master List'!$B$2:$P$74,12,),0) -> 0 | W90: =+V90*U90 -> 0 | Y90: R4 | AB90: =IFERROR(VLOOKUP(Z90,'Cost Master List'!$B$2:$P$74,12,),0) -> 0 | AC90: =+AB90*AA90 -> 0 | AE90: R4 | AH90: =IFERROR(VLOOKUP(AF90,'Cost Master List'!$B$2:$P$74,12,),0) -> 0 | AI90: =+AH90*AG90 -> 0 | AK90: R4 | AN90: =IFERROR(VLOOKUP(AL90,'Cost Master List'!$B$2:$P$74,12,),0) -> 0 | AO90: =+AN90*AM90 -> 0 | AQ90: R4 | AT90: =IFERROR(VLOOKUP(AR90,'Cost Master List'!$B$2:$P$74,12,),0) -> 0 | AU90: =+AT90*AS90 -> 0 | AW90: R4 | AZ90: =IFERROR(VLOOKUP(AX90,'Cost Master List'!$B$2:$P$74,12,),0) -> 0 | BA90: =+AZ90*AY90 -> 0
A91: R5 | D91: =IFERROR(VLOOKUP(B91,'Cost Master List'!$B$2:$P$74,12,),0) -> 0 | E91: =+D91*C91 -> 0 | G91: R5 | J91: =IFERROR(VLOOKUP(H91,'Cost Master List'!$B$2:$P$74,12,),0) -> 0 | K91: =+J91*I91 -> 0 | M91: R5 | P91: =IFERROR(VLOOKUP(N91,'Cost Master List'!$B$2:$P$74,12,),0) -> 0 | Q91: =+P91*O91 -> 0 | S91: R5 | V91: =IFERROR(VLOOKUP(T91,'Cost Master List'!$B$2:$P$74,12,),0) -> 0 | W91: =+V91*U91 -> 0 | Y91: R5 | AB91: =IFERROR(VLOOKUP(Z91,'Cost Master List'!$B$2:$P$74,12,),0) -> 0 | AC91: =+AB91*AA91 -> 0 | AE91: R5 | AH91: =IFERROR(VLOOKUP(AF91,'Cost Master List'!$B$2:$P$74,12,),0) -> 0 | AI91: =+AH91*AG91 -> 0 | AK91: R5 | AN91: =IFERROR(VLOOKUP(AL91,'Cost Master List'!$B$2:$P$74,12,),0) -> 0 | AO91: =+AN91*AM91 -> 0 | AQ91: R5 | AT91: =IFERROR(VLOOKUP(AR91,'Cost Master List'!$B$2:$P$74,12,),0) -> 0 | AU91: =+AT91*AS91 -> 0 | AW91: R5 | AZ91: =IFERROR(VLOOKUP(AX91,'Cost Master List'!$B$2:$P$74,12,),0) -> 0 | BA91: =+AZ91*AY91 -> 0
A92: P1 | B92: 1 Gallon Jug & Box Combo | D92: =IFERROR(VLOOKUP('Manufactured Items Models'!B92,'Cost Master List'!$B$84:$L$98,11,FALSE),0) -> 1.6 | E92: =+D92/$A$86 -> 0.2 | G92: P1 | J92: =IFERROR(VLOOKUP('Manufactured Items Models'!H92,'Cost Master List'!$B$84:$L$98,11,FALSE),0) -> 0 | K92: =+J92/$G$14 -> 0 | M92: P1 | P92: =IFERROR(VLOOKUP('Manufactured Items Models'!N92,'Cost Master List'!$B$84:$L$98,11,FALSE),0) -> 0 | Q92: =+P92/$G$14 -> 0 | S92: P1 | V92: =IFERROR(VLOOKUP('Manufactured Items Models'!T92,'Cost Master List'!$B$84:$L$98,11,FALSE),0) -> 0 | W92: =+V92/$G$14 -> 0 | Y92: P1 | AB92: =IFERROR(VLOOKUP('Manufactured Items Models'!Z92,'Cost Master List'!$B$84:$L$98,11,FALSE),0) -> 0 | AC92: =+AB92/$G$14 -> 0 | AE92: P1 | AH92: =IFERROR(VLOOKUP('Manufactured Items Models'!AF92,'Cost Master List'!$B$84:$L$98,11,FALSE),0) -> 0 | AI92: =+AH92/$G$14 -> 0 | AK92: P1 | AN92: =IFERROR(VLOOKUP('Manufactured Items Models'!AL92,'Cost Master List'!$B$84:$L$98,11,FALSE),0) -> 0 | AO92: =+AN92/$G$14 -> 0 | AQ92: P1 | AT92: =IFERROR(VLOOKUP('Manufactured Items Models'!AR92,'Cost Master List'!$B$84:$L$98,11,FALSE),0) -> 0 | AU92: =+AT92/$G$14 -> 0 | AW92: P1 | AZ92: =IFERROR(VLOOKUP('Manufactured Items Models'!AX92,'Cost Master List'!$B$84:$L$98,11,FALSE),0) -> 0 | BA92: =+AZ92/$G$14 -> 0
A93: P2 | D93: =IFERROR(VLOOKUP('Manufactured Items Models'!B93,'Cost Master List'!$B$84:$L$98,11,FALSE),0) -> 0 | E93: =+D93/$A$86 -> 0 | G93: P2 | J93: =IFERROR(VLOOKUP('Manufactured Items Models'!H93,'Cost Master List'!$B$84:$L$98,11,FALSE),0) -> 0 | K93: =+J93/$G$14 -> 0 | M93: P2 | P93: =IFERROR(VLOOKUP('Manufactured Items Models'!N93,'Cost Master List'!$B$84:$L$98,11,FALSE),0) -> 0 | Q93: =+P93/$G$14 -> 0 | S93: P2 | V93: =IFERROR(VLOOKUP('Manufactured Items Models'!T93,'Cost Master List'!$B$84:$L$98,11,FALSE),0) -> 0 | W93: =+V93/$G$14 -> 0 | Y93: P2 | AB93: =IFERROR(VLOOKUP('Manufactured Items Models'!Z93,'Cost Master List'!$B$84:$L$98,11,FALSE),0) -> 0 | AC93: =+AB93/$G$14 -> 0 | AE93: P2 | AH93: =IFERROR(VLOOKUP('Manufactured Items Models'!AF93,'Cost Master List'!$B$84:$L$98,11,FALSE),0) -> 0 | AI93: =+AH93/$G$14 -> 0 | AK93: P2 | AN93: =IFERROR(VLOOKUP('Manufactured Items Models'!AL93,'Cost Master List'!$B$84:$L$98,11,FALSE),0) -> 0 | AO93: =+AN93/$G$14 -> 0 | AQ93: P2 | AT93: =IFERROR(VLOOKUP('Manufactured Items Models'!AR93,'Cost Master List'!$B$84:$L$98,11,FALSE),0) -> 0 | AU93: =+AT93/$G$14 -> 0 | AW93: P2 | AZ93: =IFERROR(VLOOKUP('Manufactured Items Models'!AX93,'Cost Master List'!$B$84:$L$98,11,FALSE),0) -> 0 | BA93: =+AZ93/$G$14 -> 0
A94: P3 | D94: =IFERROR(VLOOKUP('Manufactured Items Models'!B94,'Cost Master List'!$B$84:$L$98,11,FALSE),0) -> 0 | E94: =+D94/$A$86 -> 0 | G94: P3 | J94: =IFERROR(VLOOKUP('Manufactured Items Models'!H94,'Cost Master List'!$B$84:$L$98,11,FALSE),0) -> 0 | K94: =+J94/$G$14 -> 0 | M94: P3 | P94: =IFERROR(VLOOKUP('Manufactured Items Models'!N94,'Cost Master List'!$B$84:$L$98,11,FALSE),0) -> 0 | Q94: =+P94/$G$14 -> 0 | S94: P3 | V94: =IFERROR(VLOOKUP('Manufactured Items Models'!T94,'Cost Master List'!$B$84:$L$98,11,FALSE),0) -> 0 | W94: =+V94/$G$14 -> 0 | Y94: P3 | AB94: =IFERROR(VLOOKUP('Manufactured Items Models'!Z94,'Cost Master List'!$B$84:$L$98,11,FALSE),0) -> 0 | AC94: =+AB94/$G$14 -> 0 | AE94: P3 | AH94: =IFERROR(VLOOKUP('Manufactured Items Models'!AF94,'Cost Master List'!$B$84:$L$98,11,FALSE),0) -> 0 | AI94: =+AH94/$G$14 -> 0 | AK94: P3 | AN94: =IFERROR(VLOOKUP('Manufactured Items Models'!AL94,'Cost Master List'!$B$84:$L$98,11,FALSE),0) -> 0 | AO94: =+AN94/$G$14 -> 0 | AQ94: P3 | AT94: =IFERROR(VLOOKUP('Manufactured Items Models'!AR94,'Cost Master List'!$B$84:$L$98,11,FALSE),0) -> 0 | AU94: =+AT94/$G$14 -> 0 | AW94: P3 | AZ94: =IFERROR(VLOOKUP('Manufactured Items Models'!AX94,'Cost Master List'!$B$84:$L$98,11,FALSE),0) -> 0 | BA94: =+AZ94/$G$14 -> 0
A95: Labor | E95: 1 | G95: Labor | K95: 1 | M95: Labor | Q95: 1 | S95: Labor | W95: 1 | Y95: Labor | AC95: 1 | AE95: Labor | AI95: 1 | AK95: Labor | AO95: 1 | AQ95: Labor | AU95: 1 | AW95: Labor | BA95: 1
B96: Annatto Extract P1428 (8) | D96: Cost/lb | E96: =+SUM(E87:E95) -> 3.7782221 | J96: Cost/lb | K96: =+SUM(K87:K95) -> 1 | P96: Cost/lb | Q96: =+SUM(Q87:Q95) -> 1 | V96: Cost/lb | W96: =+SUM(W87:W95) -> 1 | AB96: Cost/lb | AC96: =+SUM(AC87:AC95) -> 1 | AH96: Cost/lb | AI96: =+SUM(AI87:AI95) -> 1 | AN96: Cost/lb | AO96: =+SUM(AO87:AO95) -> 1 | AT96: Cost/lb | AU96: =+SUM(AU87:AU95) -> 1 | AZ96: Cost/lb | BA96: =+SUM(BA87:BA95) -> 1
A98: 44 | B98: Annatto Extract P1428 | C98: Composition | D98: Price/lb | E98: Formula Cost | I98: Composition | J98: Price/lb | K98: Formula Cost | O98: Composition | P98: Price/lb | Q98: Formula Cost | U98: Composition | V98: Price/lb | W98: Formula Cost | AA98: Composition | AB98: Price/lb | AC98: Formula Cost | AG98: Composition | AH98: Price/lb | AI98: Formula Cost | AM98: Composition | AN98: Price/lb | AO98: Formula Cost | AS98: Composition | AT98: Price/lb | AU98: Formula Cost | AY98: Composition | AZ98: Price/lb | BA98: Formula Cost
A99: R1 | B99: Annatto Extract WS5 (Cyber Colors) | C99: 0.4 | D99: =IFERROR(VLOOKUP(B99,'Cost Master List'!$B$2:$P$74,12,),0) -> 6.1053606 | E99: =+D99*C99 -> 2.4421442 | G99: R1 | J99: =IFERROR(VLOOKUP(H99,'Cost Master List'!$B$2:$P$74,12,),0) -> 0 | K99: =+J99*I99 -> 0 | M99: R1 | P99: =IFERROR(VLOOKUP(N99,'Cost Master List'!$B$2:$P$74,12,),0) -> 0 | Q99: =+P99*O99 -> 0 | S99: R1 | V99: =IFERROR(VLOOKUP(T99,'Cost Master List'!$B$2:$P$74,12,),0) -> 0 | W99: =+V99*U99 -> 0 | Y99: R1 | AB99: =IFERROR(VLOOKUP(Z99,'Cost Master List'!$B$2:$P$74,12,),0) -> 0 | AC99: =+AB99*AA99 -> 0 | AE99: R1 | AH99: =IFERROR(VLOOKUP(AF99,'Cost Master List'!$B$2:$P$74,12,),0) -> 0 | AI99: =+AH99*AG99 -> 0 | AK99: R1 | AN99: =IFERROR(VLOOKUP(AL99,'Cost Master List'!$B$2:$P$74,12,),0) -> 0 | AO99: =+AN99*AM99 -> 0 | AQ99: R1 | AT99: =IFERROR(VLOOKUP(AR99,'Cost Master List'!$B$2:$P$74,12,),0) -> 0 | AU99: =+AT99*AS99 -> 0 | AW99: R1 | AZ99: =IFERROR(VLOOKUP(AX99,'Cost Master List'!$B$2:$P$74,12,),0) -> 0 | BA99: =+AZ99*AY99 -> 0
A100: R2 | B100: DI Water | C100: 0.6 | D100: =IFERROR(VLOOKUP(B100,'Cost Master List'!$B$2:$P$74,12,),0) -> 0.22679645 | E100: =+D100*C100 -> 0.13607787 | G100: R2 | J100: =IFERROR(VLOOKUP(H100,'Cost Master List'!$B$2:$P$74,12,),0) -> 0 | K100: =+J100*I100 -> 0 | M100: R2 | P100: =IFERROR(VLOOKUP(N100,'Cost Master List'!$B$2:$P$74,12,),0) -> 0 | Q100: =+P100*O100 -> 0 | S100: R2 | V100: =IFERROR(VLOOKUP(T100,'Cost Master List'!$B$2:$P$74,12,),0) -> 0 | W100: =+V100*U100 -> 0 | Y100: R2 | AB100: =IFERROR(VLOOKUP(Z100,'Cost Master List'!$B$2:$P$74,12,),0) -> 0 | AC100: =+AB100*AA100 -> 0 | AE100: R2 | AH100: =IFERROR(VLOOKUP(AF100,'Cost Master List'!$B$2:$P$74,12,),0) -> 0 | AI100: =+AH100*AG100 -> 0 | AK100: R2 | AN100: =IFERROR(VLOOKUP(AL100,'Cost Master List'!$B$2:$P$74,12,),0) -> 0 | AO100: =+AN100*AM100 -> 0 | AQ100: R2 | AT100: =IFERROR(VLOOKUP(AR100,'Cost Master List'!$B$2:$P$74,12,),0) -> 0 | AU100: =+AT100*AS100 -> 0 | AW100: R2 | AZ100: =IFERROR(VLOOKUP(AX100,'Cost Master List'!$B$2:$P$74,12,),0) -> 0 | BA100: =+AZ100*AY100 -> 0
A101: R3 | D101: =IFERROR(VLOOKUP(B101,'Cost Master List'!$B$2:$P$74,12,),0) -> 0 | E101: =+D101*C101 -> 0 | G101: R3 | J101: =IFERROR(VLOOKUP(H101,'Cost Master List'!$B$2:$P$74,12,),0) -> 0 | K101: =+J101*I101 -> 0 | M101: R3 | P101: =IFERROR(VLOOKUP(N101,'Cost Master List'!$B$2:$P$74,12,),0) -> 0 | Q101: =+P101*O101 -> 0 | S101: R3 | V101: =IFERROR(VLOOKUP(T101,'Cost Master List'!$B$2:$P$74,12,),0) -> 0 | W101: =+V101*U101 -> 0 | Y101: R3 | AB101: =IFERROR(VLOOKUP(Z101,'Cost Master List'!$B$2:$P$74,12,),0) -> 0 | AC101: =+AB101*AA101 -> 0 | AE101: R3 | AH101: =IFERROR(VLOOKUP(AF101,'Cost Master List'!$B$2:$P$74,12,),0) -> 0 | AI101: =+AH101*AG101 -> 0 | AK101: R3 | AN101: =IFERROR(VLOOKUP(AL101,'Cost Master List'!$B$2:$P$74,12,),0) -> 0 | AO101: =+AN101*AM101 -> 0 | AQ101: R3 | AT101: =IFERROR(VLOOKUP(AR101,'Cost Master List'!$B$2:$P$74,12,),0) -> 0 | AU101: =+AT101*AS101 -> 0 | AW101: R3 | AZ101: =IFERROR(VLOOKUP(AX101,'Cost Master List'!$B$2:$P$74,12,),0) -> 0 | BA101: =+AZ101*AY101 -> 0
A102: R4 | D102: =IFERROR(VLOOKUP(B102,'Cost Master List'!$B$2:$P$74,12,),0) -> 0 | E102: =+D102*C102 -> 0 | G102: R4 | J102: =IFERROR(VLOOKUP(H102,'Cost Master List'!$B$2:$P$74,12,),0) -> 0 | K102: =+J102*I102 -> 0 | M102: R4 | P102: =IFERROR(VLOOKUP(N102,'Cost Master List'!$B$2:$P$74,12,),0) -> 0 | Q102: =+P102*O102 -> 0 | S102: R4 | V102: =IFERROR(VLOOKUP(T102,'Cost Master List'!$B$2:$P$74,12,),0) -> 0 | W102: =+V102*U102 -> 0 | Y102: R4 | AB102: =IFERROR(VLOOKUP(Z102,'Cost Master List'!$B$2:$P$74,12,),0) -> 0 | AC102: =+AB102*AA102 -> 0 | AE102: R4 | AH102: =IFERROR(VLOOKUP(AF102,'Cost Master List'!$B$2:$P$74,12,),0) -> 0 | AI102: =+AH102*AG102 -> 0 | AK102: R4 | AN102: =IFERROR(VLOOKUP(AL102,'Cost Master List'!$B$2:$P$74,12,),0) -> 0 | AO102: =+AN102*AM102 -> 0 | AQ102: R4 | AT102: =IFERROR(VLOOKUP(AR102,'Cost Master List'!$B$2:$P$74,12,),0) -> 0 | AU102: =+AT102*AS102 -> 0 | AW102: R4 | AZ102: =IFERROR(VLOOKUP(AX102,'Cost Master List'!$B$2:$P$74,12,),0) -> 0 | BA102: =+AZ102*AY102 -> 0
A103: R5 | D103: =IFERROR(VLOOKUP(B103,'Cost Master List'!$B$2:$P$74,12,),0) -> 0 | E103: =+D103*C103 -> 0 | G103: R5 | J103: =IFERROR(VLOOKUP(H103,'Cost Master List'!$B$2:$P$74,12,),0) -> 0 | K103: =+J103*I103 -> 0 | M103: R5 | P103: =IFERROR(VLOOKUP(N103,'Cost Master List'!$B$2:$P$74,12,),0) -> 0 | Q103: =+P103*O103 -> 0 | S103: R5 | V103: =IFERROR(VLOOKUP(T103,'Cost Master List'!$B$2:$P$74,12,),0) -> 0 | W103: =+V103*U103 -> 0 | Y103: R5 | AB103: =IFERROR(VLOOKUP(Z103,'Cost Master List'!$B$2:$P$74,12,),0) -> 0 | AC103: =+AB103*AA103 -> 0 | AE103: R5 | AH103: =IFERROR(VLOOKUP(AF103,'Cost Master List'!$B$2:$P$74,12,),0) -> 0 | AI103: =+AH103*AG103 -> 0 | AK103: R5 | AN103: =IFERROR(VLOOKUP(AL103,'Cost Master List'!$B$2:$P$74,12,),0) -> 0 | AO103: =+AN103*AM103 -> 0 | AQ103: R5 | AT103: =IFERROR(VLOOKUP(AR103,'Cost Master List'!$B$2:$P$74,12,),0) -> 0 | AU103: =+AT103*AS103 -> 0 | AW103: R5 | AZ103: =IFERROR(VLOOKUP(AX103,'Cost Master List'!$B$2:$P$74,12,),0) -> 0 | BA103: =+AZ103*AY103 -> 0
A104: P1 | B104: 5 Gallon Pails | D104: =IFERROR(VLOOKUP('Manufactured Items Models'!B104,'Cost Master List'!$B$84:$L$98,11,FALSE),0) -> 9.68 | E104: =+D104/$A$98 -> 0.22 | G104: P1 | J104: =IFERROR(VLOOKUP('Manufactured Items Models'!H104,'Cost Master List'!$B$84:$L$98,11,FALSE),0) -> 0 | K104: =+J104/$G$14 -> 0 | M104: P1 | P104: =IFERROR(VLOOKUP('Manufactured Items Models'!N104,'Cost Master List'!$B$84:$L$98,11,FALSE),0) -> 0 | Q104: =+P104/$G$14 -> 0 | S104: P1 | V104: =IFERROR(VLOOKUP('Manufactured Items Models'!T104,'Cost Master List'!$B$84:$L$98,11,FALSE),0) -> 0 | W104: =+V104/$G$14 -> 0 | Y104: P1 | AB104: =IFERROR(VLOOKUP('Manufactured Items Models'!Z104,'Cost Master List'!$B$84:$L$98,11,FALSE),0) -> 0 | AC104: =+AB104/$G$14 -> 0 | AE104: P1 | AH104: =IFERROR(VLOOKUP('Manufactured Items Models'!AF104,'Cost Master List'!$B$84:$L$98,11,FALSE),0) -> 0 | AI104: =+AH104/$G$14 -> 0 | AK104: P1 | AN104: =IFERROR(VLOOKUP('Manufactured Items Models'!AL104,'Cost Master List'!$B$84:$L$98,11,FALSE),0) -> 0 | AO104: =+AN104/$G$14 -> 0 | AQ104: P1 | AT104: =IFERROR(VLOOKUP('Manufactured Items Models'!AR104,'Cost Master List'!$B$84:$L$98,11,FALSE),0) -> 0 | AU104: =+AT104/$G$14 -> 0 | AW104: P1 | AZ104: =IFERROR(VLOOKUP('Manufactured Items Models'!AX104,'Cost Master List'!$B$84:$L$98,11,FALSE),0) -> 0 | BA104: =+AZ104/$G$14 -> 0
A105: P2 | D105: =IFERROR(VLOOKUP('Manufactured Items Models'!B105,'Cost Master List'!$B$84:$L$98,11,FALSE),0) -> 0 | E105: =+D105/$A$98 -> 0 | G105: P2 | J105: =IFERROR(VLOOKUP('Manufactured Items Models'!H105,'Cost Master List'!$B$84:$L$98,11,FALSE),0) -> 0 | K105: =+J105/$G$14 -> 0 | M105: P2 | P105: =IFERROR(VLOOKUP('Manufactured Items Models'!N105,'Cost Master List'!$B$84:$L$98,11,FALSE),0) -> 0 | Q105: =+P105/$G$14 -> 0 | S105: P2 | V105: =IFERROR(VLOOKUP('Manufactured Items Models'!T105,'Cost Master List'!$B$84:$L$98,11,FALSE),0) -> 0 | W105: =+V105/$G$14 -> 0 | Y105: P2 | AB105: =IFERROR(VLOOKUP('Manufactured Items Models'!Z105,'Cost Master List'!$B$84:$L$98,11,FALSE),0) -> 0 | AC105: =+AB105/$G$14 -> 0 | AE105: P2 | AH105: =IFERROR(VLOOKUP('Manufactured Items Models'!AF105,'Cost Master List'!$B$84:$L$98,11,FALSE),0) -> 0 | AI105: =+AH105/$G$14 -> 0 | AK105: P2 | AN105: =IFERROR(VLOOKUP('Manufactured Items Models'!AL105,'Cost Master List'!$B$84:$L$98,11,FALSE),0) -> 0 | AO105: =+AN105/$G$14 -> 0 | AQ105: P2 | AT105: =IFERROR(VLOOKUP('Manufactured Items Models'!AR105,'Cost Master List'!$B$84:$L$98,11,FALSE),0) -> 0 | AU105: =+AT105/$G$14 -> 0 | AW105: P2 | AZ105: =IFERROR(VLOOKUP('Manufactured Items Models'!AX105,'Cost Master List'!$B$84:$L$98,11,FALSE),0) -> 0 | BA105: =+AZ105/$G$14 -> 0
A106: P3 | D106: =IFERROR(VLOOKUP('Manufactured Items Models'!B106,'Cost Master List'!$B$84:$L$98,11,FALSE),0) -> 0 | E106: =+D106/$A$98 -> 0 | G106: P3 | J106: =IFERROR(VLOOKUP('Manufactured Items Models'!H106,'Cost Master List'!$B$84:$L$98,11,FALSE),0) -> 0 | K106: =+J106/$G$14 -> 0 | M106: P3 | P106: =IFERROR(VLOOKUP('Manufactured Items Models'!N106,'Cost Master List'!$B$84:$L$98,11,FALSE),0) -> 0 | Q106: =+P106/$G$14 -> 0 | S106: P3 | V106: =IFERROR(VLOOKUP('Manufactured Items Models'!T106,'Cost Master List'!$B$84:$L$98,11,FALSE),0) -> 0 | W106: =+V106/$G$14 -> 0 | Y106: P3 | AB106: =IFERROR(VLOOKUP('Manufactured Items Models'!Z106,'Cost Master List'!$B$84:$L$98,11,FALSE),0) -> 0 | AC106: =+AB106/$G$14 -> 0 | AE106: P3 | AH106: =IFERROR(VLOOKUP('Manufactured Items Models'!AF106,'Cost Master List'!$B$84:$L$98,11,FALSE),0) -> 0 | AI106: =+AH106/$G$14 -> 0 | AK106: P3 | AN106: =IFERROR(VLOOKUP('Manufactured Items Models'!AL106,'Cost Master List'!$B$84:$L$98,11,FALSE),0) -> 0 | AO106: =+AN106/$G$14 -> 0 | AQ106: P3 | AT106: =IFERROR(VLOOKUP('Manufactured Items Models'!AR106,'Cost Master List'!$B$84:$L$98,11,FALSE),0) -> 0 | AU106: =+AT106/$G$14 -> 0 | AW106: P3 | AZ106: =IFERROR(VLOOKUP('Manufactured Items Models'!AX106,'Cost Master List'!$B$84:$L$98,11,FALSE),0) -> 0 | BA106: =+AZ106/$G$14 -> 0
A107: Labor | E107: 1 | G107: Labor | K107: 1 | M107: Labor | Q107: 1 | S107: Labor | W107: 1 | Y107: Labor | AC107: 1 | AE107: Labor | AI107: 1 | AK107: Labor | AO107: 1 | AQ107: Labor | AU107: 1 | AW107: Labor | BA107: 1
B108: Annatto Extract P1428 (44) | D108: Cost/lb | E108: =+SUM(E99:E107) -> 3.7982221 | J108: Cost/lb | K108: =+SUM(K99:K107) -> 1 | P108: Cost/lb | Q108: =+SUM(Q99:Q107) -> 1 | V108: Cost/lb | W108: =+SUM(W99:W107) -> 1 | AB108: Cost/lb | AC108: =+SUM(AC99:AC107) -> 1 | AH108: Cost/lb | AI108: =+SUM(AI99:AI107) -> 1 | AN108: Cost/lb | AO108: =+SUM(AO99:AO107) -> 1 | AT108: Cost/lb | AU108: =+SUM(AU99:AU107) -> 1 | AZ108: Cost/lb | BA108: =+SUM(BA99:BA107) -> 1

Sheet Customer Pricing
A1: Customer | B1: Close Probability | C1: Distributed or Manufactured? | D1: Product | E1: Cost | F1: Additional Cost (per lb) | G1: Margin | H1: Price | I1: Volume | J1: Annual Revenue | K1: Gross Profit | L1: % of Volume to hit 2026 | M1: Agreement | N1: Incoterms | O1: 1st Order Ship | P1: Order Pattern | Q1: Notes | R1: Date Updated | Z1: {=_xlfn._xlws.SORT(_xlfn.UNIQUE(_xlfn._xlws.FILTER('Cost Master List'!$B:$B,'Cost Master List'!$B:$B<>"")))} -> 1 Gallon Jug & Box Combo | AA1: {=_xlfn.LET( _xlpm.rng,'Manufactured Items Models'!$B:$BA, _xlpm.rows,{12;24;36;48;60;72;84;96;108}, _xlpm.itemCols,{1,7,13,19,25,31,37,43,49}, _xlpm.items,_xlfn.TOCOL(INDEX(_xlpm.rng,_xlpm.rows,_xlpm.itemCols),1), _xlfn._xlws.FILTER(_xlpm.items,_xlpm.items<>"") )} -> Annatto Extract P2401 (8) | AB1: {=_xlfn.LET( _xlpm.rng,'Manufactured Items Models'!$B:$BA, _xlpm.rows,{12;24;36;48;60;72;84;96;108}, _xlpm.itemCols,{1,7,13,19,25,31,37,43,49}, _xlpm.priceCols,_xlpm.itemCols+3, _xlpm.items,_xlfn.TOCOL(INDEX(_xlpm.rng,_xlpm.rows,_xlpm.itemCols),1), _xlpm.prices,_xlfn.TOCOL(INDEX(_xlpm.rng,_xlpm.rows,_xlpm.priceCols),1), _xlpm.mask,_xlpm.items<>"", _xlfn._xlws.FILTER(_xlpm.items,_xlpm.mask) )} -> Annatto Extract P2401 (8) | AC1: {=_xlfn.LET( _xlpm.rng,'Manufactured Items Models'!$B:$BA, _xlpm.rows,{12;24;36;48;60;72;84;96;108}, _xlpm.itemCols,{1,7,13,19,25,31,37,43,49}, _xlpm.priceCols,_xlpm.itemCols+3, _xlpm.items,_xlfn.TOCOL(INDEX(_xlpm.rng,_xlpm.rows,_xlpm.itemCols),1), _xlpm.prices,_xlfn.TOCOL(INDEX(_xlpm.rng,_xlpm.rows,_xlpm.priceCols),1), _xlpm.mask,_xlpm.items<>"", _xlfn._xlws.FILTER(_xlpm.prices,_xlpm.mask) )} -> #VALUE!
A2: Flavorchem | B2: 0.5 | C2: Manufactured | D2: Annatto Extract P1428 (8) | E2: {=IF(LOWER(TRIM($C2))="distributed",_xlfn.XLOOKUP($D2,'Cost Master List'!$B:$B,'Cost Master List'!$M:$M,"",0),_xlfn.LET(_xlpm.norm,_xlfn.LAMBDA(_xlpm.x,TRIM(SUBSTITUTE(_xlpm.x,CHAR(160),""))),_xlpm.rng,'Manufactured Items Models'!$B:$BA,_xlpm.rows,{12;24;36;48;60;72;84;96;108},_xlpm.itemCols,{1,7,13,19,25,31,37,43,49},_xlpm.priceCols,_xlpm.itemCols+3,_xlpm.items,INDEX(_xlpm.rng,_xlpm.rows,_xlpm.itemCols),_xlpm.prices,INDEX(_xlpm.rng,_xlpm.rows,_xlpm.priceCols),_xlpm.needle,_xlpm.norm($D2),_xlpm.hit,SUMPRODUCT((_xlpm.norm(_xlpm.items)=_xlpm.needle)*_xlpm.prices),IF(_xlpm.hit=0,"",_xlpm.hit)))} -> 3.7782221 | F2: 0 | G2: 0.28585906 | H2: =IF(OR(E2="",G2=""),0,(E2+F2)/(1-G2)) -> 5.2905833 | I2: 16000 | J2: =+I2*H2 -> 84649.332 | K2: =+J2*G2 -> 24197.779 | L2: 0.9 | M2: Quoted | O2: February | P2: Every Month | T2: Revenue Total | U2: =+SUM(J2:J1048576) -> 6479764.9 | Z2: 12x12x16 box | AA2: Natural Red D1303 (40) | AB2: Natural Red D1303 (40)
A3: Flavorchem | B3: 0.5 | C3: Distributed | D3: Annatto Extract P1315 (IFF) | E3: {=IF(LOWER(TRIM($C3))="distributed",_xlfn.XLOOKUP($D3,'Cost Master List'!$B:$B,'Cost Master List'!$M:$M,"",0),_xlfn.LET(_xlpm.norm,_xlfn.LAMBDA(_xlpm.x,TRIM(SUBSTITUTE(_xlpm.x,CHAR(160),""))),_xlpm.rng,'Manufactured Items Models'!$B:$BA,_xlpm.rows,{12;24;36;48;60;72;84;96;108},_xlpm.itemCols,{1,7,13,19,25,31,37,43,49},_xlpm.priceCols,_xlpm.itemCols+3,_xlpm.items,INDEX(_xlpm.rng,_xlpm.rows,_xlpm.itemCols),_xlpm.prices,INDEX(_xlpm.rng,_xlpm.rows,_xlpm.priceCols),_xlpm.needle,_xlpm.norm($D3),_xlpm.hit,SUMPRODUCT((_xlpm.norm(_xlpm.items)=_xlpm.needle)*_xlpm.prices),IF(_xlpm.hit=0,"",_xlpm.hit)))} -> 26.0952 | F3: 0 | G3: 0.17811387 | H3: =IF(OR(E3="",G3=""),0,(E3+F3)/(1-G3)) -> 31.750384 | I3: 1000 | J3: =+I3*H3 -> 31750.384 | K3: =+J3*G3 -> 5655.1837 | L3: 1 | M3: Quoted | O3: February | P3: Semi-Annual | T3: Gross Profit | U3: =+SUM(K2:K1048576) -> 2192614.7 | Z3: 15x15x15 box | AA3: Natural BP N1399 (11) | AB3: Natural BP N1399 (11)
A4: Black Label | B4: 0.1 | C4: Distributed | D4: Natural Green J1410 (Cyber Colors) | E4: {=IF(LOWER(TRIM($C4))="distributed",_xlfn.XLOOKUP($D4,'Cost Master List'!$B:$B,'Cost Master List'!$M:$M,"",0),_xlfn.LET(_xlpm.norm,_xlfn.LAMBDA(_xlpm.x,TRIM(SUBSTITUTE(_xlpm.x,CHAR(160),""))),_xlpm.rng,'Manufactured Items Models'!$B:$BA,_xlpm.rows,{12;24;36;48;60;72;84;96;108},_xlpm.itemCols,{1,7,13,19,25,31,37,43,49},_xlpm.priceCols,_xlpm.itemCols+3,_xlpm.items,INDEX(_xlpm.rng,_xlpm.rows,_xlpm.itemCols),_xlpm.prices,INDEX(_xlpm.rng,_xlpm.rows,_xlpm.priceCols),_xlpm.needle,_xlpm.norm($D4),_xlpm.hit,SUMPRODUCT((_xlpm.norm(_xlpm.items)=_xlpm.needle)*_xlpm.prices),IF(_xlpm.hit=0,"",_xlpm.hit)))} -> 20.375507 | F4: 0 | H4: =IF(OR(E4="",G4=""),0,(E4+F4)/(1-G4)) -> 0 | I4: 1600 | J4: =+I4*H4 -> 0 | K4: =+J4*G4 -> 0 | L4: 0.5 | M4: Quoted | O4: June | P4: Every Other Month | T4: GP % | U4: =+U3/U2 -> 0.33837874 | Z4: 16x12x10 box | AA4: Natural Red A1320 (44) | AB4: Natural Red A1320 (44)
A5: Black Label | B5: 0.6 | C5: Manufactured | D5: Natural Blue L1355 (11) | E5: {=IF(LOWER(TRIM($C5))="distributed",_xlfn.XLOOKUP($D5,'Cost Master List'!$B:$B,'Cost Master List'!$M:$M,"",0),_xlfn.LET(_xlpm.norm,_xlfn.LAMBDA(_xlpm.x,TRIM(SUBSTITUTE(_xlpm.x,CHAR(160),""))),_xlpm.rng,'Manufactured Items Models'!$B:$BA,_xlpm.rows,{12;24;36;48;60;72;84;96;108},_xlpm.itemCols,{1,7,13,19,25,31,37,43,49},_xlpm.priceCols,_xlpm.itemCols+3,_xlpm.items,INDEX(_xlpm.rng,_xlpm.rows,_xlpm.itemCols),_xlpm.prices,INDEX(_xlpm.rng,_xlpm.rows,_xlpm.priceCols),_xlpm.needle,_xlpm.norm($D5),_xlpm.hit,SUMPRODUCT((_xlpm.norm(_xlpm.items)=_xlpm.needle)*_xlpm.prices),IF(_xlpm.hit=0,"",_xlpm.hit)))} -> 18.115126 | F5: 0 | G5: 0.47278462 | H5: =IF(OR(E5="",G5=""),0,(E5+F5)/(1-G5)) -> 34.36001 | I5: 1000 | J5: =+I5*H5 -> 34360.01 | K5: =+J5*G5 -> 16244.884 | L5: 1 | M5: Quoted | O5: March | P5: Quarterly | Z5: 30 Gal Fiber Drums | AA5: Natural Red E1430 (44) | AB5: Natural Red E1430 (44)
A6: Black Label | B6: 0 | C6: Manufactured | D6: Natural BP N1399 (11) | E6: {=IF(LOWER(TRIM($C6))="distributed",_xlfn.XLOOKUP($D6,'Cost Master List'!$B:$B,'Cost Master List'!$M:$M,"",0),_xlfn.LET(_xlpm.norm,_xlfn.LAMBDA(_xlpm.x,TRIM(SUBSTITUTE(_xlpm.x,CHAR(160),""))),_xlpm.rng,'Manufactured Items Models'!$B:$BA,_xlpm.rows,{12;24;36;48;60;72;84;96;108},_xlpm.itemCols,{1,7,13,19,25,31,37,43,49},_xlpm.priceCols,_xlpm.itemCols+3,_xlpm.items,INDEX(_xlpm.rng,_xlpm.rows,_xlpm.itemCols),_xlpm.prices,INDEX(_xlpm.rng,_xlpm.rows,_xlpm.priceCols),_xlpm.needle,_xlpm.norm($D6),_xlpm.hit,SUMPRODUCT((_xlpm.norm(_xlpm.items)=_xlpm.needle)*_xlpm.prices),IF(_xlpm.hit=0,"",_xlpm.hit)))} -> 39.444965 | F6: 0 | G6: 0.62144819 | H6: =IF(OR(E6="",G6=""),0,(E6+F6)/(1-G6)) -> 104.19965 | J6: =+I6*H6 -> 0 | K6: =+J6*G6 -> 0 | L6: 0 | M6: Quoted | Z6: 5 Gallon Pails | AA6: Natural Blue L1355 (11) | AB6: Natural Blue L1355 (11)
A7: Black Label | B7: 1 | C7: Manufactured | D7: Natural Red D1307 (40) | E7: {=IF(LOWER(TRIM($C7))="distributed",_xlfn.XLOOKUP($D7,'Cost Master List'!$B:$B,'Cost Master List'!$M:$M,"",0),_xlfn.LET(_xlpm.norm,_xlfn.LAMBDA(_xlpm.x,TRIM(SUBSTITUTE(_xlpm.x,CHAR(160),""))),_xlpm.rng,'Manufactured Items Models'!$B:$BA,_xlpm.rows,{12;24;36;48;60;72;84;96;108},_xlpm.itemCols,{1,7,13,19,25,31,37,43,49},_xlpm.priceCols,_xlpm.itemCols+3,_xlpm.items,INDEX(_xlpm.rng,_xlpm.rows,_xlpm.itemCols),_xlpm.prices,INDEX(_xlpm.rng,_xlpm.rows,_xlpm.priceCols),_xlpm.needle,_xlpm.norm($D7),_xlpm.hit,SUMPRODUCT((_xlpm.norm(_xlpm.items)=_xlpm.needle)*_xlpm.prices),IF(_xlpm.hit=0,"",_xlpm.hit)))} -> 7.6097008 | F7: 0 | G7: 0.16832757 | H7: =IF(OR(E7="",G7=""),0,(E7+F7)/(1-G7)) -> 9.1498775 | I7: 47000 | J7: =+I7*H7 -> 430044.24 | K7: =+J7*G7 -> 72388.303 | L7: 1 | M7: Accepted | O7: January | P7: Every Month | Z7: Amaranth (Vidhi) | AA7: Natural Red C1409 (8) | AB7: Natural Red C1409 (8)
A8: Black Label | B8: 1 | C8: Distributed | D8: Carnosox 10% liquid | E8: {=IF(LOWER(TRIM($C8))="distributed",_xlfn.XLOOKUP($D8,'Cost Master List'!$B:$B,'Cost Master List'!$M:$M,"",0),_xlfn.LET(_xlpm.norm,_xlfn.LAMBDA(_xlpm.x,TRIM(SUBSTITUTE(_xlpm.x,CHAR(160),""))),_xlpm.rng,'Manufactured Items Models'!$B:$BA,_xlpm.rows,{12;24;36;48;60;72;84;96;108},_xlpm.itemCols,{1,7,13,19,25,31,37,43,49},_xlpm.priceCols,_xlpm.itemCols+3,_xlpm.items,INDEX(_xlpm.rng,_xlpm.rows,_xlpm.itemCols),_xlpm.prices,INDEX(_xlpm.rng,_xlpm.rows,_xlpm.priceCols),_xlpm.needle,_xlpm.norm($D8),_xlpm.hit,SUMPRODUCT((_xlpm.norm(_xlpm.items)=_xlpm.needle)*_xlpm.prices),IF(_xlpm.hit=0,"",_xlpm.hit)))} -> 21.384184 | F8: 0 | G8: 0.34585448 | H8: =IF(OR(E8="",G8=""),0,(E8+F8)/(1-G8)) -> 32.690255 | I8: 1000 | J8: =+I8*H8 -> 32690.255 | K8: =+J8*G8 -> 11306.071 | L8: 1 | M8: Quoted | O8: January | P8: Every 6 Weeks | Z8: Annatto Extract P1315 (IFF) | AA8: Natural Red B1416 (8) | AB8: Natural Red B1416 (8)
A9: Brimhall | B9: 0.6 | C9: Distributed | D9: Natural Yellow G2422 (Nutracean) | E9: {=IF(LOWER(TRIM($C9))="distributed",_xlfn.XLOOKUP($D9,'Cost Master List'!$B:$B,'Cost Master List'!$M:$M,"",0),_xlfn.LET(_xlpm.norm,_xlfn.LAMBDA(_xlpm.x,TRIM(SUBSTITUTE(_xlpm.x,CHAR(160),""))),_xlpm.rng,'Manufactured Items Models'!$B:$BA,_xlpm.rows,{12;24;36;48;60;72;84;96;108},_xlpm.itemCols,{1,7,13,19,25,31,37,43,49},_xlpm.priceCols,_xlpm.itemCols+3,_xlpm.items,INDEX(_xlpm.rng,_xlpm.rows,_xlpm.itemCols),_xlpm.prices,INDEX(_xlpm.rng,_xlpm.rows,_xlpm.priceCols),_xlpm.needle,_xlpm.norm($D9),_xlpm.hit,SUMPRODUCT((_xlpm.norm(_xlpm.items)=_xlpm.needle)*_xlpm.prices),IF(_xlpm.hit=0,"",_xlpm.hit)))} -> 34.906242 | F9: 0 | G9: 0.34755501 | H9: =IF(OR(E9="",G9=""),0,(E9+F9)/(1-G9)) -> 53.500667 | I9: 3000 | J9: =+I9*H9 -> 160502 | K9: =+J9*G9 -> 55783.274 | L9: 1 | M9: Quoted | O9: February | P9: Every 6 Weeks | Z9: Annatto Extract P1315 (Imbarex) | AA9: Natural Yellow G3401-N (44) | AB9: Natural Yellow G3401-N (44)
A10: Brimhall | B10: 0.5 | C10: Distributed | D10: Annatto Extract P2404 (Cyber Colors) | E10: {=IF(LOWER(TRIM($C10))="distributed",_xlfn.XLOOKUP($D10,'Cost Master List'!$B:$B,'Cost Master List'!$M:$M,"",0),_xlfn.LET(_xlpm.norm,_xlfn.LAMBDA(_xlpm.x,TRIM(SUBSTITUTE(_xlpm.x,CHAR(160),""))),_xlpm.rng,'Manufactured Items Models'!$B:$BA,_xlpm.rows,{12;24;36;48;60;72;84;96;108},_xlpm.itemCols,{1,7,13,19,25,31,37,43,49},_xlpm.priceCols,_xlpm.itemCols+3,_xlpm.items,INDEX(_xlpm.rng,_xlpm.rows,_xlpm.itemCols),_xlpm.prices,INDEX(_xlpm.rng,_xlpm.rows,_xlpm.priceCols),_xlpm.needle,_xlpm.norm($D10),_xlpm.hit,SUMPRODUCT((_xlpm.norm(_xlpm.items)=_xlpm.needle)*_xlpm.prices),IF(_xlpm.hit=0,"",_xlpm.hit)))} -> 7.3221235 | F10: 0 | G10: 0.30133024 | H10: =IF(OR(E10="",G10=""),0,(E10+F10)/(1-G10)) -> 10.480092 | I10: 6000 | J10: =+I10*H10 -> 62880.553 | K10: =+J10*G10 -> 18947.812 | L10: 1 | M10: Quoted | O10: February | P10: Every Other Month | Z10: Annatto Extract P2404 (Cyber Colors) | AA10: Annatto Extract P2401 (40) | AB10: Annatto Extract P2401 (40)
A11: Brimhall | B11: 0.1 | C11: Distributed | D11: FD&C Red 40 HD Lake (Vidhi) | E11: {=IF(LOWER(TRIM($C11))="distributed",_xlfn.XLOOKUP($D11,'Cost Master List'!$B:$B,'Cost Master List'!$M:$M,"",0),_xlfn.LET(_xlpm.norm,_xlfn.LAMBDA(_xlpm.x,TRIM(SUBSTITUTE(_xlpm.x,CHAR(160),""))),_xlpm.rng,'Manufactured Items Models'!$B:$BA,_xlpm.rows,{12;24;36;48;60;72;84;96;108},_xlpm.itemCols,{1,7,13,19,25,31,37,43,49},_xlpm.priceCols,_xlpm.itemCols+3,_xlpm.items,INDEX(_xlpm.rng,_xlpm.rows,_xlpm.itemCols),_xlpm.prices,INDEX(_xlpm.rng,_xlpm.rows,_xlpm.priceCols),_xlpm.needle,_xlpm.norm($D11),_xlpm.hit,SUMPRODUCT((_xlpm.norm(_xlpm.items)=_xlpm.needle)*_xlpm.prices),IF(_xlpm.hit=0,"",_xlpm.hit)))} -> 11.455716 | F11: 0 | G11: 0.24633546 | H11: =IF(OR(E11="",G11=""),0,(E11+F11)/(1-G11)) -> 15.20002 | I11: 20000 | J11: =+I11*H11 -> 304000.39 | K11: =+J11*G11 -> 74886.078 | L11: 1 | M11: Quoted | O11: May | P11: Every 6 Weeks | Z11: Annatto Extract P2408 (Cyber Colors) | AA11: Natural Red D1305 (40) | AB11: Natural Red D1305 (40)
A12: Marzetti | B12: 0.6 | C12: Distributed | E12: {=IF(LOWER(TRIM($C12))="distributed",_xlfn.XLOOKUP($D12,'Cost Master List'!$B:$B,'Cost Master List'!$M:$M,"",0),_xlfn.LET(_xlpm.norm,_xlfn.LAMBDA(_xlpm.x,TRIM(SUBSTITUTE(_xlpm.x,CHAR(160),""))),_xlpm.rng,'Manufactured Items Models'!$B:$BA,_xlpm.rows,{12;24;36;48;60;72;84;96;108},_xlpm.itemCols,{1,7,13,19,25,31,37,43,49},_xlpm.priceCols,_xlpm.itemCols+3,_xlpm.items,INDEX(_xlpm.rng,_xlpm.rows,_xlpm.itemCols),_xlpm.prices,INDEX(_xlpm.rng,_xlpm.rows,_xlpm.priceCols),_xlpm.needle,_xlpm.norm($D12),_xlpm.hit,SUMPRODUCT((_xlpm.norm(_xlpm.items)=_xlpm.needle)*_xlpm.prices),IF(_xlpm.hit=0,"",_xlpm.hit)))} -> 0 | F12: 0 | H12: =IF(OR(E12="",G12=""),0,(E12+F12)/(1-G12)) -> 0 | I12: 13000 | J12: =+I12*H12 -> 0 | K12: =+J12*G12 -> 0 | M12: Quoted | O12: March | P12: Every Month | Z12: Annatto Extract WS5 (Cyber Colors) | AA12: Natural Blue L1405 (44) | AB12: Natural Blue L1405 (44)
A13: Marzetti | B13: 0.6 | C13: Distributed | D13: Caramel Color R1410 (Alvin) | E13: {=IF(LOWER(TRIM($C13))="distributed",_xlfn.XLOOKUP($D13,'Cost Master List'!$B:$B,'Cost Master List'!$M:$M,"",0),_xlfn.LET(_xlpm.norm,_xlfn.LAMBDA(_xlpm.x,TRIM(SUBSTITUTE(_xlpm.x,CHAR(160),""))),_xlpm.rng,'Manufactured Items Models'!$B:$BA,_xlpm.rows,{12;24;36;48;60;72;84;96;108},_xlpm.itemCols,{1,7,13,19,25,31,37,43,49},_xlpm.priceCols,_xlpm.itemCols+3,_xlpm.items,INDEX(_xlpm.rng,_xlpm.rows,_xlpm.itemCols),_xlpm.prices,INDEX(_xlpm.rng,_xlpm.rows,_xlpm.priceCols),_xlpm.needle,_xlpm.norm($D13),_xlpm.hit,SUMPRODUCT((_xlpm.norm(_xlpm.items)=_xlpm.needle)*_xlpm.prices),IF(_xlpm.hit=0,"",_xlpm.hit)))} -> 1.0432637 | F13: 0 | G13: 0.25489346 | H13: =IF(OR(E13="",G13=""),0,(E13+F13)/(1-G13)) -> 1.4001537 | I13: 75000 | J13: =+I13*H13 -> 105011.53 | K13: =+J13*G13 -> 26766.751 | L13: 0.7 | M13: Quoted | O13: March | P13: Every Month | Z13: Ascorbic Acid (Brenntag) | AA13: Natural Red C1309 (44) | AB13: Natural Red C1309 (44)
A14: Marzetti | B14: 0.6 | C14: Manufactured | D14: Annatto Extract P2401 (8) | E14: {=IF(LOWER(TRIM($C14))="distributed",_xlfn.XLOOKUP($D14,'Cost Master List'!$B:$B,'Cost Master List'!$M:$M,"",0),_xlfn.LET(_xlpm.norm,_xlfn.LAMBDA(_xlpm.x,TRIM(SUBSTITUTE(_xlpm.x,CHAR(160),""))),_xlpm.rng,'Manufactured Items Models'!$B:$BA,_xlpm.rows,{12;24;36;48;60;72;84;96;108},_xlpm.itemCols,{1,7,13,19,25,31,37,43,49},_xlpm.priceCols,_xlpm.itemCols+3,_xlpm.items,INDEX(_xlpm.rng,_xlpm.rows,_xlpm.itemCols),_xlpm.prices,INDEX(_xlpm.rng,_xlpm.rows,_xlpm.priceCols),_xlpm.needle,_xlpm.norm($D14),_xlpm.hit,SUMPRODUCT((_xlpm.norm(_xlpm.items)=_xlpm.needle)*_xlpm.prices),IF(_xlpm.hit=0,"",_xlpm.hit)))} -> 1.9418671 | F14: 0 | G14: 0.6416698 | H14: =IF(OR(E14="",G14=""),0,(E14+F14)/(1-G14)) -> 5.4192113 | I14: 50000 | J14: =+I14*H14 -> 270960.56 | K14: =+J14*G14 -> 173867.21 | L14: 0.8 | M14: Quoted | O14: March | P14: Every Month | Z14: Beet Powder 0.8% (Nutracean) | AA14: Annatto Extract P2404 | AB14: Annatto Extract P2404
A15: NPIC | B15: 0.85 | C15: Distributed | D15: Natural Green J1410 (Cyber Colors) | E15: {=IF(LOWER(TRIM($C15))="distributed",_xlfn.XLOOKUP($D15,'Cost Master List'!$B:$B,'Cost Master List'!$M:$M,"",0),_xlfn.LET(_xlpm.norm,_xlfn.LAMBDA(_xlpm.x,TRIM(SUBSTITUTE(_xlpm.x,CHAR(160),""))),_xlpm.rng,'Manufactured Items Models'!$B:$BA,_xlpm.rows,{12;24;36;48;60;72;84;96;108},_xlpm.itemCols,{1,7,13,19,25,31,37,43,49},_xlpm.priceCols,_xlpm.itemCols+3,_xlpm.items,INDEX(_xlpm.rng,_xlpm.rows,_xlpm.itemCols),_xlpm.prices,INDEX(_xlpm.rng,_xlpm.rows,_xlpm.priceCols),_xlpm.needle,_xlpm.norm($D15),_xlpm.hit,SUMPRODUCT((_xlpm.norm(_xlpm.items)=_xlpm.needle)*_xlpm.prices),IF(_xlpm.hit=0,"",_xlpm.hit)))} -> 20.375507 | F15: 0 | G15: 0.37258444 | H15: =IF(OR(E15="",G15=""),0,(E15+F15)/(1-G15)) -> 32.475298 | I15: 12000 | J15: =+I15*H15 -> 389703.57 | K15: =+J15*G15 -> 145197.49 | L15: 1 | M15: Quoted | O15: January | P15: Every 6 Weeks | Z15: Beet Powder 2.1% (Nutracean) | AA15: Natural Red D1307 (40) | AB15: Natural Red D1307 (40)
A16: P&L Solutions | B16: 1 | C16: Distributed | D16: Amaranth (Vidhi) | E16: {=IF(LOWER(TRIM($C16))="distributed",_xlfn.XLOOKUP($D16,'Cost Master List'!$B:$B,'Cost Master List'!$M:$M,"",0),_xlfn.LET(_xlpm.norm,_xlfn.LAMBDA(_xlpm.x,TRIM(SUBSTITUTE(_xlpm.x,CHAR(160),""))),_xlpm.rng,'Manufactured Items Models'!$B:$BA,_xlpm.rows,{12;24;36;48;60;72;84;96;108},_xlpm.itemCols,{1,7,13,19,25,31,37,43,49},_xlpm.priceCols,_xlpm.itemCols+3,_xlpm.items,INDEX(_xlpm.rng,_xlpm.rows,_xlpm.itemCols),_xlpm.prices,INDEX(_xlpm.rng,_xlpm.rows,_xlpm.priceCols),_xlpm.needle,_xlpm.norm($D16),_xlpm.hit,SUMPRODUCT((_xlpm.norm(_xlpm.items)=_xlpm.needle)*_xlpm.prices),IF(_xlpm.hit=0,"",_xlpm.hit)))} -> 4.0142972 | F16: 0 | G16: 0.35 | H16: =IF(OR(E16="",G16=""),0,(E16+F16)/(1-G16)) -> 6.1758419 | I16: 2200 | J16: =+I16*H16 -> 13586.852 | K16: =+J16*G16 -> 4755.3983 | L16: 1 | M16: Quoted | O16: January | P16: Quarterly | Z16: Black Carrot EV100 (Nutracean) | AA16: Annatto Extract P1411 (8) | AB16: Annatto Extract P1411 (8)
A17: P&L Solutions | B17: 1 | C17: Distributed | D17: FD&C Yellow 6 Powder (Vidhi) | E17: {=IF(LOWER(TRIM($C17))="distributed",_xlfn.XLOOKUP($D17,'Cost Master List'!$B:$B,'Cost Master List'!$M:$M,"",0),_xlfn.LET(_xlpm.norm,_xlfn.LAMBDA(_xlpm.x,TRIM(SUBSTITUTE(_xlpm.x,CHAR(160),""))),_xlpm.rng,'Manufactured Items Models'!$B:$BA,_xlpm.rows,{12;24;36;48;60;72;84;96;108},_xlpm.itemCols,{1,7,13,19,25,31,37,43,49},_xlpm.priceCols,_xlpm.itemCols+3,_xlpm.items,INDEX(_xlpm.rng,_xlpm.rows,_xlpm.itemCols),_xlpm.prices,INDEX(_xlpm.rng,_xlpm.rows,_xlpm.priceCols),_xlpm.needle,_xlpm.norm($D17),_xlpm.hit,SUMPRODUCT((_xlpm.norm(_xlpm.items)=_xlpm.needle)*_xlpm.prices),IF(_xlpm.hit=0,"",_xlpm.hit)))} -> 4.427974 | F17: 0 | G17: 0.20360338 | H17: =IF(OR(E17="",G17=""),0,(E17+F17)/(1-G17)) -> 5.560011 | I17: 13200 | J17: =+I17*H17 -> 73392.145 | K17: =+J17*G17 -> 14942.889 | L17: 1 | M17: Quoted | O17: January | P17: Quarterly | Z17: Blue USFDA Poly Bag 32x32x.004 | AA17: Annatto Extract P1411 (44) | AB17: Annatto Extract P1411 (44)
A18: P&L Solutions | B18: 1 | C18: Distributed | D18: FD&C Red 3 Powder (Vidhi) | E18: {=IF(LOWER(TRIM($C18))="distributed",_xlfn.XLOOKUP($D18,'Cost Master List'!$B:$B,'Cost Master List'!$M:$M,"",0),_xlfn.LET(_xlpm.norm,_xlfn.LAMBDA(_xlpm.x,TRIM(SUBSTITUTE(_xlpm.x,CHAR(160),""))),_xlpm.rng,'Manufactured Items Models'!$B:$BA,_xlpm.rows,{12;24;36;48;60;72;84;96;108},_xlpm.itemCols,{1,7,13,19,25,31,37,43,49},_xlpm.priceCols,_xlpm.itemCols+3,_xlpm.items,INDEX(_xlpm.rng,_xlpm.rows,_xlpm.itemCols),_xlpm.prices,INDEX(_xlpm.rng,_xlpm.rows,_xlpm.priceCols),_xlpm.needle,_xlpm.norm($D18),_xlpm.hit,SUMPRODUCT((_xlpm.norm(_xlpm.items)=_xlpm.needle)*_xlpm.prices),IF(_xlpm.hit=0,"",_xlpm.hit)))} -> 51.563535 | F18: 0 | G18: 0.17180318 | H18: =IF(OR(E18="",G18=""),0,(E18+F18)/(1-G18)) -> 62.260001 | I18: 2640 | J18: =+I18*H18 -> 164366.4 | K18: =+J18*G18 -> 28238.672 | L18: 1 | M18: Quoted | O18: January | P18: Quarterly | Z18: Blue USFDA Poly Bag 34x40x.004 | AA18: Annatto Extract P1414 (8) | AB18: Annatto Extract P1414 (8)
A19: P&L Solutions | B19: 1 | C19: Distributed | D19: FD&C Yellow 5 Powder (Vidhi) | E19: {=IF(LOWER(TRIM($C19))="distributed",_xlfn.XLOOKUP($D19,'Cost Master List'!$B:$B,'Cost Master List'!$M:$M,"",0),_xlfn.LET(_xlpm.norm,_xlfn.LAMBDA(_xlpm.x,TRIM(SUBSTITUTE(_xlpm.x,CHAR(160),""))),_xlpm.rng,'Manufactured Items Models'!$B:$BA,_xlpm.rows,{12;24;36;48;60;72;84;96;108},_xlpm.itemCols,{1,7,13,19,25,31,37,43,49},_xlpm.priceCols,_xlpm.itemCols+3,_xlpm.items,INDEX(_xlpm.rng,_xlpm.rows,_xlpm.itemCols),_xlpm.prices,INDEX(_xlpm.rng,_xlpm.rows,_xlpm.priceCols),_xlpm.needle,_xlpm.norm($D19),_xlpm.hit,SUMPRODUCT((_xlpm.norm(_xlpm.items)=_xlpm.needle)*_xlpm.prices),IF(_xlpm.hit=0,"",_xlpm.hit)))} -> 4.7829104 | F19: 0 | G19: 0.20151936 | H19: =IF(OR(E19="",G19=""),0,(E19+F19)/(1-G19)) -> 5.9900143 | I19: 2200 | J19: =+I19*H19 -> 13178.031 | K19: =+J19*G19 -> 2655.6284 | L19: 1 | M19: Quoted | O19: January | P19: Quarterly | Z19: Butterfly Pea (Hiche) | AA19: Annatto Extract P1414 (44) | AB19: Annatto Extract P1414 (44)
A20: Prime Ingredients | B20: 0.9 | C20: Distributed | D20: Natural Blue L1300 (Hiche) | E20: {=IF(LOWER(TRIM($C20))="distributed",_xlfn.XLOOKUP($D20,'Cost Master List'!$B:$B,'Cost Master List'!$M:$M,"",0),_xlfn.LET(_xlpm.norm,_xlfn.LAMBDA(_xlpm.x,TRIM(SUBSTITUTE(_xlpm.x,CHAR(160),""))),_xlpm.rng,'Manufactured Items Models'!$B:$BA,_xlpm.rows,{12;24;36;48;60;72;84;96;108},_xlpm.itemCols,{1,7,13,19,25,31,37,43,49},_xlpm.priceCols,_xlpm.itemCols+3,_xlpm.items,INDEX(_xlpm.rng,_xlpm.rows,_xlpm.itemCols),_xlpm.prices,INDEX(_xlpm.rng,_xlpm.rows,_xlpm.priceCols),_xlpm.needle,_xlpm.norm($D20),_xlpm.hit,SUMPRODUCT((_xlpm.norm(_xlpm.items)=_xlpm.needle)*_xlpm.prices),IF(_xlpm.hit=0,"",_xlpm.hit)))} -> 51.473723 | F20: 0 | G20: 0.48526216 | H20: =IF(OR(E20="",G20=""),0,(E20+F20)/(1-G20)) -> 99.999883 | I20: 3400 | J20: =+I20*H20 -> 339999.6 | K20: =+J20*G20 -> 164988.94 | L20: 1 | M20: Quoted | O20: January | P20: Every Month | Z20: Caramel Color R1410 (Alvin) | AA20: Annatto Extract P1428 (8) | AB20: Annatto Extract P1428 (8)
A21: Prime Ingredients | B21: 0.9 | C21: Manufactured | D21: Natural Red D1305 (40) | E21: {=IF(LOWER(TRIM($C21))="distributed",_xlfn.XLOOKUP($D21,'Cost Master List'!$B:$B,'Cost Master List'!$M:$M,"",0),_xlfn.LET(_xlpm.norm,_xlfn.LAMBDA(_xlpm.x,TRIM(SUBSTITUTE(_xlpm.x,CHAR(160),""))),_xlpm.rng,'Manufactured Items Models'!$B:$BA,_xlpm.rows,{12;24;36;48;60;72;84;96;108},_xlpm.itemCols,{1,7,13,19,25,31,37,43,49},_xlpm.priceCols,_xlpm.itemCols+3,_xlpm.items,INDEX(_xlpm.rng,_xlpm.rows,_xlpm.itemCols),_xlpm.prices,INDEX(_xlpm.rng,_xlpm.rows,_xlpm.priceCols),_xlpm.needle,_xlpm.norm($D21),_xlpm.hit,SUMPRODUCT((_xlpm.norm(_xlpm.items)=_xlpm.needle)*_xlpm.prices),IF(_xlpm.hit=0,"",_xlpm.hit)))} -> 5.9834568 | F21: 0 | G21: 0.31617476 | H21: =IF(OR(E21="",G21=""),0,(E21+F21)/(1-G21)) -> 8.7499795 | I21: 70000 | J21: =+I21*H21 -> 612498.56 | K21: =+J21*G21 -> 193656.59 | L21: 1 | M21: Quoted | N21: Delivered | O21: January | P21: Every Other Month | Z21: Carnosic 10% liquid | AA21: Annatto Extract P1428 (44) | AB21: Annatto Extract P1428 (44)
A22: Prime Ingredients | B22: 0.9 | C22: Distributed | D22: Annatto Extract P1315 (IFF) | E22: {=IF(LOWER(TRIM($C22))="distributed",_xlfn.XLOOKUP($D22,'Cost Master List'!$B:$B,'Cost Master List'!$M:$M,"",0),_xlfn.LET(_xlpm.norm,_xlfn.LAMBDA(_xlpm.x,TRIM(SUBSTITUTE(_xlpm.x,CHAR(160),""))),_xlpm.rng,'Manufactured Items Models'!$B:$BA,_xlpm.rows,{12;24;36;48;60;72;84;96;108},_xlpm.itemCols,{1,7,13,19,25,31,37,43,49},_xlpm.priceCols,_xlpm.itemCols+3,_xlpm.items,INDEX(_xlpm.rng,_xlpm.rows,_xlpm.itemCols),_xlpm.prices,INDEX(_xlpm.rng,_xlpm.rows,_xlpm.priceCols),_xlpm.needle,_xlpm.norm($D22),_xlpm.hit,SUMPRODUCT((_xlpm.norm(_xlpm.items)=_xlpm.needle)*_xlpm.prices),IF(_xlpm.hit=0,"",_xlpm.hit)))} -> 26.0952 | F22: 0 | G22: 0.17811387 | H22: =IF(OR(E22="",G22=""),0,(E22+F22)/(1-G22)) -> 31.750384 | I22: 1200 | J22: =+I22*H22 -> 38100.461 | K22: =+J22*G22 -> 6786.2205 | L22: 1 | M22: Quoted | O22: January | P22: Every 6 Weeks | Z22: Carnosic 15% pwd
A23: Prime Ingredients | B23: 1 | C23: Distributed | D23: Annatto Extract P2404 (Cyber Colors) | E23: {=IF(LOWER(TRIM($C23))="distributed",_xlfn.XLOOKUP($D23,'Cost Master List'!$B:$B,'Cost Master List'!$M:$M,"",0),_xlfn.LET(_xlpm.norm,_xlfn.LAMBDA(_xlpm.x,TRIM(SUBSTITUTE(_xlpm.x,CHAR(160),""))),_xlpm.rng,'Manufactured Items Models'!$B:$BA,_xlpm.rows,{12;24;36;48;60;72;84;96;108},_xlpm.itemCols,{1,7,13,19,25,31,37,43,49},_xlpm.priceCols,_xlpm.itemCols+3,_xlpm.items,INDEX(_xlpm.rng,_xlpm.rows,_xlpm.itemCols),_xlpm.prices,INDEX(_xlpm.rng,_xlpm.rows,_xlpm.priceCols),_xlpm.needle,_xlpm.norm($D23),_xlpm.hit,SUMPRODUCT((_xlpm.norm(_xlpm.items)=_xlpm.needle)*_xlpm.prices),IF(_xlpm.hit=0,"",_xlpm.hit)))} -> 7.3221235 | F23: 0 | G23: 0.28564673 | H23: =IF(OR(E23="",G23=""),0,(E23+F23)/(1-G23)) -> 10.250004 | I23: 50000 | J23: =+I23*H23 -> 512500.18 | K23: =+J23*G23 -> 146394 | L23: 1 | M23: Quoted | N23: Delivered | O23: January | P23: Every 6 Weeks | Z23: Carnosic 20% pwd
A24: Prime Ingredients | B24: 0.9 | C24: Distributed | D24: Natural Yellow H1385 (Synthite) | E24: {=IF(LOWER(TRIM($C24))="distributed",_xlfn.XLOOKUP($D24,'Cost Master List'!$B:$B,'Cost Master List'!$M:$M,"",0),_xlfn.LET(_xlpm.norm,_xlfn.LAMBDA(_xlpm.x,TRIM(SUBSTITUTE(_xlpm.x,CHAR(160),""))),_xlpm.rng,'Manufactured Items Models'!$B:$BA,_xlpm.rows,{12;24;36;48;60;72;84;96;108},_xlpm.itemCols,{1,7,13,19,25,31,37,43,49},_xlpm.priceCols,_xlpm.itemCols+3,_xlpm.items,INDEX(_xlpm.rng,_xlpm.rows,_xlpm.itemCols),_xlpm.prices,INDEX(_xlpm.rng,_xlpm.rows,_xlpm.priceCols),_xlpm.needle,_xlpm.norm($D24),_xlpm.hit,SUMPRODUCT((_xlpm.norm(_xlpm.items)=_xlpm.needle)*_xlpm.prices),IF(_xlpm.hit=0,"",_xlpm.hit)))} -> 10.947692 | F24: 0 | G24: 0.4 | H24: =IF(OR(E24="",G24=""),0,(E24+F24)/(1-G24)) -> 18.246153 | I24: 17000 | J24: =+I24*H24 -> 310184.6 | K24: =+J24*G24 -> 124073.84 | L24: 1 | O24: January | P24: Every 6 Weeks | Z24: Carnosic 5% liquid
A25: Pylam | B25: 0 | C25: Distributed | D25: FD&C Yellow 5 Powder (Vidhi) | E25: {=IF(LOWER(TRIM($C25))="distributed",_xlfn.XLOOKUP($D25,'Cost Master List'!$B:$B,'Cost Master List'!$M:$M,"",0),_xlfn.LET(_xlpm.norm,_xlfn.LAMBDA(_xlpm.x,TRIM(SUBSTITUTE(_xlpm.x,CHAR(160),""))),_xlpm.rng,'Manufactured Items Models'!$B:$BA,_xlpm.rows,{12;24;36;48;60;72;84;96;108},_xlpm.itemCols,{1,7,13,19,25,31,37,43,49},_xlpm.priceCols,_xlpm.itemCols+3,_xlpm.items,INDEX(_xlpm.rng,_xlpm.rows,_xlpm.itemCols),_xlpm.prices,INDEX(_xlpm.rng,_xlpm.rows,_xlpm.priceCols),_xlpm.needle,_xlpm.norm($D25),_xlpm.hit,SUMPRODUCT((_xlpm.norm(_xlpm.items)=_xlpm.needle)*_xlpm.prices),IF(_xlpm.hit=0,"",_xlpm.hit)))} -> 4.7829104 | F25: 1.2 | G25: 0.30437086 | H25: =IF(OR(E25="",G25=""),0,(E25+F25)/(1-G25)) -> 8.6007186 | I25: 10000 | J25: =+I25*H25 -> 86007.186 | K25: =+J25*G25 -> 26178.081 | L25: 1 | M25: Quoted | O25: January | P25: Semi-Annual | Z25: Carnosox 10% liquid
A26: Pylam | B26: 0 | C26: Distributed | D26: FD&C Blue 1 Powder (Vidhi) | E26: {=IF(LOWER(TRIM($C26))="distributed",_xlfn.XLOOKUP($D26,'Cost Master List'!$B:$B,'Cost Master List'!$M:$M,"",0),_xlfn.LET(_xlpm.norm,_xlfn.LAMBDA(_xlpm.x,TRIM(SUBSTITUTE(_xlpm.x,CHAR(160),""))),_xlpm.rng,'Manufactured Items Models'!$B:$BA,_xlpm.rows,{12;24;36;48;60;72;84;96;108},_xlpm.itemCols,{1,7,13,19,25,31,37,43,49},_xlpm.priceCols,_xlpm.itemCols+3,_xlpm.items,INDEX(_xlpm.rng,_xlpm.rows,_xlpm.itemCols),_xlpm.prices,INDEX(_xlpm.rng,_xlpm.rows,_xlpm.priceCols),_xlpm.needle,_xlpm.norm($D26),_xlpm.hit,SUMPRODUCT((_xlpm.norm(_xlpm.items)=_xlpm.needle)*_xlpm.prices),IF(_xlpm.hit=0,"",_xlpm.hit)))} -> 12.236576 | F26: 1.2 | G26: 0.28718397 | H26: =IF(OR(E26="",G26=""),0,(E26+F26)/(1-G26)) -> 18.849991 | I26: 2000 | J26: =+I26*H26 -> 37699.982 | K26: =+J26*G26 -> 10826.831 | L26: 1 | M26: Quoted | O26: February | P26: Semi-Annual | Z26: Carnosox 10% powder
A27: Prime Ingredients | B27: 0.9 | C27: Manufactured | D27: Annatto Extract P1411 (8) | E27: {=IF(LOWER(TRIM($C27))="distributed",_xlfn.XLOOKUP($D27,'Cost Master List'!$B:$B,'Cost Master List'!$M:$M,"",0),_xlfn.LET(_xlpm.norm,_xlfn.LAMBDA(_xlpm.x,TRIM(SUBSTITUTE(_xlpm.x,CHAR(160),""))),_xlpm.rng,'Manufactured Items Models'!$B:$BA,_xlpm.rows,{12;24;36;48;60;72;84;96;108},_xlpm.itemCols,{1,7,13,19,25,31,37,43,49},_xlpm.priceCols,_xlpm.itemCols+3,_xlpm.items,INDEX(_xlpm.rng,_xlpm.rows,_xlpm.itemCols),_xlpm.prices,INDEX(_xlpm.rng,_xlpm.rows,_xlpm.priceCols),_xlpm.needle,_xlpm.norm($D27),_xlpm.hit,SUMPRODUCT((_xlpm.norm(_xlpm.items)=_xlpm.needle)*_xlpm.prices),IF(_xlpm.hit=0,"",_xlpm.hit)))} -> 2.6612949 | F27: 0 | G27: 0.33468594 | H27: =IF(OR(E27="",G27=""),0,(E27+F27)/(1-G27)) -> 4.0000582 | I27: 520 | J27: =+I27*H27 -> 2080.0302 | K27: =+J27*G27 -> 696.15688 | L27: 1 | M27: Quoted | O27: February | P27: Every 6 Weeks | Z27: Carnosox PP
A28: Prime Ingredients | B28: 0.9 | C28: Manufactured | D28: Annatto Extract P1414 (8) | E28: {=IF(LOWER(TRIM($C28))="distributed",_xlfn.XLOOKUP($D28,'Cost Master List'!$B:$B,'Cost Master List'!$M:$M,"",0),_xlfn.LET(_xlpm.norm,_xlfn.LAMBDA(_xlpm.x,TRIM(SUBSTITUTE(_xlpm.x,CHAR(160),""))),_xlpm.rng,'Manufactured Items Models'!$B:$BA,_xlpm.rows,{12;24;36;48;60;72;84;96;108},_xlpm.itemCols,{1,7,13,19,25,31,37,43,49},_xlpm.priceCols,_xlpm.itemCols+3,_xlpm.items,INDEX(_xlpm.rng,_xlpm.rows,_xlpm.itemCols),_xlpm.prices,INDEX(_xlpm.rng,_xlpm.rows,_xlpm.priceCols),_xlpm.needle,_xlpm.norm($D28),_xlpm.hit,SUMPRODUCT((_xlpm.norm(_xlpm.items)=_xlpm.needle)*_xlpm.prices),IF(_xlpm.hit=0,"",_xlpm.hit)))} -> 3.0140088 | F28: 0 | G28: 0.39478428 | H28: =IF(OR(E28="",G28=""),0,(E28+F28)/(1-G28)) -> 4.980057 | I28: 2700 | J28: =+I28*H28 -> 13446.154 | K28: =+J28*G28 -> 5308.3302 | L28: 1 | M28: Quoted | O28: February | P28: Every 6 Weeks | Z28: Citric Acid*
A29: Ajinomoto | B29: 0.6 | C29: Distributed | D29: Natural Yellow H1385 (Synthite) | E29: {=IF(LOWER(TRIM($C29))="distributed",_xlfn.XLOOKUP($D29,'Cost Master List'!$B:$B,'Cost Master List'!$M:$M,"",0),_xlfn.LET(_xlpm.norm,_xlfn.LAMBDA(_xlpm.x,TRIM(SUBSTITUTE(_xlpm.x,CHAR(160),""))),_xlpm.rng,'Manufactured Items Models'!$B:$BA,_xlpm.rows,{12;24;36;48;60;72;84;96;108},_xlpm.itemCols,{1,7,13,19,25,31,37,43,49},_xlpm.priceCols,_xlpm.itemCols+3,_xlpm.items,INDEX(_xlpm.rng,_xlpm.rows,_xlpm.itemCols),_xlpm.prices,INDEX(_xlpm.rng,_xlpm.rows,_xlpm.priceCols),_xlpm.needle,_xlpm.norm($D29),_xlpm.hit,SUMPRODUCT((_xlpm.norm(_xlpm.items)=_xlpm.needle)*_xlpm.prices),IF(_xlpm.hit=0,"",_xlpm.hit)))} -> 10.947692 | F29: 0 | G29: 0.44984179 | H29: =IF(OR(E29="",G29=""),0,(E29+F29)/(1-G29)) -> 19.89917 | I29: 8000 | J29: =+I29*H29 -> 159193.36 | K29: =+J29*G29 -> 71611.827 | L29: 1 | M29: Quoted | N29: FOB MO | O29: January | P29: Every 6 Weeks | Z29: DI Water
A30: Black Label | B30: 0.5 | C30: Manufactured | D30: Natural Red C1309 (44) | E30: {=IF(LOWER(TRIM($C30))="distributed",_xlfn.XLOOKUP($D30,'Cost Master List'!$B:$B,'Cost Master List'!$M:$M,"",0),_xlfn.LET(_xlpm.norm,_xlfn.LAMBDA(_xlpm.x,TRIM(SUBSTITUTE(_xlpm.x,CHAR(160),""))),_xlpm.rng,'Manufactured Items Models'!$B:$BA,_xlpm.rows,{12;24;36;48;60;72;84;96;108},_xlpm.itemCols,{1,7,13,19,25,31,37,43,49},_xlpm.priceCols,_xlpm.itemCols+3,_xlpm.items,INDEX(_xlpm.rng,_xlpm.rows,_xlpm.itemCols),_xlpm.prices,INDEX(_xlpm.rng,_xlpm.rows,_xlpm.priceCols),_xlpm.needle,_xlpm.norm($D30),_xlpm.hit,SUMPRODUCT((_xlpm.norm(_xlpm.items)=_xlpm.needle)*_xlpm.prices),IF(_xlpm.hit=0,"",_xlpm.hit)))} -> 3.4219823 | F30: 0 | G30: 0.5 | H30: =IF(OR(E30="",G30=""),0,(E30+F30)/(1-G30)) -> 6.8439646 | I30: 1900 | J30: =+I30*H30 -> 13003.533 | K30: =+J30*G30 -> 6501.7664 | L30: 1 | O30: January | P30: Every 6 Weeks | Z30: FD&C Blue 1 Powder (Vidhi)
A31: Black Label | B31: 0.5 | C31: Manufactured | D31: Natural Red D1305 (40) | E31: {=IF(LOWER(TRIM($C31))="distributed",_xlfn.XLOOKUP($D31,'Cost Master List'!$B:$B,'Cost Master List'!$M:$M,"",0),_xlfn.LET(_xlpm.norm,_xlfn.LAMBDA(_xlpm.x,TRIM(SUBSTITUTE(_xlpm.x,CHAR(160),""))),_xlpm.rng,'Manufactured Items Models'!$B:$BA,_xlpm.rows,{12;24;36;48;60;72;84;96;108},_xlpm.itemCols,{1,7,13,19,25,31,37,43,49},_xlpm.priceCols,_xlpm.itemCols+3,_xlpm.items,INDEX(_xlpm.rng,_xlpm.rows,_xlpm.itemCols),_xlpm.prices,INDEX(_xlpm.rng,_xlpm.rows,_xlpm.priceCols),_xlpm.needle,_xlpm.norm($D31),_xlpm.hit,SUMPRODUCT((_xlpm.norm(_xlpm.items)=_xlpm.needle)*_xlpm.prices),IF(_xlpm.hit=0,"",_xlpm.hit)))} -> 5.9834568 | F31: 0 | G31: 0.32 | H31: =IF(OR(E31="",G31=""),0,(E31+F31)/(1-G31)) -> 8.7992012 | I31: 4390 | J31: =+I31*H31 -> 38628.493 | K31: =+J31*G31 -> 12361.118 | L31: 1 | O31: January | P31: Every 6 Weeks | Z31: FD&C Blue 1 Powder (Vivify)
A32: Black Label | B32: 0.5 | C32: Distributed | D32: Natural Yellow G1301-N (Cybercolors) | E32: {=IF(LOWER(TRIM($C32))="distributed",_xlfn.XLOOKUP($D32,'Cost Master List'!$B:$B,'Cost Master List'!$M:$M,"",0),_xlfn.LET(_xlpm.norm,_xlfn.LAMBDA(_xlpm.x,TRIM(SUBSTITUTE(_xlpm.x,CHAR(160),""))),_xlpm.rng,'Manufactured Items Models'!$B:$BA,_xlpm.rows,{12;24;36;48;60;72;84;96;108},_xlpm.itemCols,{1,7,13,19,25,31,37,43,49},_xlpm.priceCols,_xlpm.itemCols+3,_xlpm.items,INDEX(_xlpm.rng,_xlpm.rows,_xlpm.itemCols),_xlpm.prices,INDEX(_xlpm.rng,_xlpm.rows,_xlpm.priceCols),_xlpm.needle,_xlpm.norm($D32),_xlpm.hit,SUMPRODUCT((_xlpm.norm(_xlpm.items)=_xlpm.needle)*_xlpm.prices),IF(_xlpm.hit=0,"",_xlpm.hit)))} -> 15.034958 | F32: 0 | G32: 0.3 | H32: =IF(OR(E32="",G32=""),0,(E32+F32)/(1-G32)) -> 21.478512 | I32: 2200 | J32: =+I32*H32 -> 47252.726 | K32: =+J32*G32 -> 14175.818 | L32: 1 | O32: January | P32: Every 6 Weeks | Z32: FD&C Red 3 Powder (Vidhi)
A33: Black Label | B33: 0.5 | C33: Distributed | D33: Natural Yellow H1385 (Synthite) | E33: {=IF(LOWER(TRIM($C33))="distributed",_xlfn.XLOOKUP($D33,'Cost Master List'!$B:$B,'Cost Master List'!$M:$M,"",0),_xlfn.LET(_xlpm.norm,_xlfn.LAMBDA(_xlpm.x,TRIM(SUBSTITUTE(_xlpm.x,CHAR(160),""))),_xlpm.rng,'Manufactured Items Models'!$B:$BA,_xlpm.rows,{12;24;36;48;60;72;84;96;108},_xlpm.itemCols,{1,7,13,19,25,31,37,43,49},_xlpm.priceCols,_xlpm.itemCols+3,_xlpm.items,INDEX(_xlpm.rng,_xlpm.rows,_xlpm.itemCols),_xlpm.prices,INDEX(_xlpm.rng,_xlpm.rows,_xlpm.priceCols),_xlpm.needle,_xlpm.norm($D33),_xlpm.hit,SUMPRODUCT((_xlpm.norm(_xlpm.items)=_xlpm.needle)*_xlpm.prices),IF(_xlpm.hit=0,"",_xlpm.hit)))} -> 10.947692 | F33: 0 | G33: 0.45 | H33: =IF(OR(E33="",G33=""),0,(E33+F33)/(1-G33)) -> 19.904894 | I33: 3900 | J33: =+I33*H33 -> 77629.086 | K33: =+J33*G33 -> 34933.089 | L33: 1 | O33: January | P33: Every 6 Weeks | Z33: FD&C Red 40 Granular (Vidhi)
A34: Black Label | B34: 0.5 | C34: Distributed | D34: Natural Red O1312 (AroMoss) | E34: {=IF(LOWER(TRIM($C34))="distributed",_xlfn.XLOOKUP($D34,'Cost Master List'!$B:$B,'Cost Master List'!$M:$M,"",0),_xlfn.LET(_xlpm.norm,_xlfn.LAMBDA(_xlpm.x,TRIM(SUBSTITUTE(_xlpm.x,CHAR(160),""))),_xlpm.rng,'Manufactured Items Models'!$B:$BA,_xlpm.rows,{12;24;36;48;60;72;84;96;108},_xlpm.itemCols,{1,7,13,19,25,31,37,43,49},_xlpm.priceCols,_xlpm.itemCols+3,_xlpm.items,INDEX(_xlpm.rng,_xlpm.rows,_xlpm.itemCols),_xlpm.prices,INDEX(_xlpm.rng,_xlpm.rows,_xlpm.priceCols),_xlpm.needle,_xlpm.norm($D34),_xlpm.hit,SUMPRODUCT((_xlpm.norm(_xlpm.items)=_xlpm.needle)*_xlpm.prices),IF(_xlpm.hit=0,"",_xlpm.hit)))} -> 17.111793 | F34: 0 | G34: 0.4 | H34: =IF(OR(E34="",G34=""),0,(E34+F34)/(1-G34)) -> 28.519654 | I34: 3410 | J34: =+I34*H34 -> 97252.021 | K34: =+J34*G34 -> 38900.808 | L34: 1 | O34: January | P34: Every 6 Weeks | Z34: FD&C Red 40 HD Lake (Vidhi)
A35: Black Label | B35: 0.8 | C35: Manufactured | D35: Natural Red D1307 (40) | E35: {=IF(LOWER(TRIM($C35))="distributed",_xlfn.XLOOKUP($D35,'Cost Master List'!$B:$B,'Cost Master List'!$M:$M,"",0),_xlfn.LET(_xlpm.norm,_xlfn.LAMBDA(_xlpm.x,TRIM(SUBSTITUTE(_xlpm.x,CHAR(160),""))),_xlpm.rng,'Manufactured Items Models'!$B:$BA,_xlpm.rows,{12;24;36;48;60;72;84;96;108},_xlpm.itemCols,{1,7,13,19,25,31,37,43,49},_xlpm.priceCols,_xlpm.itemCols+3,_xlpm.items,INDEX(_xlpm.rng,_xlpm.rows,_xlpm.itemCols),_xlpm.prices,INDEX(_xlpm.rng,_xlpm.rows,_xlpm.priceCols),_xlpm.needle,_xlpm.norm($D35),_xlpm.hit,SUMPRODUCT((_xlpm.norm(_xlpm.items)=_xlpm.needle)*_xlpm.prices),IF(_xlpm.hit=0,"",_xlpm.hit)))} -> 7.6097008 | F35: 0 | G35: 0.3085 | H35: =IF(OR(E35="",G35=""),0,(E35+F35)/(1-G35)) -> 11.004629 | I35: 10780 | J35: =+I35*H35 -> 118629.9 | K35: =+J35*G35 -> 36597.324 | L35: 1 | O35: January | P35: Every 6 Weeks | Z35: FD&C Yellow 5 Powder (Vidhi)
A36: Prime Ingredients | B36: 0.6 | C36: Manufactured | D36: Natural Red B1416 (8) | E36: {=IF(LOWER(TRIM($C36))="distributed",_xlfn.XLOOKUP($D36,'Cost Master List'!$B:$B,'Cost Master List'!$M:$M,"",0),_xlfn.LET(_xlpm.norm,_xlfn.LAMBDA(_xlpm.x,TRIM(SUBSTITUTE(_xlpm.x,CHAR(160),""))),_xlpm.rng,'Manufactured Items Models'!$B:$BA,_xlpm.rows,{12;24;36;48;60;72;84;96;108},_xlpm.itemCols,{1,7,13,19,25,31,37,43,49},_xlpm.priceCols,_xlpm.itemCols+3,_xlpm.items,INDEX(_xlpm.rng,_xlpm.rows,_xlpm.itemCols),_xlpm.prices,INDEX(_xlpm.rng,_xlpm.rows,_xlpm.priceCols),_xlpm.needle,_xlpm.norm($D36),_xlpm.hit,SUMPRODUCT((_xlpm.norm(_xlpm.items)=_xlpm.needle)*_xlpm.prices),IF(_xlpm.hit=0,"",_xlpm.hit)))} -> 21.90533 | F36: 0 | G36: 0.55 | H36: =IF(OR(E36="",G36=""),0,(E36+F36)/(1-G36)) -> 48.678511 | I36: 4100 | J36: =+I36*H36 -> 199581.9 | K36: =+J36*G36 -> 109770.04 | L36: 1 | O36: February | P36: Every Month | Z36: FD&C Yellow 5 Powder (Vivify)
A37: Prime Ingredients | B37: 0.6 | C37: Distributed | D37: Natural Red Q1404 (Cybercolors) | E37: {=IF(LOWER(TRIM($C37))="distributed",_xlfn.XLOOKUP($D37,'Cost Master List'!$B:$B,'Cost Master List'!$M:$M,"",0),_xlfn.LET(_xlpm.norm,_xlfn.LAMBDA(_xlpm.x,TRIM(SUBSTITUTE(_xlpm.x,CHAR(160),""))),_xlpm.rng,'Manufactured Items Models'!$B:$BA,_xlpm.rows,{12;24;36;48;60;72;84;96;108},_xlpm.itemCols,{1,7,13,19,25,31,37,43,49},_xlpm.priceCols,_xlpm.itemCols+3,_xlpm.items,INDEX(_xlpm.rng,_xlpm.rows,_xlpm.itemCols),_xlpm.prices,INDEX(_xlpm.rng,_xlpm.rows,_xlpm.priceCols),_xlpm.needle,_xlpm.norm($D37),_xlpm.hit,SUMPRODUCT((_xlpm.norm(_xlpm.items)=_xlpm.needle)*_xlpm.prices),IF(_xlpm.hit=0,"",_xlpm.hit)))} -> 23.01417 | F37: 0 | G37: 0.3 | H37: =IF(OR(E37="",G37=""),0,(E37+F37)/(1-G37)) -> 32.877386 | I37: 34000 | J37: =+I37*H37 -> 1117831.1 | K37: =+J37*G37 -> 335349.34 | L37: 1 | N37: FOB MO | O37: February | P37: Every 6 Weeks | Z37: FD&C Yellow 6 Powder (Vidhi)
A38: Black Label | B38: 0.6 | C38: Distributed | D38: Natural Green J1410 (Cyber Colors) | E38: {=IF(LOWER(TRIM($C38))="distributed",_xlfn.XLOOKUP($D38,'Cost Master List'!$B:$B,'Cost Master List'!$M:$M,"",0),_xlfn.LET(_xlpm.norm,_xlfn.LAMBDA(_xlpm.x,TRIM(SUBSTITUTE(_xlpm.x,CHAR(160),""))),_xlpm.rng,'Manufactured Items Models'!$B:$BA,_xlpm.rows,{12;24;36;48;60;72;84;96;108},_xlpm.itemCols,{1,7,13,19,25,31,37,43,49},_xlpm.priceCols,_xlpm.itemCols+3,_xlpm.items,INDEX(_xlpm.rng,_xlpm.rows,_xlpm.itemCols),_xlpm.prices,INDEX(_xlpm.rng,_xlpm.rows,_xlpm.priceCols),_xlpm.needle,_xlpm.norm($D38),_xlpm.hit,SUMPRODUCT((_xlpm.norm(_xlpm.items)=_xlpm.needle)*_xlpm.prices),IF(_xlpm.hit=0,"",_xlpm.hit)))} -> 20.375507 | F38: 0 | G38: 0.25 | H38: =IF(OR(E38="",G38=""),0,(E38+F38)/(1-G38)) -> 27.167343 | I38: 2200 | J38: =+I38*H38 -> 59768.154 | K38: =+J38*G38 -> 14942.038 | L38: 1 | M38: Quoted | N38: FOB MO | O38: February | P38: Every 6 Weeks | Z38: Fine Flour Salt (Brenntag)
A39: Pecan Deluxe | B39: 0.6 | C39: Manufactured | D39: Natural Red E1430 (44) | E39: {=IF(LOWER(TRIM($C39))="distributed",_xlfn.XLOOKUP($D39,'Cost Master List'!$B:$B,'Cost Master List'!$M:$M,"",0),_xlfn.LET(_xlpm.norm,_xlfn.LAMBDA(_xlpm.x,TRIM(SUBSTITUTE(_xlpm.x,CHAR(160),""))),_xlpm.rng,'Manufactured Items Models'!$B:$BA,_xlpm.rows,{12;24;36;48;60;72;84;96;108},_xlpm.itemCols,{1,7,13,19,25,31,37,43,49},_xlpm.priceCols,_xlpm.itemCols+3,_xlpm.items,INDEX(_xlpm.rng,_xlpm.rows,_xlpm.itemCols),_xlpm.prices,INDEX(_xlpm.rng,_xlpm.rows,_xlpm.priceCols),_xlpm.needle,_xlpm.norm($D39),_xlpm.hit,SUMPRODUCT((_xlpm.norm(_xlpm.items)=_xlpm.needle)*_xlpm.prices),IF(_xlpm.hit=0,"",_xlpm.hit)))} -> 5.3980216 | F39: 0 | G39: 0.4 | H39: =IF(OR(E39="",G39=""),0,(E39+F39)/(1-G39)) -> 8.9967027 | I39: 3400 | J39: =+I39*H39 -> 30588.789 | K39: =+J39*G39 -> 12235.516 | L39: 1 | M39: Quoted | N39: FOB MO | O39: June | P39: Every 6 Weeks | Z39: Glycerin*
A40: Prime Ingredients | B40: 0.6 | C40: Manufactured | D40: Natural Yellow G3401-N (44) | E40: {=IF(LOWER(TRIM($C40))="distributed",_xlfn.XLOOKUP($D40,'Cost Master List'!$B:$B,'Cost Master List'!$M:$M,"",0),_xlfn.LET(_xlpm.norm,_xlfn.LAMBDA(_xlpm.x,TRIM(SUBSTITUTE(_xlpm.x,CHAR(160),""))),_xlpm.rng,'Manufactured Items Models'!$B:$BA,_xlpm.rows,{12;24;36;48;60;72;84;96;108},_xlpm.itemCols,{1,7,13,19,25,31,37,43,49},_xlpm.priceCols,_xlpm.itemCols+3,_xlpm.items,INDEX(_xlpm.rng,_xlpm.rows,_xlpm.itemCols),_xlpm.prices,INDEX(_xlpm.rng,_xlpm.rows,_xlpm.priceCols),_xlpm.needle,_xlpm.norm($D40),_xlpm.hit,SUMPRODUCT((_xlpm.norm(_xlpm.items)=_xlpm.needle)*_xlpm.prices),IF(_xlpm.hit=0,"",_xlpm.hit)))} -> 4.7495047 | F40: 0 | G40: 0.65 | H40: =IF(OR(E40="",G40=""),0,(E40+F40)/(1-G40)) -> 13.570013 | I40: 10000 | J40: =+I40*H40 -> 135700.13 | K40: =+J40*G40 -> 88205.088 | L40: 1 | M40: Quoted | N40: FOB MO | O40: February | P40: Every 6 Weeks | Z40: Maltodextrin M-100 IP (Brenntag)
A41: Black Label | B41: 1 | C41: Distributed | D41: Tocobiol SF (BTSA) | E41: {=IF(LOWER(TRIM($C41))="distributed",_xlfn.XLOOKUP($D41,'Cost Master List'!$B:$B,'Cost Master List'!$M:$M,"",0),_xlfn.LET(_xlpm.norm,_xlfn.LAMBDA(_xlpm.x,TRIM(SUBSTITUTE(_xlpm.x,CHAR(160),""))),_xlpm.rng,'Manufactured Items Models'!$B:$BA,_xlpm.rows,{12;24;36;48;60;72;84;96;108},_xlpm.itemCols,{1,7,13,19,25,31,37,43,49},_xlpm.priceCols,_xlpm.itemCols+3,_xlpm.items,INDEX(_xlpm.rng,_xlpm.rows,_xlpm.itemCols),_xlpm.prices,INDEX(_xlpm.rng,_xlpm.rows,_xlpm.priceCols),_xlpm.needle,_xlpm.norm($D41),_xlpm.hit,SUMPRODUCT((_xlpm.norm(_xlpm.items)=_xlpm.needle)*_xlpm.prices),IF(_xlpm.hit=0,"",_xlpm.hit)))} -> 19.413777 | F41: 0 | G41: 0.22157019 | H41: =IF(OR(E41="",G41=""),0,(E41+F41)/(1-G41)) -> 24.939662 | I41: 10000 | J41: =+I41*H41 -> 249396.62 | K41: =+J41*G41 -> 55258.856 | L41: 1 | M41: Quoted | N41: FOB MO | O41: January | P41: Quarterly | Z41: Mystery Box for Beet*
A42: Liber & Co | B42: 0.5 | C42: Distributed | D42: Natural Yellow H1485 (Synthite) | E42: {=IF(LOWER(TRIM($C42))="distributed",_xlfn.XLOOKUP($D42,'Cost Master List'!$B:$B,'Cost Master List'!$M:$M,"",0),_xlfn.LET(_xlpm.norm,_xlfn.LAMBDA(_xlpm.x,TRIM(SUBSTITUTE(_xlpm.x,CHAR(160),""))),_xlpm.rng,'Manufactured Items Models'!$B:$BA,_xlpm.rows,{12;24;36;48;60;72;84;96;108},_xlpm.itemCols,{1,7,13,19,25,31,37,43,49},_xlpm.priceCols,_xlpm.itemCols+3,_xlpm.items,INDEX(_xlpm.rng,_xlpm.rows,_xlpm.itemCols),_xlpm.prices,INDEX(_xlpm.rng,_xlpm.rows,_xlpm.priceCols),_xlpm.needle,_xlpm.norm($D42),_xlpm.hit,SUMPRODUCT((_xlpm.norm(_xlpm.items)=_xlpm.needle)*_xlpm.prices),IF(_xlpm.hit=0,"",_xlpm.hit)))} -> 4.672007 | F42: 0 | G42: 0.6 | H42: =IF(OR(E42="",G42=""),0,(E42+F42)/(1-G42)) -> 11.680017 | I42: 220 | J42: =+I42*H42 -> 2569.6038 | K42: =+J42*G42 -> 1541.7623 | Z42: NaCu Chlorophyll 98% (Nutracean)
A43: Liber & Co | B43: 0.5 | C43: Manufactured | D43: Natural Red C1409 (8) | E43: {=IF(LOWER(TRIM($C43))="distributed",_xlfn.XLOOKUP($D43,'Cost Master List'!$B:$B,'Cost Master List'!$M:$M,"",0),_xlfn.LET(_xlpm.norm,_xlfn.LAMBDA(_xlpm.x,TRIM(SUBSTITUTE(_xlpm.x,CHAR(160),""))),_xlpm.rng,'Manufactured Items Models'!$B:$BA,_xlpm.rows,{12;24;36;48;60;72;84;96;108},_xlpm.itemCols,{1,7,13,19,25,31,37,43,49},_xlpm.priceCols,_xlpm.itemCols+3,_xlpm.items,INDEX(_xlpm.rng,_xlpm.rows,_xlpm.itemCols),_xlpm.prices,INDEX(_xlpm.rng,_xlpm.rows,_xlpm.priceCols),_xlpm.needle,_xlpm.norm($D43),_xlpm.hit,SUMPRODUCT((_xlpm.norm(_xlpm.items)=_xlpm.needle)*_xlpm.prices),IF(_xlpm.hit=0,"",_xlpm.hit)))} -> 8.1301527 | F43: 0 | G43: 0.6 | H43: =IF(OR(E43="",G43=""),0,(E43+F43)/(1-G43)) -> 20.325382 | I43: 450 | J43: =+I43*H43 -> 9146.4218 | K43: =+J43*G43 -> 5487.8531 | Z43: Natural Blue L1300 (Hiche)
A44: Liber & Co | B44: 0.5 | C44: Manufactured | E44: {=IF(LOWER(TRIM($C44))="distributed",_xlfn.XLOOKUP($D44,'Cost Master List'!$B:$B,'Cost Master List'!$M:$M,"",0),_xlfn.LET(_xlpm.norm,_xlfn.LAMBDA(_xlpm.x,TRIM(SUBSTITUTE(_xlpm.x,CHAR(160),""))),_xlpm.rng,'Manufactured Items Models'!$B:$BA,_xlpm.rows,{12;24;36;48;60;72;84;96;108},_xlpm.itemCols,{1,7,13,19,25,31,37,43,49},_xlpm.priceCols,_xlpm.itemCols+3,_xlpm.items,INDEX(_xlpm.rng,_xlpm.rows,_xlpm.itemCols),_xlpm.prices,INDEX(_xlpm.rng,_xlpm.rows,_xlpm.priceCols),_xlpm.needle,_xlpm.norm($D44),_xlpm.hit,SUMPRODUCT((_xlpm.norm(_xlpm.items)=_xlpm.needle)*_xlpm.prices),IF(_xlpm.hit=0,"",_xlpm.hit)))} -> 68.574865 | F44: 0 | H44: =IF(OR(E44="",G44=""),0,(E44+F44)/(1-G44)) -> 0 | Z44: Natural Green J1410 (Cyber Colors)
A45: Pocantico | B45: 0.2 | C45: Distributed | D45: Natural Yellow G1301-N (Cybercolors) | E45: {=IF(LOWER(TRIM($C45))="distributed",_xlfn.XLOOKUP($D45,'Cost Master List'!$B:$B,'Cost Master List'!$M:$M,"",0),_xlfn.LET(_xlpm.norm,_xlfn.LAMBDA(_xlpm.x,TRIM(SUBSTITUTE(_xlpm.x,CHAR(160),""))),_xlpm.rng,'Manufactured Items Models'!$B:$BA,_xlpm.rows,{12;24;36;48;60;72;84;96;108},_xlpm.itemCols,{1,7,13,19,25,31,37,43,49},_xlpm.priceCols,_xlpm.itemCols+3,_xlpm.items,INDEX(_xlpm.rng,_xlpm.rows,_xlpm.itemCols),_xlpm.prices,INDEX(_xlpm.rng,_xlpm.rows,_xlpm.priceCols),_xlpm.needle,_xlpm.norm($D45),_xlpm.hit,SUMPRODUCT((_xlpm.norm(_xlpm.items)=_xlpm.needle)*_xlpm.prices),IF(_xlpm.hit=0,"",_xlpm.hit)))} -> 15.034958 | F45: 0 | G45: 0.4 | H45: =IF(OR(E45="",G45=""),0,(E45+F45)/(1-G45)) -> 25.058264 | Z45: Natural Orange F1333 (AroMoss)
A46: Pocantico | B46: 0.2 | C46: Distributed | D46: Natural Yellow H1385 (Synthite) | E46: {=IF(LOWER(TRIM($C46))="distributed",_xlfn.XLOOKUP($D46,'Cost Master List'!$B:$B,'Cost Master List'!$M:$M,"",0),_xlfn.LET(_xlpm.norm,_xlfn.LAMBDA(_xlpm.x,TRIM(SUBSTITUTE(_xlpm.x,CHAR(160),""))),_xlpm.rng,'Manufactured Items Models'!$B:$BA,_xlpm.rows,{12;24;36;48;60;72;84;96;108},_xlpm.itemCols,{1,7,13,19,25,31,37,43,49},_xlpm.priceCols,_xlpm.itemCols+3,_xlpm.items,INDEX(_xlpm.rng,_xlpm.rows,_xlpm.itemCols),_xlpm.prices,INDEX(_xlpm.rng,_xlpm.rows,_xlpm.priceCols),_xlpm.needle,_xlpm.norm($D46),_xlpm.hit,SUMPRODUCT((_xlpm.norm(_xlpm.items)=_xlpm.needle)*_xlpm.prices),IF(_xlpm.hit=0,"",_xlpm.hit)))} -> 10.947692 | F46: 0 | G46: 0.45 | H46: =IF(OR(E46="",G46=""),0,(E46+F46)/(1-G46)) -> 19.904894 | Z46: Natural Red D1305 (Seneca)
A47: Pocantico | B47: 0.2 | C47: Distributed | D47: Natural Orange F1333 (AroMoss) | E47: {=IF(LOWER(TRIM($C47))="distributed",_xlfn.XLOOKUP($D47,'Cost Master List'!$B:$B,'Cost Master List'!$M:$M,"",0),_xlfn.LET(_xlpm.norm,_xlfn.LAMBDA(_xlpm.x,TRIM(SUBSTITUTE(_xlpm.x,CHAR(160),""))),_xlpm.rng,'Manufactured Items Models'!$B:$BA,_xlpm.rows,{12;24;36;48;60;72;84;96;108},_xlpm.itemCols,{1,7,13,19,25,31,37,43,49},_xlpm.priceCols,_xlpm.itemCols+3,_xlpm.items,INDEX(_xlpm.rng,_xlpm.rows,_xlpm.itemCols),_xlpm.prices,INDEX(_xlpm.rng,_xlpm.rows,_xlpm.priceCols),_xlpm.needle,_xlpm.norm($D47),_xlpm.hit,SUMPRODUCT((_xlpm.norm(_xlpm.items)=_xlpm.needle)*_xlpm.prices),IF(_xlpm.hit=0,"",_xlpm.hit)))} -> 19.69387 | F47: 0 | G47: 0.4 | H47: =IF(OR(E47="",G47=""),0,(E47+F47)/(1-G47)) -> 32.823117 | Z47: Natural Red D1307 (Seneca)
A48: Pocantico | B48: 0.2 | C48: Distributed | D48: Annatto Extract P1315 (IFF) | E48: {=IF(LOWER(TRIM($C48))="distributed",_xlfn.XLOOKUP($D48,'Cost Master List'!$B:$B,'Cost Master List'!$M:$M,"",0),_xlfn.LET(_xlpm.norm,_xlfn.LAMBDA(_xlpm.x,TRIM(SUBSTITUTE(_xlpm.x,CHAR(160),""))),_xlpm.rng,'Manufactured Items Models'!$B:$BA,_xlpm.rows,{12;24;36;48;60;72;84;96;108},_xlpm.itemCols,{1,7,13,19,25,31,37,43,49},_xlpm.priceCols,_xlpm.itemCols+3,_xlpm.items,INDEX(_xlpm.rng,_xlpm.rows,_xlpm.itemCols),_xlpm.prices,INDEX(_xlpm.rng,_xlpm.rows,_xlpm.priceCols),_xlpm.needle,_xlpm.norm($D48),_xlpm.hit,SUMPRODUCT((_xlpm.norm(_xlpm.items)=_xlpm.needle)*_xlpm.prices),IF(_xlpm.hit=0,"",_xlpm.hit)))} -> 26.0952 | F48: 0 | G48: 0.4 | H48: =IF(OR(E48="",G48=""),0,(E48+F48)/(1-G48)) -> 43.492 | Z48: Natural Red O1312 (AroMoss)
D49: Natural Red D1307 (40) | E49: {=IF(LOWER(TRIM($C49))="distributed",_xlfn.XLOOKUP($D49,'Cost Master List'!$B:$B,'Cost Master List'!$M:$M,"",0),_xlfn.LET(_xlpm.norm,_xlfn.LAMBDA(_xlpm.x,TRIM(SUBSTITUTE(_xlpm.x,CHAR(160),""))),_xlpm.rng,'Manufactured Items Models'!$B:$BA,_xlpm.rows,{12;24;36;48;60;72;84;96;108},_xlpm.itemCols,{1,7,13,19,25,31,37,43,49},_xlpm.priceCols,_xlpm.itemCols+3,_xlpm.items,INDEX(_xlpm.rng,_xlpm.rows,_xlpm.itemCols),_xlpm.prices,INDEX(_xlpm.rng,_xlpm.rows,_xlpm.priceCols),_xlpm.needle,_xlpm.norm($D49),_xlpm.hit,SUMPRODUCT((_xlpm.norm(_xlpm.items)=_xlpm.needle)*_xlpm.prices),IF(_xlpm.hit=0,"",_xlpm.hit)))} -> 7.6097008 | F49: 0 | G49: 0.34 | H49: =IF(OR(E49="",G49=""),0,(E49+F49)/(1-G49)) -> 11.52985 | Z49: Natural Red Q1304 (Cyber Colors)
F50: 0 | Z50: Natural Red Q1404 (Cybercolors)
F51: 0 | Z51: Natural Red Q2350 (Cyber Colors)
Z52: Natural Yellow G1301 (Nutracean China)
Z53: Natural Yellow G1301 (Nutracean Slovenia)
Z54: Natural Yellow G1301-N (Cybercolors)
Z55: Natural Yellow G2422 (Black Label)
Z56: Natural Yellow G2422 (Nutracean)
Z57: Natural Yellow G3403 (Cybercolors)
Z58: Natural Yellow H1385 (Maak)
Z59: Natural Yellow H1385 (Synthite)
Z60: Natural Yellow H1485 (Maak)
Z61: Natural Yellow H1485 (Synthite)
Z62: Natural Yellow H2395 (Maak)
Z63: Not Assigned
... Z77: WWI Product Code

Sheet Proforma P&L
A1: Scenario | B1: January | C1: February | D1: March | E1: April | F1: May | G1: June | H1: July | I1: August | J1: September | K1: October | L1: November | M1: December | AA1: January | AB1: 1 | AC1: 0 | AE1: Prob | AF1: Rev | AG1: Cost | AH1: Vol | AI1: Share2026 | AJ1: ShipText | AK1: Pattern | AL1: StartMonth | AM1: PerMonths | AN1: IsSixWeeks | AO1: Occur2026 | AP1: 1 | AQ1: 2 | AR1: 3 | AS1: 4 | AT1: 5 | AU1: 6 | AV1: 7 | AW1: 8 | AX1: 9 | AY1: 10 | AZ1: 11 | BA1: 12 | BB1: Rev_Jan | BC1: Rev_Feb | BD1: Rev_Mar | BE1: Rev_Apr | BF1: Rev_May | BG1: Rev_Jun | BH1: Rev_Jul | BI1: Rev_Aug | BJ1: Rev_Sep | BK1: Rev_Oct | BL1: Rev_Nov | BM1: Rev_Dec | BN1: COGS_Jan | BO1: COGS_Feb | BP1: COGS_Mar | BQ1: COGS_Apr | BR1: COGS_May | BS1: COGS_Jun | BT1: COGS_Jul | BU1: COGS_Aug | BV1: COGS_Sep | BW1: COGS_Oct | BX1: COGS_Nov | BY1: COGS_Dec
A2: 0.85 | AA2: February | AB2: 2 | AC2: 1 | AE2: ='Customer Pricing'!$B2 -> 0.5 | AF2: ='Customer Pricing'!$J2 -> 84649.332 | AG2: ='Customer Pricing'!$E2 -> 3.7782221 | AH2: ='Customer Pricing'!$I2 -> 16000 | AI2: ='Customer Pricing'!$L2 -> 0.9 | AJ2: ='Customer Pricing'!$O2 -> February | AK2: ='Customer Pricing'!$P2 -> Every Month | AL2: {=IF(AJ2="",0, MATCH(LOWER(AJ2), LOWER($AA$1:$AA$12), 0))} -> 2 | AM2: =IF(ISNUMBER(SEARCH("6 week",LOWER($AK2))),0, IF(ISNUMBER(SEARCH("every 2",LOWER($AK2)))+ISNUMBER(SEARCH("bi-month",LOWER($AK2)))+ISNUMBER(SEARCH("bimonth",LOWER($AK2))),2, IF(ISNUMBER(SEARCH("quarter",LOWER($AK2))),3, IF(ISNUMBER(SEARCH("semi",LOWER($AK2))),6, IF(ISNUMBER(SEARCH("annual",LOWER($AK2))),12,1))))) -> 1 | AN2: =ISNUMBER(SEARCH("6 week",LOWER($AK2))) -> FALSE | AO2: =SUM(AP2:BA2) -> 11 | AP2: =IF($AN2, IF(AND(AP$1>=$AL2, ISNUMBER(MATCH(AP$1-$AL2, $AC$1:$AC$8,0))),1,0), IF(AND(AP$1>=$AL2, $AM2>0, MOD(AP$1-$AL2, $AM2)=0),1,0) ) -> 0 | AQ2: =IF($AN2, IF(AND(AQ$1>=$AL2, ISNUMBER(MATCH(AQ$1-$AL2, $AC$1:$AC$8,0))),1,0), IF(AND(AQ$1>=$AL2, $AM2>0, MOD(AQ$1-$AL2, $AM2)=0),1,0) ) -> 1 | AR2: =IF($AN2, IF(AND(AR$1>=$AL2, ISNUMBER(MATCH(AR$1-$AL2, $AC$1:$AC$8,0))),1,0), IF(AND(AR$1>=$AL2, $AM2>0, MOD(AR$1-$AL2, $AM2)=0),1,0) ) -> 1 | AS2: =IF($AN2, IF(AND(AS$1>=$AL2, ISNUMBER(MATCH(AS$1-$AL2, $AC$1:$AC$8,0))),1,0), IF(AND(AS$1>=$AL2, $AM2>0, MOD(AS$1-$AL2, $AM2)=0),1,0) ) -> 1 | AT2: =IF($AN2, IF(AND(AT$1>=$AL2, ISNUMBER(MATCH(AT$1-$AL2, $AC$1:$AC$8,0))),1,0), IF(AND(AT$1>=$AL2, $AM2>0, MOD(AT$1-$AL2, $AM2)=0),1,0) ) -> 1 | AU2: =IF($AN2, IF(AND(AU$1>=$AL2, ISNUMBER(MATCH(AU$1-$AL2, $AC$1:$AC$8,0))),1,0), IF(AND(AU$1>=$AL2, $AM2>0, MOD(AU$1-$AL2, $AM2)=0),1,0) ) -> 1 | AV2: =IF($AN2, IF(AND(AV$1>=$AL2, ISNUMBER(MATCH(AV$1-$AL2, $AC$1:$AC$8,0))),1,0), IF(AND(AV$1>=$AL2, $AM2>0, MOD(AV$1-$AL2, $AM2)=0),1,0) ) -> 1 | AW2: =IF($AN2, IF(AND(AW$1>=$AL2, ISNUMBER(MATCH(AW$1-$AL2, $AC$1:$AC$8,0))),1,0), IF(AND(AW$1>=$AL2, $AM2>0, MOD(AW$1-$AL2, $AM2)=0),1,0) ) -> 1 | ... BA2: =IF($AN2, IF(AND(BA$1>=$AL2, ISNUMBER(MATCH(BA$1-$AL2, $AC$1:$AC$8,0))),1,0), IF(AND(BA$1>=$AL2, $AM2>0, MOD(BA$1-$AL2, $AM2)=0),1,0) ) -> 1 | BB2: =IF($AE2>=$A$2, IF($AO2=0,0, $AF2*$AI2/$AO2 * AP2), 0) -> 0 | BC2: =IF($AE2>=$A$2, IF($AO2=0,0, $AF2*$AI2/$AO2 * AQ2), 0) -> 0 | BD2: =IF($AE2>=$A$2, IF($AO2=0,0, $AF2*$AI2/$AO2 * AR2), 0) -> 0 | BE2: =IF($AE2>=$A$2, IF($AO2=0,0, $AF2*$AI2/$AO2 * AS2), 0) -> 0 | BF2: =IF($AE2>=$A$2, IF($AO2=0,0, $AF2*$AI2/$AO2 * AT2), 0) -> 0 | BG2: =IF($AE2>=$A$2, IF($AO2=0,0, $AF2*$AI2/$AO2 * AU2), 0) -> 0 | BH2: =IF($AE2>=$A$2, IF($AO2=0,0, $AF2*$AI2/$AO2 * AV2), 0) -> 0 | BI2: =IF($AE2>=$A$2, IF($AO2=0,0, $AF2*$AI2/$AO2 * AW2), 0) -> 0 | ... BM2: =IF($AE2>=$A$2, IF($AO2=0,0, $AF2*$AI2/$AO2 * BA2), 0) -> 0 | BN2: =IF($AE2>=$A$2, IF($AO2=0,0, $AG2*$AH2*$AI2/$AO2 * AP2), 0) -> 0 | BO2: =IF($AE2>=$A$2, IF($AO2=0,0, $AG2*$AH2*$AI2/$AO2 * AQ2), 0) -> 0 | BP2: =IF($AE2>=$A$2, IF($AO2=0,0, $AG2*$AH2*$AI2/$AO2 * AR2), 0) -> 0 | BQ2: =IF($AE2>=$A$2, IF($AO2=0,0, $AG2*$AH2*$AI2/$AO2 * AS2), 0) -> 0 | BR2: =IF($AE2>=$A$2, IF($AO2=0,0, $AG2*$AH2*$AI2/$AO2 * AT2), 0) -> 0 | BS2: =IF($AE2>=$A$2, IF($AO2=0,0, $AG2*$AH2*$AI2/$AO2 * AU2), 0) -> 0 | BT2: =IF($AE2>=$A$2, IF($AO2=0,0, $AG2*$AH2*$AI2/$AO2 * AV2), 0) -> 0 | BU2: =IF($AE2>=$A$2, IF($AO2=0,0, $AG2*$AH2*$AI2/$AO2 * AW2), 0) -> 0 | ... BY2: =IF($AE2>=$A$2, IF($AO2=0,0, $AG2*$AH2*$AI2/$AO2 * BA2), 0) -> 0
A3: Revenue | B3: =SUM(BB$2:BB$50) -> 404089.26 | C3: =SUM(BC$2:BC$50) -> 277550.02 | D3: =SUM(BD$2:BD$50) -> 117152.64 | E3: =SUM(BE$2:BE$50) -> 404089.26 | F3: =SUM(BF$2:BF$50) -> 277550.02 | G3: =SUM(BG$2:BG$50) -> 117152.64 | H3: =SUM(BH$2:BH$50) -> 404089.26 | I3: =SUM(BI$2:BI$50) -> 277550.02 | ... M3: =SUM(BM$2:BM$50) -> 117152.64 | O3: =SUM(B3:M3) -> 3195167.7 | AA3: March | AB3: 3 | AC3: 3 | AE3: ='Customer Pricing'!$B3 -> 0.5 | AF3: ='Customer Pricing'!$J3 -> 31750.384 | AG3: ='Customer Pricing'!$E3 -> 26.0952 | AH3: ='Customer Pricing'!$I3 -> 1000 | AI3: ='Customer Pricing'!$L3 -> 1 | AJ3: ='Customer Pricing'!$O3 -> February | AK3: ='Customer Pricing'!$P3 -> Semi-Annual | AL3: {=IF(AJ3="",0, MATCH(LOWER(AJ3), LOWER($AA$1:$AA$12), 0))} -> 2 | AM3: =IF(ISNUMBER(SEARCH("6 week",LOWER($AK3))),0, IF(ISNUMBER(SEARCH("every 2",LOWER($AK3)))+ISNUMBER(SEARCH("bi-month",LOWER($AK3)))+ISNUMBER(SEARCH("bimonth",LOWER($AK3))),2, IF(ISNUMBER(SEARCH("quarter",LOWER($AK3))),3, IF(ISNUMBER(SEARCH("semi",LOWER($AK3))),6, IF(ISNUMBER(SEARCH("annual",LOWER($AK3))),12,1))))) -> 6 | AN3: =ISNUMBER(SEARCH("6 week",LOWER($AK3))) -> FALSE | AO3: =SUM(AP3:BA3) -> 2 | AP3: =IF($AN3, IF(AND(AP$1>=$AL3, ISNUMBER(MATCH(AP$1-$AL3, $AC$1:$AC$8,0))),1,0), IF(AND(AP$1>=$AL3, $AM3>0, MOD(AP$1-$AL3, $AM3)=0),1,0) ) -> 0 | AQ3: =IF($AN3, IF(AND(AQ$1>=$AL3, ISNUMBER(MATCH(AQ$1-$AL3, $AC$1:$AC$8,0))),1,0), IF(AND(AQ$1>=$AL3, $AM3>0, MOD(AQ$1-$AL3, $AM3)=0),1,0) ) -> 1 | AR3: =IF($AN3, IF(AND(AR$1>=$AL3, ISNUMBER(MATCH(AR$1-$AL3, $AC$1:$AC$8,0))),1,0), IF(AND(AR$1>=$AL3, $AM3>0, MOD(AR$1-$AL3, $AM3)=0),1,0) ) -> 0 | AS3: =IF($AN3, IF(AND(AS$1>=$AL3, ISNUMBER(MATCH(AS$1-$AL3, $AC$1:$AC$8,0))),1,0), IF(AND(AS$1>=$AL3, $AM3>0, MOD(AS$1-$AL3, $AM3)=0),1,0) ) -> 0 | AT3: =IF($AN3, IF(AND(AT$1>=$AL3, ISNUMBER(MATCH(AT$1-$AL3, $AC$1:$AC$8,0))),1,0), IF(AND(AT$1>=$AL3, $AM3>0, MOD(AT$1-$AL3, $AM3)=0),1,0) ) -> 0 | AU3: =IF($AN3, IF(AND(AU$1>=$AL3, ISNUMBER(MATCH(AU$1-$AL3, $AC$1:$AC$8,0))),1,0), IF(AND(AU$1>=$AL3, $AM3>0, MOD(AU$1-$AL3, $AM3)=0),1,0) ) -> 0 | AV3: =IF($AN3, IF(AND(AV$1>=$AL3, ISNUMBER(MATCH(AV$1-$AL3, $AC$1:$AC$8,0))),1,0), IF(AND(AV$1>=$AL3, $AM3>0, MOD(AV$1-$AL3, $AM3)=0),1,0) ) -> 0 | AW3: =IF($AN3, IF(AND(AW$1>=$AL3, ISNUMBER(MATCH(AW$1-$AL3, $AC$1:$AC$8,0))),1,0), IF(AND(AW$1>=$AL3, $AM3>0, MOD(AW$1-$AL3, $AM3)=0),1,0) ) -> 1 | ... BA3: =IF($AN3, IF(AND(BA$1>=$AL3, ISNUMBER(MATCH(BA$1-$AL3, $AC$1:$AC$8,0))),1,0), IF(AND(BA$1>=$AL3, $AM3>0, MOD(BA$1-$AL3, $AM3)=0),1,0) ) -> 0 | BB3: =IF($AE3>=$A$2, IF($AO3=0,0, $AF3*$AI3/$AO3 * AP3), 0) -> 0 | BC3: =IF($AE3>=$A$2, IF($AO3=0,0, $AF3*$AI3/$AO3 * AQ3), 0) -> 0 | BD3: =IF($AE3>=$A$2, IF($AO3=0,0, $AF3*$AI3/$AO3 * AR3), 0) -> 0 | BE3: =IF($AE3>=$A$2, IF($AO3=0,0, $AF3*$AI3/$AO3 * AS3), 0) -> 0 | BF3: =IF($AE3>=$A$2, IF($AO3=0,0, $AF3*$AI3/$AO3 * AT3), 0) -> 0 | BG3: =IF($AE3>=$A$2, IF($AO3=0,0, $AF3*$AI3/$AO3 * AU3), 0) -> 0 | BH3: =IF($AE3>=$A$2, IF($AO3=0,0, $AF3*$AI3/$AO3 * AV3), 0) -> 0 | BI3: =IF($AE3>=$A$2, IF($AO3=0,0, $AF3*$AI3/$AO3 * AW3), 0) -> 0 | ... BM3: =IF($AE3>=$A$2, IF($AO3=0,0, $AF3*$AI3/$AO3 * BA3), 0) -> 0 | BN3: =IF($AE3>=$A$2, IF($AO3=0,0, $AG3*$AH3*$AI3/$AO3 * AP3), 0) -> 0 | BO3: =IF($AE3>=$A$2, IF($AO3=0,0, $AG3*$AH3*$AI3/$AO3 * AQ3), 0) -> 0 | BP3: =IF($AE3>=$A$2, IF($AO3=0,0, $AG3*$AH3*$AI3/$AO3 * AR3), 0) -> 0 | BQ3: =IF($AE3>=$A$2, IF($AO3=0,0, $AG3*$AH3*$AI3/$AO3 * AS3), 0) -> 0 | BR3: =IF($AE3>=$A$2, IF($AO3=0,0, $AG3*$AH3*$AI3/$AO3 * AT3), 0) -> 0 | BS3: =IF($AE3>=$A$2, IF($AO3=0,0, $AG3*$AH3*$AI3/$AO3 * AU3), 0) -> 0 | BT3: =IF($AE3>=$A$2, IF($AO3=0,0, $AG3*$AH3*$AI3/$AO3 * AV3), 0) -> 0 | BU3: =IF($AE3>=$A$2, IF($AO3=0,0, $AG3*$AH3*$AI3/$AO3 * AW3), 0) -> 0 | ... BY3: =IF($AE3>=$A$2, IF($AO3=0,0, $AG3*$AH3*$AI3/$AO3 * BA3), 0) -> 0
A4: COGS | B4: =SUM(BN$2:BN$50) -> 287487.21 | C4: =SUM(BO$2:BO$50) -> 186660.27 | D4: =SUM(BP$2:BP$50) -> 80482.593 | E4: =SUM(BQ$2:BQ$50) -> 287487.21 | F4: =SUM(BR$2:BR$50) -> 186660.27 | G4: =SUM(BS$2:BS$50) -> 80482.593 | H4: =SUM(BT$2:BT$50) -> 287487.21 | I4: =SUM(BU$2:BU$50) -> 186660.27 | ... M4: =SUM(BY$2:BY$50) -> 80482.593 | O4: =SUM(B4:M4) -> 2218520.3 | AA4: April | AB4: 4 | AC4: 4 | AE4: ='Customer Pricing'!$B4 -> 0.1 | AF4: ='Customer Pricing'!$J4 -> 0 | AG4: ='Customer Pricing'!$E4 -> 20.375507 | AH4: ='Customer Pricing'!$I4 -> 1600 | AI4: ='Customer Pricing'!$L4 -> 0.5 | AJ4: ='Customer Pricing'!$O4 -> June | AK4: ='Customer Pricing'!$P4 -> Every Other Month | AL4: {=IF(AJ4="",0, MATCH(LOWER(AJ4), LOWER($AA$1:$AA$12), 0))} -> 6 | AM4: =IF(ISNUMBER(SEARCH("6 week",LOWER($AK4))),0, IF(ISNUMBER(SEARCH("every 2",LOWER($AK4)))+ISNUMBER(SEARCH("bi-month",LOWER($AK4)))+ISNUMBER(SEARCH("bimonth",LOWER($AK4))),2, IF(ISNUMBER(SEARCH("quarter",LOWER($AK4))),3, IF(ISNUMBER(SEARCH("semi",LOWER($AK4))),6, IF(ISNUMBER(SEARCH("annual",LOWER($AK4))),12,1))))) -> 1 | AN4: =ISNUMBER(SEARCH("6 week",LOWER($AK4))) -> FALSE | AO4: =SUM(AP4:BA4) -> 7 | AP4: =IF($AN4, IF(AND(AP$1>=$AL4, ISNUMBER(MATCH(AP$1-$AL4, $AC$1:$AC$8,0))),1,0), IF(AND(AP$1>=$AL4, $AM4>0, MOD(AP$1-$AL4, $AM4)=0),1,0) ) -> 0 | AQ4: =IF($AN4, IF(AND(AQ$1>=$AL4, ISNUMBER(MATCH(AQ$1-$AL4, $AC$1:$AC$8,0))),1,0), IF(AND(AQ$1>=$AL4, $AM4>0, MOD(AQ$1-$AL4, $AM4)=0),1,0) ) -> 0 | AR4: =IF($AN4, IF(AND(AR$1>=$AL4, ISNUMBER(MATCH(AR$1-$AL4, $AC$1:$AC$8,0))),1,0), IF(AND(AR$1>=$AL4, $AM4>0, MOD(AR$1-$AL4, $AM4)=0),1,0) ) -> 0 | AS4: =IF($AN4, IF(AND(AS$1>=$AL4, ISNUMBER(MATCH(AS$1-$AL4, $AC$1:$AC$8,0))),1,0), IF(AND(AS$1>=$AL4, $AM4>0, MOD(AS$1-$AL4, $AM4)=0),1,0) ) -> 0 | AT4: =IF($AN4, IF(AND(AT$1>=$AL4, ISNUMBER(MATCH(AT$1-$AL4, $AC$1:$AC$8,0))),1,0), IF(AND(AT$1>=$AL4, $AM4>0, MOD(AT$1-$AL4, $AM4)=0),1,0) ) -> 0 | AU4: =IF($AN4, IF(AND(AU$1>=$AL4, ISNUMBER(MATCH(AU$1-$AL4, $AC$1:$AC$8,0))),1,0), IF(AND(AU$1>=$AL4, $AM4>0, MOD(AU$1-$AL4, $AM4)=0),1,0) ) -> 1 | AV4: =IF($AN4, IF(AND(AV$1>=$AL4, ISNUMBER(MATCH(AV$1-$AL4, $AC$1:$AC$8,0))),1,0), IF(AND(AV$1>=$AL4, $AM4>0, MOD(AV$1-$AL4, $AM4)=0),1,0) ) -> 1 | AW4: =IF($AN4, IF(AND(AW$1>=$AL4, ISNUMBER(MATCH(AW$1-$AL4, $AC$1:$AC$8,0))),1,0), IF(AND(AW$1>=$AL4, $AM4>0, MOD(AW$1-$AL4, $AM4)=0),1,0) ) -> 1 | ... BA4: =IF($AN4, IF(AND(BA$1>=$AL4, ISNUMBER(MATCH(BA$1-$AL4, $AC$1:$AC$8,0))),1,0), IF(AND(BA$1>=$AL4, $AM4>0, MOD(BA$1-$AL4, $AM4)=0),1,0) ) -> 1 | BB4: =IF($AE4>=$A$2, IF($AO4=0,0, $AF4*$AI4/$AO4 * AP4), 0) -> 0 | BC4: =IF($AE4>=$A$2, IF($AO4=0,0, $AF4*$AI4/$AO4 * AQ4), 0) -> 0 | BD4: =IF($AE4>=$A$2, IF($AO4=0,0, $AF4*$AI4/$AO4 * AR4), 0) -> 0 | BE4: =IF($AE4>=$A$2, IF($AO4=0,0, $AF4*$AI4/$AO4 * AS4), 0) -> 0 | BF4: =IF($AE4>=$A$2, IF($AO4=0,0, $AF4*$AI4/$AO4 * AT4), 0) -> 0 | BG4: =IF($AE4>=$A$2, IF($AO4=0,0, $AF4*$AI4/$AO4 * AU4), 0) -> 0 | BH4: =IF($AE4>=$A$2, IF($AO4=0,0, $AF4*$AI4/$AO4 * AV4), 0) -> 0 | BI4: =IF($AE4>=$A$2, IF($AO4=0,0, $AF4*$AI4/$AO4 * AW4), 0) -> 0 | ... BM4: =IF($AE4>=$A$2, IF($AO4=0,0, $AF4*$AI4/$AO4 * BA4), 0) -> 0 | BN4: =IF($AE4>=$A$2, IF($AO4=0,0, $AG4*$AH4*$AI4/$AO4 * AP4), 0) -> 0 | BO4: =IF($AE4>=$A$2, IF($AO4=0,0, $AG4*$AH4*$AI4/$AO4 * AQ4), 0) -> 0 | BP4: =IF($AE4>=$A$2, IF($AO4=0,0, $AG4*$AH4*$AI4/$AO4 * AR4), 0) -> 0 | BQ4: =IF($AE4>=$A$2, IF($AO4=0,0, $AG4*$AH4*$AI4/$AO4 * AS4), 0) -> 0 | BR4: =IF($AE4>=$A$2, IF($AO4=0,0, $AG4*$AH4*$AI4/$AO4 * AT4), 0) -> 0 | BS4: =IF($AE4>=$A$2, IF($AO4=0,0, $AG4*$AH4*$AI4/$AO4 * AU4), 0) -> 0 | BT4: =IF($AE4>=$A$2, IF($AO4=0,0, $AG4*$AH4*$AI4/$AO4 * AV4), 0) -> 0 | BU4: =IF($AE4>=$A$2, IF($AO4=0,0, $AG4*$AH4*$AI4/$AO4 * AW4), 0) -> 0 | ... BY4: =IF($AE4>=$A$2, IF($AO4=0,0, $AG4*$AH4*$AI4/$AO4 * BA4), 0) -> 0
A5: Gross Profit | B5: =+B3-B4 -> 116602.05 | C5: =+C3-C4 -> 90889.749 | D5: =+D3-D4 -> 36670.047 | E5: =+E3-E4 -> 116602.05 | F5: =+F3-F4 -> 90889.749 | G5: =+G3-G4 -> 36670.047 | H5: =+H3-H4 -> 116602.05 | I5: =+I3-I4 -> 90889.749 | ... M5: =+M3-M4 -> 36670.047 | O5: =SUM(B5:M5) -> 976647.38 | P5: =O5/O3 -> 0.30566389 | AA5: May | AB5: 5 | AC5: 6 | AE5: ='Customer Pricing'!$B5 -> 0.6 | AF5: ='Customer Pricing'!$J5 -> 34360.01 | AG5: ='Customer Pricing'!$E5 -> 18.115126 | AH5: ='Customer Pricing'!$I5 -> 1000 | AI5: ='Customer Pricing'!$L5 -> 1 | AJ5: ='Customer Pricing'!$O5 -> March | AK5: ='Customer Pricing'!$P5 -> Quarterly | AL5: {=IF(AJ5="",0, MATCH(LOWER(AJ5), LOWER($AA$1:$AA$12), 0))} -> 3 | AM5: =IF(ISNUMBER(SEARCH("6 week",LOWER($AK5))),0, IF(ISNUMBER(SEARCH("every 2",LOWER($AK5)))+ISNUMBER(SEARCH("bi-month",LOWER($AK5)))+ISNUMBER(SEARCH("bimonth",LOWER($AK5))),2, IF(ISNUMBER(SEARCH("quarter",LOWER($AK5))),3, IF(ISNUMBER(SEARCH("semi",LOWER($AK5))),6, IF(ISNUMBER(SEARCH("annual",LOWER($AK5))),12,1))))) -> 3 | AN5: =ISNUMBER(SEARCH("6 week",LOWER($AK5))) -> FALSE | AO5: =SUM(AP5:BA5) -> 4 | AP5: =IF($AN5, IF(AND(AP$1>=$AL5, ISNUMBER(MATCH(AP$1-$AL5, $AC$1:$AC$8,0))),1,0), IF(AND(AP$1>=$AL5, $AM5>0, MOD(AP$1-$AL5, $AM5)=0),1,0) ) -> 0 | AQ5: =IF($AN5, IF(AND(AQ$1>=$AL5, ISNUMBER(MATCH(AQ$1-$AL5, $AC$1:$AC$8,0))),1,0), IF(AND(AQ$1>=$AL5, $AM5>0, MOD(AQ$1-$AL5, $AM5)=0),1,0) ) -> 0 | AR5: =IF($AN5, IF(AND(AR$1>=$AL5, ISNUMBER(MATCH(AR$1-$AL5, $AC$1:$AC$8,0))),1,0), IF(AND(AR$1>=$AL5, $AM5>0, MOD(AR$1-$AL5, $AM5)=0),1,0) ) -> 1 | AS5: =IF($AN5, IF(AND(AS$1>=$AL5, ISNUMBER(MATCH(AS$1-$AL5, $AC$1:$AC$8,0))),1,0), IF(AND(AS$1>=$AL5, $AM5>0, MOD(AS$1-$AL5, $AM5)=0),1,0) ) -> 0 | AT5: =IF($AN5, IF(AND(AT$1>=$AL5, ISNUMBER(MATCH(AT$1-$AL5, $AC$1:$AC$8,0))),1,0), IF(AND(AT$1>=$AL5, $AM5>0, MOD(AT$1-$AL5, $AM5)=0),1,0) ) -> 0 | AU5: =IF($AN5, IF(AND(AU$1>=$AL5, ISNUMBER(MATCH(AU$1-$AL5, $AC$1:$AC$8,0))),1,0), IF(AND(AU$1>=$AL5, $AM5>0, MOD(AU$1-$AL5, $AM5)=0),1,0) ) -> 1 | AV5: =IF($AN5, IF(AND(AV$1>=$AL5, ISNUMBER(MATCH(AV$1-$AL5, $AC$1:$AC$8,0))),1,0), IF(AND(AV$1>=$AL5, $AM5>0, MOD(AV$1-$AL5, $AM5)=0),1,0) ) -> 0 | AW5: =IF($AN5, IF(AND(AW$1>=$AL5, ISNUMBER(MATCH(AW$1-$AL5, $AC$1:$AC$8,0))),1,0), IF(AND(AW$1>=$AL5, $AM5>0, MOD(AW$1-$AL5, $AM5)=0),1,0) ) -> 0 | ... BA5: =IF($AN5, IF(AND(BA$1>=$AL5, ISNUMBER(MATCH(BA$1-$AL5, $AC$1:$AC$8,0))),1,0), IF(AND(BA$1>=$AL5, $AM5>0, MOD(BA$1-$AL5, $AM5)=0),1,0) ) -> 1 | BB5: =IF($AE5>=$A$2, IF($AO5=0,0, $AF5*$AI5/$AO5 * AP5), 0) -> 0 | BC5: =IF($AE5>=$A$2, IF($AO5=0,0, $AF5*$AI5/$AO5 * AQ5), 0) -> 0 | BD5: =IF($AE5>=$A$2, IF($AO5=0,0, $AF5*$AI5/$AO5 * AR5), 0) -> 0 | BE5: =IF($AE5>=$A$2, IF($AO5=0,0, $AF5*$AI5/$AO5 * AS5), 0) -> 0 | BF5: =IF($AE5>=$A$2, IF($AO5=0,0, $AF5*$AI5/$AO5 * AT5), 0) -> 0 | BG5: =IF($AE5>=$A$2, IF($AO5=0,0, $AF5*$AI5/$AO5 * AU5), 0) -> 0 | BH5: =IF($AE5>=$A$2, IF($AO5=0,0, $AF5*$AI5/$AO5 * AV5), 0) -> 0 | BI5: =IF($AE5>=$A$2, IF($AO5=0,0, $AF5*$AI5/$AO5 * AW5), 0) -> 0 | ... BM5: =IF($AE5>=$A$2, IF($AO5=0,0, $AF5*$AI5/$AO5 * BA5), 0) -> 0 | BN5: =IF($AE5>=$A$2, IF($AO5=0,0, $AG5*$AH5*$AI5/$AO5 * AP5), 0) -> 0 | BO5: =IF($AE5>=$A$2, IF($AO5=0,0, $AG5*$AH5*$AI5/$AO5 * AQ5), 0) -> 0 | BP5: =IF($AE5>=$A$2, IF($AO5=0,0, $AG5*$AH5*$AI5/$AO5 * AR5), 0) -> 0 | BQ5: =IF($AE5>=$A$2, IF($AO5=0,0, $AG5*$AH5*$AI5/$AO5 * AS5), 0) -> 0 | BR5: =IF($AE5>=$A$2, IF($AO5=0,0, $AG5*$AH5*$AI5/$AO5 * AT5), 0) -> 0 | BS5: =IF($AE5>=$A$2, IF($AO5=0,0, $AG5*$AH5*$AI5/$AO5 * AU5), 0) -> 0 | BT5: =IF($AE5>=$A$2, IF($AO5=0,0, $AG5*$AH5*$AI5/$AO5 * AV5), 0) -> 0 | BU5: =IF($AE5>=$A$2, IF($AO5=0,0, $AG5*$AH5*$AI5/$AO5 * AW5), 0) -> 0 | ... BY5: =IF($AE5>=$A$2, IF($AO5=0,0, $AG5*$AH5*$AI5/$AO5 * BA5), 0) -> 0
O6: =SUM(B6:M6) -> 0 | AA6: June | AB6: 6 | AC6: 7 | AE6: ='Customer Pricing'!$B6 -> 0 | AF6: ='Customer Pricing'!$J6 -> 0 | AG6: ='Customer Pricing'!$E6 -> 39.444965 | AH6: ='Customer Pricing'!$I6 -> 0 | AI6: ='Customer Pricing'!$L6 -> 0 | AJ6: ='Customer Pricing'!$O6 -> 0 | AK6: ='Customer Pricing'!$P6 -> 0 | AL6: {=IF(AJ6="",0, MATCH(LOWER(AJ6), LOWER($AA$1:$AA$12), 0))} -> #N/A | AM6: =IF(ISNUMBER(SEARCH("6 week",LOWER($AK6))),0, IF(ISNUMBER(SEARCH("every 2",LOWER($AK6)))+ISNUMBER(SEARCH("bi-month",LOWER($AK6)))+ISNUMBER(SEARCH("bimonth",LOWER($AK6))),2, IF(ISNUMBER(SEARCH("quarter",LOWER($AK6))),3, IF(ISNUMBER(SEARCH("semi",LOWER($AK6))),6, IF(ISNUMBER(SEARCH("annual",LOWER($AK6))),12,1))))) -> 1 | AN6: =ISNUMBER(SEARCH("6 week",LOWER($AK6))) -> FALSE | AO6: =SUM(AP6:BA6) -> #N/A | AP6: =IF($AN6, IF(AND(AP$1>=$AL6, ISNUMBER(MATCH(AP$1-$AL6, $AC$1:$AC$8,0))),1,0), IF(AND(AP$1>=$AL6, $AM6>0, MOD(AP$1-$AL6, $AM6)=0),1,0) ) -> #N/A | AQ6: =IF($AN6, IF(AND(AQ$1>=$AL6, ISNUMBER(MATCH(AQ$1-$AL6, $AC$1:$AC$8,0))),1,0), IF(AND(AQ$1>=$AL6, $AM6>0, MOD(AQ$1-$AL6, $AM6)=0),1,0) ) -> #N/A | AR6: =IF($AN6, IF(AND(AR$1>=$AL6, ISNUMBER(MATCH(AR$1-$AL6, $AC$1:$AC$8,0))),1,0), IF(AND(AR$1>=$AL6, $AM6>0, MOD(AR$1-$AL6, $AM6)=0),1,0) ) -> #N/A | AS6: =IF($AN6, IF(AND(AS$1>=$AL6, ISNUMBER(MATCH(AS$1-$AL6, $AC$1:$AC$8,0))),1,0), IF(AND(AS$1>=$AL6, $AM6>0, MOD(AS$1-$AL6, $AM6)=0),1,0) ) -> #N/A | AT6: =IF($AN6, IF(AND(AT$1>=$AL6, ISNUMBER(MATCH(AT$1-$AL6, $AC$1:$AC$8,0))),1,0), IF(AND(AT$1>=$AL6, $AM6>0, MOD(AT$1-$AL6, $AM6)=0),1,0) ) -> #N/A | AU6: =IF($AN6, IF(AND(AU$1>=$AL6, ISNUMBER(MATCH(AU$1-$AL6, $AC$1:$AC$8,0))),1,0), IF(AND(AU$1>=$AL6, $AM6>0, MOD(AU$1-$AL6, $AM6)=0),1,0) ) -> #N/A | AV6: =IF($AN6, IF(AND(AV$1>=$AL6, ISNUMBER(MATCH(AV$1-$AL6, $AC$1:$AC$8,0))),1,0), IF(AND(AV$1>=$AL6, $AM6>0, MOD(AV$1-$AL6, $AM6)=0),1,0) ) -> #N/A | AW6: =IF($AN6, IF(AND(AW$1>=$AL6, ISNUMBER(MATCH(AW$1-$AL6, $AC$1:$AC$8,0))),1,0), IF(AND(AW$1>=$AL6, $AM6>0, MOD(AW$1-$AL6, $AM6)=0),1,0) ) -> #N/A | ... BA6: =IF($AN6, IF(AND(BA$1>=$AL6, ISNUMBER(MATCH(BA$1-$AL6, $AC$1:$AC$8,0))),1,0), IF(AND(BA$1>=$AL6, $AM6>0, MOD(BA$1-$AL6, $AM6)=0),1,0) ) -> #N/A | BB6: =IF($AE6>=$A$2, IF($AO6=0,0, $AF6*$AI6/$AO6 * AP6), 0) -> 0 | BC6: =IF($AE6>=$A$2, IF($AO6=0,0, $AF6*$AI6/$AO6 * AQ6), 0) -> 0 | BD6: =IF($AE6>=$A$2, IF($AO6=0,0, $AF6*$AI6/$AO6 * AR6), 0) -> 0 | BE6: =IF($AE6>=$A$2, IF($AO6=0,0, $AF6*$AI6/$AO6 * AS6), 0) -> 0 | BF6: =IF($AE6>=$A$2, IF($AO6=0,0, $AF6*$AI6/$AO6 * AT6), 0) -> 0 | BG6: =IF($AE6>=$A$2, IF($AO6=0,0, $AF6*$AI6/$AO6 * AU6), 0) -> 0 | BH6: =IF($AE6>=$A$2, IF($AO6=0,0, $AF6*$AI6/$AO6 * AV6), 0) -> 0 | BI6: =IF($AE6>=$A$2, IF($AO6=0,0, $AF6*$AI6/$AO6 * AW6), 0) -> 0 | ... BM6: =IF($AE6>=$A$2, IF($AO6=0,0, $AF6*$AI6/$AO6 * BA6), 0) -> 0 | BN6: =IF($AE6>=$A$2, IF($AO6=0,0, $AG6*$AH6*$AI6/$AO6 * AP6), 0) -> 0 | BO6: =IF($AE6>=$A$2, IF($AO6=0,0, $AG6*$AH6*$AI6/$AO6 * AQ6), 0) -> 0 | BP6: =IF($AE6>=$A$2, IF($AO6=0,0, $AG6*$AH6*$AI6/$AO6 * AR6), 0) -> 0 | BQ6: =IF($AE6>=$A$2, IF($AO6=0,0, $AG6*$AH6*$AI6/$AO6 * AS6), 0) -> 0 | BR6: =IF($AE6>=$A$2, IF($AO6=0,0, $AG6*$AH6*$AI6/$AO6 * AT6), 0) -> 0 | BS6: =IF($AE6>=$A$2, IF($AO6=0,0, $AG6*$AH6*$AI6/$AO6 * AU6), 0) -> 0 | BT6: =IF($AE6>=$A$2, IF($AO6=0,0, $AG6*$AH6*$AI6/$AO6 * AV6), 0) -> 0 | BU6: =IF($AE6>=$A$2, IF($AO6=0,0, $AG6*$AH6*$AI6/$AO6 * AW6), 0) -> 0 | ... BY6: =IF($AE6>=$A$2, IF($AO6=0,0, $AG6*$AH6*$AI6/$AO6 * BA6), 0) -> 0
A7: Op-Ex | B7: =+'Operating Expenses'!B34 -> 14315 | C7: =+'Operating Expenses'!C34 -> 19135 | D7: =+'Operating Expenses'!D34 -> 33150 | E7: =+'Operating Expenses'!E34 -> 33965 | F7: =+'Operating Expenses'!F34 -> 39465 | G7: =+'Operating Expenses'!G34 -> 39515 | H7: =+'Operating Expenses'!H34 -> 115565 | I7: =+'Operating Expenses'!I34 -> 38540 | ... M7: =+'Operating Expenses'!M34 -> 36165 | O7: =SUM(B7:M7) -> 483660 | AA7: July | AB7: 7 | AC7: 9 | AE7: ='Customer Pricing'!$B7 -> 1 | AF7: ='Customer Pricing'!$J7 -> 430044.24 | AG7: ='Customer Pricing'!$E7 -> 7.6097008 | AH7: ='Customer Pricing'!$I7 -> 47000 | AI7: ='Customer Pricing'!$L7 -> 1 | AJ7: ='Customer Pricing'!$O7 -> January | AK7: ='Customer Pricing'!$P7 -> Every Month | AL7: {=IF(AJ7="",0, MATCH(LOWER(AJ7), LOWER($AA$1:$AA$12), 0))} -> 1 | AM7: =IF(ISNUMBER(SEARCH("6 week",LOWER($AK7))),0, IF(ISNUMBER(SEARCH("every 2",LOWER($AK7)))+ISNUMBER(SEARCH("bi-month",LOWER($AK7)))+ISNUMBER(SEARCH("bimonth",LOWER($AK7))),2, IF(ISNUMBER(SEARCH("quarter",LOWER($AK7))),3, IF(ISNUMBER(SEARCH("semi",LOWER($AK7))),6, IF(ISNUMBER(SEARCH("annual",LOWER($AK7))),12,1))))) -> 1 | AN7: =ISNUMBER(SEARCH("6 week",LOWER($AK7))) -> FALSE | AO7: =SUM(AP7:BA7) -> 12 | AP7: =IF($AN7, IF(AND(AP$1>=$AL7, ISNUMBER(MATCH(AP$1-$AL7, $AC$1:$AC$8,0))),1,0), IF(AND(AP$1>=$AL7, $AM7>0, MOD(AP$1-$AL7, $AM7)=0),1,0) ) -> 1 | AQ7: =IF($AN7, IF(AND(AQ$1>=$AL7, ISNUMBER(MATCH(AQ$1-$AL7, $AC$1:$AC$8,0))),1,0), IF(AND(AQ$1>=$AL7, $AM7>0, MOD(AQ$1-$AL7, $AM7)=0),1,0) ) -> 1 | AR7: =IF($AN7, IF(AND(AR$1>=$AL7, ISNUMBER(MATCH(AR$1-$AL7, $AC$1:$AC$8,0))),1,0), IF(AND(AR$1>=$AL7, $AM7>0, MOD(AR$1-$AL7, $AM7)=0),1,0) ) -> 1 | AS7: =IF($AN7, IF(AND(AS$1>=$AL7, ISNUMBER(MATCH(AS$1-$AL7, $AC$1:$AC$8,0))),1,0), IF(AND(AS$1>=$AL7, $AM7>0, MOD(AS$1-$AL7, $AM7)=0),1,0) ) -> 1 | AT7: =IF($AN7, IF(AND(AT$1>=$AL7, ISNUMBER(MATCH(AT$1-$AL7, $AC$1:$AC$8,0))),1,0), IF(AND(AT$1>=$AL7, $AM7>0, MOD(AT$1-$AL7, $AM7)=0),1,0) ) -> 1 | AU7: =IF($AN7, IF(AND(AU$1>=$AL7, ISNUMBER(MATCH(AU$1-$AL7, $AC$1:$AC$8,0))),1,0), IF(AND(AU$1>=$AL7, $AM7>0, MOD(AU$1-$AL7, $AM7)=0),1,0) ) -> 1 | AV7: =IF($AN7, IF(AND(AV$1>=$AL7, ISNUMBER(MATCH(AV$1-$AL7, $AC$1:$AC$8,0))),1,0), IF(AND(AV$1>=$AL7, $AM7>0, MOD(AV$1-$AL7, $AM7)=0),1,0) ) -> 1 | AW7: =IF($AN7, IF(AND(AW$1>=$AL7, ISNUMBER(MATCH(AW$1-$AL7, $AC$1:$AC$8,0))),1,0), IF(AND(AW$1>=$AL7, $AM7>0, MOD(AW$1-$AL7, $AM7)=0),1,0) ) -> 1 | ... BA7: =IF($AN7, IF(AND(BA$1>=$AL7, ISNUMBER(MATCH(BA$1-$AL7, $AC$1:$AC$8,0))),1,0), IF(AND(BA$1>=$AL7, $AM7>0, MOD(BA$1-$AL7, $AM7)=0),1,0) ) -> 1 | BB7: =IF($AE7>=$A$2, IF($AO7=0,0, $AF7*$AI7/$AO7 * AP7), 0) -> 35837.02 | BC7: =IF($AE7>=$A$2, IF($AO7=0,0, $AF7*$AI7/$AO7 * AQ7), 0) -> 35837.02 | BD7: =IF($AE7>=$A$2, IF($AO7=0,0, $AF7*$AI7/$AO7 * AR7), 0) -> 35837.02 | BE7: =IF($AE7>=$A$2, IF($AO7=0,0, $AF7*$AI7/$AO7 * AS7), 0) -> 35837.02 | BF7: =IF($AE7>=$A$2, IF($AO7=0,0, $AF7*$AI7/$AO7 * AT7), 0) -> 35837.02 | BG7: =IF($AE7>=$A$2, IF($AO7=0,0, $AF7*$AI7/$AO7 * AU7), 0) -> 35837.02 | BH7: =IF($AE7>=$A$2, IF($AO7=0,0, $AF7*$AI7/$AO7 * AV7), 0) -> 35837.02 | BI7: =IF($AE7>=$A$2, IF($AO7=0,0, $AF7*$AI7/$AO7 * AW7), 0) -> 35837.02 | ... BM7: =IF($AE7>=$A$2, IF($AO7=0,0, $AF7*$AI7/$AO7 * BA7), 0) -> 35837.02 | BN7: =IF($AE7>=$A$2, IF($AO7=0,0, $AG7*$AH7*$AI7/$AO7 * AP7), 0) -> 29804.661 | BO7: =IF($AE7>=$A$2, IF($AO7=0,0, $AG7*$AH7*$AI7/$AO7 * AQ7), 0) -> 29804.661 | BP7: =IF($AE7>=$A$2, IF($AO7=0,0, $AG7*$AH7*$AI7/$AO7 * AR7), 0) -> 29804.661 | BQ7: =IF($AE7>=$A$2, IF($AO7=0,0, $AG7*$AH7*$AI7/$AO7 * AS7), 0) -> 29804.661 | BR7: =IF($AE7>=$A$2, IF($AO7=0,0, $AG7*$AH7*$AI7/$AO7 * AT7), 0) -> 29804.661 | BS7: =IF($AE7>=$A$2, IF($AO7=0,0, $AG7*$AH7*$AI7/$AO7 * AU7), 0) -> 29804.661 | BT7: =IF($AE7>=$A$2, IF($AO7=0,0, $AG7*$AH7*$AI7/$AO7 * AV7), 0) -> 29804.661 | BU7: =IF($AE7>=$A$2, IF($AO7=0,0, $AG7*$AH7*$AI7/$AO7 * AW7), 0) -> 29804.661 | ... BY7: =IF($AE7>=$A$2, IF($AO7=0,0, $AG7*$AH7*$AI7/$AO7 * BA7), 0) -> 29804.661
A8: EBITDA | B8: =+B5-B7 -> 102287.05 | C8: =+C5-C7 -> 71754.749 | D8: =+D5-D7 -> 3520.0467 | E8: =+E5-E7 -> 82637.049 | F8: =+F5-F7 -> 51424.749 | G8: =+G5-G7 -> -2844.9533 | H8: =+H5-H7 -> 1037.0489 | I8: =+I5-I7 -> 52349.749 | ... M8: =+M5-M7 -> 505.04675 | O8: =SUM(B8:M8) -> 492987.38 | AA8: August | AB8: 8 | AC8: 10 | AE8: ='Customer Pricing'!$B8 -> 1 | AF8: ='Customer Pricing'!$J8 -> 32690.255 | AG8: ='Customer Pricing'!$E8 -> 21.384184 | AH8: ='Customer Pricing'!$I8 -> 1000 | AI8: ='Customer Pricing'!$L8 -> 1 | AJ8: ='Customer Pricing'!$O8 -> January | AK8: ='Customer Pricing'!$P8 -> Every 6 Weeks | AL8: {=IF(AJ8="",0, MATCH(LOWER(AJ8), LOWER($AA$1:$AA$12), 0))} -> 1 | AM8: =IF(ISNUMBER(SEARCH("6 week",LOWER($AK8))),0, IF(ISNUMBER(SEARCH("every 2",LOWER($AK8)))+ISNUMBER(SEARCH("bi-month",LOWER($AK8)))+ISNUMBER(SEARCH("bimonth",LOWER($AK8))),2, IF(ISNUMBER(SEARCH("quarter",LOWER($AK8))),3, IF(ISNUMBER(SEARCH("semi",LOWER($AK8))),6, IF(ISNUMBER(SEARCH("annual",LOWER($AK8))),12,1))))) -> 0 | AN8: =ISNUMBER(SEARCH("6 week",LOWER($AK8))) -> TRUE | AO8: =SUM(AP8:BA8) -> 8 | AP8: =IF($AN8, IF(AND(AP$1>=$AL8, ISNUMBER(MATCH(AP$1-$AL8, $AC$1:$AC$8,0))),1,0), IF(AND(AP$1>=$AL8, $AM8>0, MOD(AP$1-$AL8, $AM8)=0),1,0) ) -> 1 | AQ8: =IF($AN8, IF(AND(AQ$1>=$AL8, ISNUMBER(MATCH(AQ$1-$AL8, $AC$1:$AC$8,0))),1,0), IF(AND(AQ$1>=$AL8, $AM8>0, MOD(AQ$1-$AL8, $AM8)=0),1,0) ) -> 1 | AR8: =IF($AN8, IF(AND(AR$1>=$AL8, ISNUMBER(MATCH(AR$1-$AL8, $AC$1:$AC$8,0))),1,0), IF(AND(AR$1>=$AL8, $AM8>0, MOD(AR$1-$AL8, $AM8)=0),1,0) ) -> 0 | AS8: =IF($AN8, IF(AND(AS$1>=$AL8, ISNUMBER(MATCH(AS$1-$AL8, $AC$1:$AC$8,0))),1,0), IF(AND(AS$1>=$AL8, $AM8>0, MOD(AS$1-$AL8, $AM8)=0),1,0) ) -> 1 | AT8: =IF($AN8, IF(AND(AT$1>=$AL8, ISNUMBER(MATCH(AT$1-$AL8, $AC$1:$AC$8,0))),1,0), IF(AND(AT$1>=$AL8, $AM8>0, MOD(AT$1-$AL8, $AM8)=0),1,0) ) -> 1 | AU8: =IF($AN8, IF(AND(AU$1>=$AL8, ISNUMBER(MATCH(AU$1-$AL8, $AC$1:$AC$8,0))),1,0), IF(AND(AU$1>=$AL8, $AM8>0, MOD(AU$1-$AL8, $AM8)=0),1,0) ) -> 0 | AV8: =IF($AN8, IF(AND(AV$1>=$AL8, ISNUMBER(MATCH(AV$1-$AL8, $AC$1:$AC$8,0))),1,0), IF(AND(AV$1>=$AL8, $AM8>0, MOD(AV$1-$AL8, $AM8)=0),1,0) ) -> 1 | AW8: =IF($AN8, IF(AND(AW$1>=$AL8, ISNUMBER(MATCH(AW$1-$AL8, $AC$1:$AC$8,0))),1,0), IF(AND(AW$1>=$AL8, $AM8>0, MOD(AW$1-$AL8, $AM8)=0),1,0) ) -> 1 | ... BA8: =IF($AN8, IF(AND(BA$1>=$AL8, ISNUMBER(MATCH(BA$1-$AL8, $AC$1:$AC$8,0))),1,0), IF(AND(BA$1>=$AL8, $AM8>0, MOD(BA$1-$AL8, $AM8)=0),1,0) ) -> 0 | BB8: =IF($AE8>=$A$2, IF($AO8=0,0, $AF8*$AI8/$AO8 * AP8), 0) -> 4086.2819 | BC8: =IF($AE8>=$A$2, IF($AO8=0,0, $AF8*$AI8/$AO8 * AQ8), 0) -> 4086.2819 | BD8: =IF($AE8>=$A$2, IF($AO8=0,0, $AF8*$AI8/$AO8 * AR8), 0) -> 0 | BE8: =IF($AE8>=$A$2, IF($AO8=0,0, $AF8*$AI8/$AO8 * AS8), 0) -> 4086.2819 | BF8: =IF($AE8>=$A$2, IF($AO8=0,0, $AF8*$AI8/$AO8 * AT8), 0) -> 4086.2819 | BG8: =IF($AE8>=$A$2, IF($AO8=0,0, $AF8*$AI8/$AO8 * AU8), 0) -> 0 | BH8: =IF($AE8>=$A$2, IF($AO8=0,0, $AF8*$AI8/$AO8 * AV8), 0) -> 4086.2819 | BI8: =IF($AE8>=$A$2, IF($AO8=0,0, $AF8*$AI8/$AO8 * AW8), 0) -> 4086.2819 | ... BM8: =IF($AE8>=$A$2, IF($AO8=0,0, $AF8*$AI8/$AO8 * BA8), 0) -> 0 | BN8: =IF($AE8>=$A$2, IF($AO8=0,0, $AG8*$AH8*$AI8/$AO8 * AP8), 0) -> 2673.023 | BO8: =IF($AE8>=$A$2, IF($AO8=0,0, $AG8*$AH8*$AI8/$AO8 * AQ8), 0) -> 2673.023 | BP8: =IF($AE8>=$A$2, IF($AO8=0,0, $AG8*$AH8*$AI8/$AO8 * AR8), 0) -> 0 | BQ8: =IF($AE8>=$A$2, IF($AO8=0,0, $AG8*$AH8*$AI8/$AO8 * AS8), 0) -> 2673.023 | BR8: =IF($AE8>=$A$2, IF($AO8=0,0, $AG8*$AH8*$AI8/$AO8 * AT8), 0) -> 2673.023 | BS8: =IF($AE8>=$A$2, IF($AO8=0,0, $AG8*$AH8*$AI8/$AO8 * AU8), 0) -> 0 | BT8: =IF($AE8>=$A$2, IF($AO8=0,0, $AG8*$AH8*$AI8/$AO8 * AV8), 0) -> 2673.023 | BU8: =IF($AE8>=$A$2, IF($AO8=0,0, $AG8*$AH8*$AI8/$AO8 * AW8), 0) -> 2673.023 | ... BY8: =IF($AE8>=$A$2, IF($AO8=0,0, $AG8*$AH8*$AI8/$AO8 * BA8), 0) -> 0
A9: Interest Paid | B9: =-+'Cash Flow Analysis'!B6 -> 1291.6667 | C9: =+'Cash Flow Analysis'!C6 -> -2486.4583 | D9: =+'Cash Flow Analysis'!D6 -> -1646.875 | E9: =+'Cash Flow Analysis'!E6 -> -807.29167 | F9: =+'Cash Flow Analysis'!F6 -> -1808.3333 | G9: =+'Cash Flow Analysis'!G6 -> -1291.6667 | H9: =+'Cash Flow Analysis'!H6 -> -613.54167 | I9: =+'Cash Flow Analysis'!I6 -> -2228.125 | J9: =+'Cash Flow Analysis'!J6 -> -1646.875 | ... M9: =+'Cash Flow Analysis'!M6 -> -1356.25 | O9: =SUM(B9:M9) -> -15306.25 | AA9: September | AB9: 9 | AE9: ='Customer Pricing'!$B9 -> 0.6 | AF9: ='Customer Pricing'!$J9 -> 160502 | AG9: ='Customer Pricing'!$E9 -> 34.906242 | AH9: ='Customer Pricing'!$I9 -> 3000 | AI9: ='Customer Pricing'!$L9 -> 1 | AJ9: ='Customer Pricing'!$O9 -> February | AK9: ='Customer Pricing'!$P9 -> Every 6 Weeks | AL9: {=IF(AJ9="",0, MATCH(LOWER(AJ9), LOWER($AA$1:$AA$12), 0))} -> 2 | AM9: =IF(ISNUMBER(SEARCH("6 week",LOWER($AK9))),0, IF(ISNUMBER(SEARCH("every 2",LOWER($AK9)))+ISNUMBER(SEARCH("bi-month",LOWER($AK9)))+ISNUMBER(SEARCH("bimonth",LOWER($AK9))),2, IF(ISNUMBER(SEARCH("quarter",LOWER($AK9))),3, IF(ISNUMBER(SEARCH("semi",LOWER($AK9))),6, IF(ISNUMBER(SEARCH("annual",LOWER($AK9))),12,1))))) -> 0 | AN9: =ISNUMBER(SEARCH("6 week",LOWER($AK9))) -> TRUE | AO9: =SUM(AP9:BA9) -> 8 | AP9: =IF($AN9, IF(AND(AP$1>=$AL9, ISNUMBER(MATCH(AP$1-$AL9, $AC$1:$AC$8,0))),1,0), IF(AND(AP$1>=$AL9, $AM9>0, MOD(AP$1-$AL9, $AM9)=0),1,0) ) -> 0 | AQ9: =IF($AN9, IF(AND(AQ$1>=$AL9, ISNUMBER(MATCH(AQ$1-$AL9, $AC$1:$AC$8,0))),1,0), IF(AND(AQ$1>=$AL9, $AM9>0, MOD(AQ$1-$AL9, $AM9)=0),1,0) ) -> 1 | AR9: =IF($AN9, IF(AND(AR$1>=$AL9, ISNUMBER(MATCH(AR$1-$AL9, $AC$1:$AC$8,0))),1,0), IF(AND(AR$1>=$AL9, $AM9>0, MOD(AR$1-$AL9, $AM9)=0),1,0) ) -> 1 | AS9: =IF($AN9, IF(AND(AS$1>=$AL9, ISNUMBER(MATCH(AS$1-$AL9, $AC$1:$AC$8,0))),1,0), IF(AND(AS$1>=$AL9, $AM9>0, MOD(AS$1-$AL9, $AM9)=0),1,0) ) -> 0 | AT9: =IF($AN9, IF(AND(AT$1>=$AL9, ISNUMBER(MATCH(AT$1-$AL9, $AC$1:$AC$8,0))),1,0), IF(AND(AT$1>=$AL9, $AM9>0, MOD(AT$1-$AL9, $AM9)=0),1,0) ) -> 1 | AU9: =IF($AN9, IF(AND(AU$1>=$AL9, ISNUMBER(MATCH(AU$1-$AL9, $AC$1:$AC$8,0))),1,0), IF(AND(AU$1>=$AL9, $AM9>0, MOD(AU$1-$AL9, $AM9)=0),1,0) ) -> 1 | AV9: =IF($AN9, IF(AND(AV$1>=$AL9, ISNUMBER(MATCH(AV$1-$AL9, $AC$1:$AC$8,0))),1,0), IF(AND(AV$1>=$AL9, $AM9>0, MOD(AV$1-$AL9, $AM9)=0),1,0) ) -> 0 | AW9: =IF($AN9, IF(AND(AW$1>=$AL9, ISNUMBER(MATCH(AW$1-$AL9, $AC$1:$AC$8,0))),1,0), IF(AND(AW$1>=$AL9, $AM9>0, MOD(AW$1-$AL9, $AM9)=0),1,0) ) -> 1 | ... BA9: =IF($AN9, IF(AND(BA$1>=$AL9, ISNUMBER(MATCH(BA$1-$AL9, $AC$1:$AC$8,0))),1,0), IF(AND(BA$1>=$AL9, $AM9>0, MOD(BA$1-$AL9, $AM9)=0),1,0) ) -> 1 | BB9: =IF($AE9>=$A$2, IF($AO9=0,0, $AF9*$AI9/$AO9 * AP9), 0) -> 0 | BC9: =IF($AE9>=$A$2, IF($AO9=0,0, $AF9*$AI9/$AO9 * AQ9), 0) -> 0 | BD9: =IF($AE9>=$A$2, IF($AO9=0,0, $AF9*$AI9/$AO9 * AR9), 0) -> 0 | BE9: =IF($AE9>=$A$2, IF($AO9=0,0, $AF9*$AI9/$AO9 * AS9), 0) -> 0 | BF9: =IF($AE9>=$A$2, IF($AO9=0,0, $AF9*$AI9/$AO9 * AT9), 0) -> 0 | BG9: =IF($AE9>=$A$2, IF($AO9=0,0, $AF9*$AI9/$AO9 * AU9), 0) -> 0 | BH9: =IF($AE9>=$A$2, IF($AO9=0,0, $AF9*$AI9/$AO9 * AV9), 0) -> 0 | BI9: =IF($AE9>=$A$2, IF($AO9=0,0, $AF9*$AI9/$AO9 * AW9), 0) -> 0 | ... BM9: =IF($AE9>=$A$2, IF($AO9=0,0, $AF9*$AI9/$AO9 * BA9), 0) -> 0 | BN9: =IF($AE9>=$A$2, IF($AO9=0,0, $AG9*$AH9*$AI9/$AO9 * AP9), 0) -> 0 | BO9: =IF($AE9>=$A$2, IF($AO9=0,0, $AG9*$AH9*$AI9/$AO9 * AQ9), 0) -> 0 | BP9: =IF($AE9>=$A$2, IF($AO9=0,0, $AG9*$AH9*$AI9/$AO9 * AR9), 0) -> 0 | BQ9: =IF($AE9>=$A$2, IF($AO9=0,0, $AG9*$AH9*$AI9/$AO9 * AS9), 0) -> 0 | BR9: =IF($AE9>=$A$2, IF($AO9=0,0, $AG9*$AH9*$AI9/$AO9 * AT9), 0) -> 0 | BS9: =IF($AE9>=$A$2, IF($AO9=0,0, $AG9*$AH9*$AI9/$AO9 * AU9), 0) -> 0 | BT9: =IF($AE9>=$A$2, IF($AO9=0,0, $AG9*$AH9*$AI9/$AO9 * AV9), 0) -> 0 | BU9: =IF($AE9>=$A$2, IF($AO9=0,0, $AG9*$AH9*$AI9/$AO9 * AW9), 0) -> 0 | ... BY9: =IF($AE9>=$A$2, IF($AO9=0,0, $AG9*$AH9*$AI9/$AO9 * BA9), 0) -> 0
